Workbook
Name MATRIZ1: #REF!
Name MATRIZ1: #REF!
Name MATRIZ1: #REF!
Name MATRIZ2: #REF!
Name MATRIZ2: #REF!
Name MATRIZ2: #REF!
Name MATRIZ3: #REF!
Name MATRIZ3: #REF!
Name MATRIZ3: #REF!
Name MATRIZ4: #REF!
Name MATRIZ4: #REF!
Name MATRIZ4: #REF!
Name Q: #REF!
Name Q: #REF!
Name Q: #REF!
Name S: #REF!
Name S: #REF!
Name S: #REF!

Sheet COT. BSII, CF. 300, CF. 400
B1: {=+CELL("nombrearchivo")} -> C:\Users\fcola\Desktop\APPACCURATEK\[excel de prueba.xlsx]CUBICACION
B2: PRESUPUESTO:
B3: OBRA: | C3: TORRE KENEDY
B4: PRODUCTO: | C4: CAFCO 400
B5: ING. A CARGO: | O5: m²/bolsa
N6: Cafco 300 | O6: =+CUBICACION!Q4/E25 -> #DIV/0!
B7: RESUMEN | F7: RESUMEN | N7: Cafco 400 | O7: =+CUBICACION!Q3/E26 -> #DIV/0!
I8: =+I19/C9 -> 0.84988234 | J8: uf/m2 | N8: Blaze Shield II | O8: =+CUBICACION!Q2/E27 -> 2.0607611
B9: SUPERFICIE 1 | C9: =+SUM(CUBICACION!Q2:Q4) -> 1696.0064 | D9: m2 | F9: VALOR UF | G9: 40830 | H9: $ | I9: =+G19/C9 -> 34700.696 | J9: $/m2
B11: SUPERFICIE CAFCO 400 | C11: =+CUBICACION!Q3 -> 0 | D11: m2 | F11: VALOR DOLLAR | G11: 980 | H11: $ | K11: 0.35 | L11: Margen mat
B13: Rendimiento BSII/DIA | C13: 45 | D13: Bl/dia | F13: COSTO | G13: =+I111 -> 38254192 | H13: $ | I13: =+G13/G9 -> 936.91383 | J13: UF | K13: 0.35 | L13: Margen MOI | N13: 346.6 | O13: 0.328 | P13: =O13*N13 -> 113.6848
B15: Rendimiento CAFCO/DIA | C15: 35 | D15: Bl/dia | F15: MARGEN DE VENTA | G15: =+K112 -> 0.35 | H15: % | I15: =+G15 -> 0.35 | J15: % | K15: 0.35 | L15: Margen MOD | O15: 0.118 | P15: =O15*N13 -> 40.8988
B17: Rendimiento M2/BL | D17: m2/bl | F17: MARGEN DE VENTA | G17: =+G19-G13 -> 20598411 | H17: $ | I17: =+G17/G9 -> 504.49206 | J17: UF | K17: 0.35 | L17: Margen Equipos | O17: 0.087 | P17: =O17*N13 -> 30.1542
F19: PRECIO DE VENTA | G19: =+K111 -> 58852602 | H19: $ | I19: =+G19/G9 -> 1441.4059 | J19: UF | K19: 0.35 | L19: Margen GG | O19: =O13+O15+O17 -> 0.533 | P19: =P13+P15+P17 -> 184.7378
P21: =N13*O19 -> 184.7378
B22: ÍTEM Nº | C22: Descripcion | D22: Unidad | E22: Cantidad | F22: Costo Unitario | G22: Costo Total | H22: PERDIDA (%) | I22: Costo Total C/Perdida | J22: INCIDENCIA (%) | K22: Precio de Venta | M22: CUADRO DE OFERTA PARA CARTA
M23: Descripción | N23: Superficie m2 | O23: UF/m2 | P23: Total P.U. (UF) | Q23: %
B24: 1 | C24: MATERIALES | D24: =SUM(J25:J31) -> 0.57511998 | M24: Materiales Directos | N24: =+C9 -> 1696.0064 | O24: =+P24/N24 -> 0.48878432 | P24: =+Q24*P27 -> 828.98133 | Q24: =+D24 -> 0.57511998
B25: 1.1 | C25: Cafco 300 | D25: Bolsas | E25: =+CUBICACION!R4 -> 0 | F25: =16.75*G11*1.5 -> 24622.5 | G25: =+F25*E25 -> 0 | H25: 0.05 | I25: =+(G25*H25)+G25 -> 0 | J25: =I25/$I$111 -> 0 | K25: =+I25/(1-$K$11) -> 0 | M25: Mano de obra Directa e Indirecta | N25: =+N24 -> 1696.0064 | O25: =+P25/N25 -> 0.10262454 | P25: =+Q25*P27 -> 174.05188 | Q25: =+D33+D41 -> 0.12075147
B26: 1.2 | C26: Cafco 400 | D26: Bolsas | E26: =+CUBICACION!R3 -> 0 | F26: 26000 | G26: =+F26*E26 -> 0 | H26: 0.05 | I26: =+(G26*H26)+G26 -> 0 | J26: =I26/$I$111 -> 0 | K26: =+I26/(1-$K$11) -> 0 | M26: Gastos Generales | N26: =+N25 -> 1696.0064 | O26: =+P26/N26 -> 0.25847348 | P26: =+Q26*P27 -> 438.37267 | Q26: =+D48+D57+D66+D74+D81+D89+D96+D108 -> 0.30412854
B27: 1.3 | C27: Blaze Shield II | D27: Bolsas | E27: =+ROUNDUP(CUBICACION!R2,0) -> 823 | F27: 25000 | G27: =+F27*E27 -> 20575000 | H27: 0.03 | I27: =+(G27*H27)+G27 -> 21192250 | J27: =I27/$I$111 -> 0.55398505 | K27: =+I27/(1-$K$11) -> 32603462 | M27: Total | N27: =+N26 -> 1696.0064 | O27: =+SUM(O24:O26) -> 0.84988234 | P27: =+I19 -> 1441.4059
B28: 1.4 | C28: Quik Set | D28: tineta | E28: =+ROUNDUP(E25/19,0) -> 0 | F28: =21.5*G11*1.5 -> 31605 | G28: =+F28*E28 -> 0 | H28: 0.05 | I28: =+(G28*H28)+G28 -> 0 | J28: =I28/$I$111 -> 0 | K28: =+I28/(1-$K$11) -> 0
B29: 1.5 | C29: MALLA | D29: M2 | E29: 0 | F29: =32967/50 -> 659.34 | G29: =+F29*E29 -> 0 | H29: 0.05 | I29: =+(G29*H29)+G29 -> 0 | J29: =I29/$I$111 -> 0 | K29: =+I29/(1-$K$11) -> 0
B30: 1.6 | C30: Bond Seal | D30: tineta | E30: =ROUNDUP(+(E27/4)*2/19,0) -> 22 | F30: 35000 | G30: =+F30*E30 -> 770000 | H30: 0.05 | I30: =+(G30*H30)+G30 -> 808500 | J30: =I30/$I$111 -> 0.021134939 | K30: =+I30/(1-$K$11) -> 1243846.2
B31: 1.7 | C31: SHIPPING | D31: UNI. | E31: 0 | F31: =4500*G11 -> 4410000 | G31: =+F31*E31 -> 0 | H31: 0.05 | I31: =+(G31*H31)+G31 -> 0 | J31: =I31/$I$111 -> 0 | K31: =+I31/(1-$K$11) -> 0
L32: BLAZE SHIELD II | M32: Descripción | N32: Superficie m2 | O32: UF/m2 | P32: Total P.U. (UF) | Q32: =+I27/($I$25+$I$26+$I$27) -> 1
B33: 2 | C33: MANO DE OBRA INDIRECTA | D33: =SUM(J34:J37) -> 0.047547731 | M33: Materiales Directos | N33: =+N36 -> 1696.0064 | O33: =+P33/N33 -> 0.48878432 | P33: =+Q32*P24 -> 828.98133 | Q33: =+E27/($E$25+$E$26+$E$27) -> 1
B34: 2.1 | C34: HD Instalacion de Faena | D34: HD | E34: 1 | I34: =+(G34*H34)+G34 -> 0 | J34: =I34/$I$111 -> 0 | K34: =+I34/(1-$K$13) -> 0 | M34: Mano de obra Directa e Indirecta | N34: =+N36 -> 1696.0064 | O34: =+P34/N34 -> 0.10262454 | P34: =+Q33*P25 -> 174.05188
B35: 2.2 | C35: HD induccion | D35: HD | E35: 1 | I35: =+(G35*H35)+G35 -> 0 | J35: =I35/$I$111 -> 0 | K35: =+I35/(1-$K$13) -> 0 | M35: Gastos Generales | N35: =+N36 -> 1696.0064 | O35: =+P35/N35 -> 0.25847348 | P35: =+Q33*P26 -> 438.37267
B36: 2.3 | C36: Supervisión 100% tiempo efectivo | D36: HD | E36: =+ROUNDUP((($E$25/$C$15+$E$26/$C$15+$E$27/$C$13)/$E$41)+$E$34+$E$35,0) -> 21 | F36: =75900 -> 75900 | G36: =+F36*E36 -> 1593900 | I36: =+(G36*H36)+G36 -> 1593900 | J36: =I36/$I$111 -> 0.041666022 | K36: =+I36/(1-$K$13) -> 2452153.8 | M36: Total | N36: =+CUBICACION!Q2 -> 1696.0064 | O36: =+SUM(O33:O35) -> 0.84988234 | P36: =+SUM(P33:P35) -> 1441.4059
B37: 2.4 | C37: Prevencionista 15% tiempo efectivo | D37: HD | E37: 3 | F37: 75000 | G37: =+F37*E37 -> 225000 | I37: =+(G37*H37)+G37 -> 225000 | J37: =I37/$I$111 -> 0.0058817084 | K37: =+I37/(1-$K$13) -> 346153.85 | L37: CAFCO 400
M38: Descripción | N38: Superficie m2 | O38: UF/m2 | P38: Total P.U. (UF) | Q38: =+I26/($I$25+$I$26+$I$27) -> 0
C39: DURACIÓN OBRA | D39: HD | E39: =+ROUNDUP((($E$25/$C$15+$E$26/$C$15+$E$27/$C$13)/$E$41)+$E$34+$E$35,0) -> 21 | M39: Materiales Directos | N39: =+N42 -> 0 | O39: =+P39/N39 -> #DIV/0! | P39: =+Q38*P24 -> 0 | Q39: =+E26/($E$25+$E$26+$E$27) -> 0
M40: Mano de obra Directa e Indirecta | N40: =+N42 -> 0 | O40: =+P40/N40 -> #DIV/0! | P40: =+Q39*P25 -> 0
B41: 3 | C41: MANO DE OBRA DIRECTA | D41: =SUM(J42:J46) -> 0.073203743 | E41: 1 | F41: Cantidad de equipos | H41: 0.05 | I41: Fondo de reserva | M41: Gastos Generales | N41: =+N42 -> 0 | O41: =+P41/N41 -> #DIV/0! | P41: =+Q39*P26 -> 0
B42: 3.1 | C42: Aplicadores | D42: HD | E42: =ROUNDUP($E$36,0) -> 21 | F42: 45000 | G42: =+F42*E42*$E$41 -> 945000 | H42: =+$H$41 -> 0.05 | I42: =+(G42*H42)+G42 -> 992250 | J42: =I42/$I$111 -> 0.025938334 | K42: =+I42/(1-$K$15) -> 1526538.5 | L42: CAFCO 300 | M42: Total | N42: =+CUBICACION!Q3 -> 0 | O42: =+SUM(O39:O41) -> #DIV/0! | P42: =+SUM(P39:P41) -> 0
B43: 3.3 | C43: Maquinistas | D43: HD | E43: =ROUNDUP($E$36,0) -> 21 | F43: 42000 | G43: =+F43*E43*$E$41 -> 882000 | H43: =+$H$41 -> 0.05 | I43: =+(G43*H43)+G43 -> 926100 | J43: =I43/$I$111 -> 0.024209112 | K43: =+I43/(1-$K$15) -> 1424769.2
B44: 3.5 | C44: Ayudante de Aplicador | D44: HD | E44: =ROUNDUP($E$36,0) -> 21 | F44: 40000 | G44: =+F44*E44*$E$41 -> 840000 | H44: =+$H$41 -> 0.05 | I44: =+(G44*H44)+G44 -> 882000 | J44: =I44/$I$111 -> 0.023056297 | K44: =+I44/(1-$K$15) -> 1356923.1 | M44: Descripción | N44: Superficie m2 | O44: UF/m2 | P44: Total P.U. (UF) | Q44: =+I25/($I$25+$I$26+$I$27) -> 0
B45: 3.7 | C45: Mallero | D45: HD | F45: =33000 -> 33000 | G45: =+F45*E45*$E$41 -> 0 | H45: =+$H$41 -> 0.05 | I45: =+(G45*H45)+G45 -> 0 | J45: =I45/$I$111 -> 0 | K45: =+I45/(1-$K$15) -> 0 | M45: Materiales Directos | N45: =+N48 -> 0 | O45: =+P45/N45 -> #DIV/0! | P45: =+Q44*P24 -> 0 | Q45: =+E25/($E$25+$E$26+$E$27) -> 0
B46: 3.9 | C46: Pintor SBK 113 | D46: HD | E46: 0 | F46: 40000 | G46: =+F46*E46*$E$41 -> 0 | H46: =+$H$41 -> 0.05 | I46: =+(G46*H46)+G46 -> 0 | J46: =I46/$I$111 -> 0 | K46: =+I46/(1-$K$15) -> 0 | M46: Mano de obra Directa e Indirecta | N46: =+N48 -> 0 | O46: =+P46/N46 -> #DIV/0! | P46: =+Q45*P25 -> 0
M47: Gastos Generales | N47: =+N48 -> 0 | O47: =+P47/N47 -> #DIV/0! | P47: =+Q45*P26 -> 0
B48: 4 | C48: GG VIAJES (ida y vuelta) | D48: =SUM(J49:J55) -> 0.10456371 | E48: Valor asignado | F48: 200000 | M48: Total | N48: =+CUBICACION!Q4 -> 0 | O48: =+SUM(O45:O47) -> #DIV/0! | P48: =+SUM(P45:P47) -> 0
B49: 4.1 | C49: Supervisión 100% tiempo efectivo | D49: HD | E49: =+IF($F$48>0,ROUNDUP(E36/5,0),0) -> 5 | F49: =$F$48 -> 200000 | G49: =+F49*E49 -> 1000000 | H49: 0 | I49: =+(G49*H49)+G49 -> 1000000 | J49: =I49/$I$111 -> 0.026140926 | K49: =+I49/(1-$K$19) -> 1538461.5
B50: 5.2 | C50: Prevencionista de Riesgo | D50: HD | E50: 0 | F50: =$F$48 -> 200000 | G50: =+F50*E50 -> 0 | H50: 0 | I50: =+(G50*H50)+G50 -> 0 | J50: =I50/$I$111 -> 0 | K50: =+I50/(1-$K$19) -> 0
B51: 4.2 | C51: Aplicadores | D51: HD | E51: =+IF($F$48>0,ROUNDUP(E42/5,0),0) -> 5 | F51: =$F$48 -> 200000 | G51: =+F51*E51 -> 1000000 | H51: 0 | I51: =+(G51*H51)+G51 -> 1000000 | J51: =I51/$I$111 -> 0.026140926 | K51: =+I51/(1-$K$19) -> 1538461.5
B52: 4.3 | C52: Maquinistas | D52: HD | E52: =+IF($F$48>0,ROUNDUP(E43/5,0),0) -> 5 | F52: =$F$48 -> 200000 | G52: =+F52*E52 -> 1000000 | H52: 0 | I52: =+(G52*H52)+G52 -> 1000000 | J52: =I52/$I$111 -> 0.026140926 | K52: =+I52/(1-$K$19) -> 1538461.5
B53: 4.4 | C53: Ayudante de Aplicador | D53: HD | E53: =+IF($F$48>0,ROUNDUP(E44/5,0),0) -> 5 | F53: =$F$48 -> 200000 | G53: =+F53*E53 -> 1000000 | H53: 0 | I53: =+(G53*H53)+G53 -> 1000000 | J53: =I53/$I$111 -> 0.026140926 | K53: =+I53/(1-$K$19) -> 1538461.5
B54: 4.5 | C54: Mallero | D54: HD | F54: =$F$48 -> 200000 | G54: =+F54*E54 -> 0 | H54: 0 | I54: =+(G54*H54)+G54 -> 0 | J54: =I54/$I$111 -> 0 | K54: =+I54/(1-$K$19) -> 0
B55: 4.6 | C55: Pintor SBK 113 | D55: HD | F55: =$F$48 -> 200000 | G55: =+F55*E55 -> 0 | H55: 0 | I55: =+(G55*H55)+G55 -> 0 | J55: =I55/$I$111 -> 0 | K55: =+I55/(1-$K$19) -> 0
B57: 5 | C57: GG TRASLADOS INTERNOS (nocturnos +colaciones) | D57: =SUM(J58:J64) -> 0 | E57: Valor asignado | F57: 0
B58: 5.1 | C58: Supervisor | D58: Unid | E58: =E36 -> 21 | F58: =F57 -> 0 | G58: =+F58*E58 -> 0 | H58: 0 | I58: =+(G58*H58)+G58 -> 0 | J58: =I58/$I$111 -> 0 | K58: =+I58/(1-$K$19) -> 0
B59: 5.2 | C59: Prevencionista de Riesgo | D59: Unid | E59: 0 | F59: =F57 -> 0 | G59: =+F59*E59 -> 0 | H59: 0 | I59: =+(G59*H59)+G59 -> 0 | J59: =I59/$I$111 -> 0 | K59: =+I59/(1-$K$19) -> 0
B60: 5.3 | C60: Administrador /oficina técnica | D60: Unid | F60: =F57 -> 0 | G60: =+F60*E60 -> 0 | H60: 0 | I60: =+(G60*H60)+G60 -> 0 | J60: =I60/$I$111 -> 0 | K60: =+I60/(1-$K$19) -> 0
B61: 5.4 | C61: Aplicador | D61: Unid | E61: =$E$39 -> 21 | F61: =+F57 -> 0 | G61: =+F61*E61 -> 0 | H61: 0 | I61: =+(G61*H61)+G61 -> 0 | J61: =I61/$I$111 -> 0 | K61: =+I61/(1-$K$19) -> 0
B62: 5.5 | C62: Ayudante | D62: Unid | E62: =$E$39 -> 21 | F62: =+F57 -> 0 | G62: =+F62*E62 -> 0 | H62: 0 | I62: =+(G62*H62)+G62 -> 0 | J62: =I62/$I$111 -> 0 | K62: =+I62/(1-$K$19) -> 0
B63: 5.6 | C63: Maquinista | D63: Unid | E63: =$E$39 -> 21 | F63: =+F57 -> 0 | G63: =+F63*E63 -> 0 | H63: 0 | I63: =+(G63*H63)+G63 -> 0 | J63: =I63/$I$111 -> 0 | K63: =+I63/(1-$K$19) -> 0
B64: 5.7 | C64: pintor sbk 113 | D64: Unid | E64: =$E$39 -> 21 | F64: =+F57 -> 0 | G64: =+F64*E64 -> 0 | H64: 0 | I64: =+(G64*H64)+G64 -> 0 | J64: =I64/$I$111 -> 0 | K64: =+I64/(1-$K$19) -> 0
B66: 6 | C66: GG VIATICO | D66: =SUM(J67:J72) -> 0.063130337 | E66: Valor asignado | F66: 28000
B67: 6.1 | C67: =+C58 -> Supervisor | D67: día | E67: =+IF($F$48>0,E36,0) -> 21 | F67: =$F$66+3000 -> 31000 | G67: =+F67*E67 -> 651000 | H67: 0 | I67: =+(G67*H67)+G67 -> 651000 | J67: =I67/$I$111 -> 0.017017743 | K67: =+I67/(1-$K$19) -> 1001538.5
B68: 6.2 | C68: =+C59 -> Prevencionista de Riesgo | D68: día | E68: 0 | F68: =$F$66 -> 28000 | G68: =+F68*E68 -> 0 | H68: 0 | I68: =+(G68*H68)+G68 -> 0 | J68: =I68/$I$111 -> 0 | K68: =+I68/(1-$K$19) -> 0
B69: 6.4 | C69: =+C61 -> Aplicador | D69: día | E69: =+IF($F$48>0,E42*$E$41,0) -> 21 | F69: =$F$66 -> 28000 | G69: =+F69*E69 -> 588000 | H69: 0 | I69: =+(G69*H69)+G69 -> 588000 | J69: =I69/$I$111 -> 0.015370865 | K69: =+I69/(1-$K$19) -> 904615.38
B70: 6.5 | C70: =+C62 -> Ayudante | D70: día | E70: =+IF($F$48>0,E44*$E$41,0) -> 21 | F70: =$F$66 -> 28000 | G70: =+F70*E70 -> 588000 | H70: 0 | I70: =+(G70*H70)+G70 -> 588000 | J70: =I70/$I$111 -> 0.015370865 | K70: =+I70/(1-$K$19) -> 904615.38
B71: 6.6 | C71: =+C63 -> Maquinista | D71: día | E71: =+IF($F$48>0,E43*$E$41,0) -> 21 | F71: =$F$66 -> 28000 | G71: =+F71*E71 -> 588000 | H71: 0 | I71: =+(G71*H71)+G71 -> 588000 | J71: =I71/$I$111 -> 0.015370865 | K71: =+I71/(1-$K$19) -> 904615.38
B72: 6.7 | C72: Pintor SBK 113 | D72: día | E72: =+IF($F$48>0,E46*$E$41,0) -> 0 | F72: =$F$66 -> 28000 | G72: =+F72*E72 -> 0 | H72: 0 | I72: =+(G72*H72)+G72 -> 0 | J72: =I72/$I$111 -> 0 | K72: =+I72/(1-$K$19) -> 0
B74: 7 | C74: GG TRASLADOS | D74: =SUM(J75:J79) -> 0.10665498
B75: 7.1 | C75: Flete material | D75: unid | E75: =+E26/76+1 -> 1 | F75: 1200000 | G75: =+F75*E75 -> 1200000 | H75: 0 | I75: =+(G75*H75)+G75 -> 1200000 | J75: =I75/$I$111 -> 0.031369112 | K75: =+I75/(1-$K$19) -> 1846153.8
B76: 7.2 | C76: Flete Contenedor | D76: unid | E76: 0 | F76: 300000 | G76: =+F76*E76 -> 0 | H76: 0 | I76: =+(G76*H76)+G76 -> 0 | J76: =I76/$I$111 -> 0 | K76: =+I76/(1-$K$19) -> 0
B77: 7.3 | C77: Flete Elevador | D77: unid | E77: 0 | F77: 150000 | G77: =+F77*E77 -> 0 | H77: 0 | I77: =+(G77*H77)+G77 -> 0 | J77: =I77/$I$111 -> 0 | K77: =+I77/(1-$K$19) -> 0
B78: 7.5 | C78: Arriendo camioneta C/combustible | D78: días | E78: =E39 -> 21 | F78: 80000 | G78: =+F78*E78 -> 1680000 | H78: 0 | I78: =+(G78*H78)+G78 -> 1680000 | J78: =I78/$I$111 -> 0.043916756 | K78: =+I78/(1-$K$19) -> 2584615.4
B79: 7.6 | C79: Flete retorno | D79: unid | E79: 1 | F79: 1200000 | G79: =+F79*E79 -> 1200000 | H79: 0 | I79: =+(G79*H79)+G79 -> 1200000 | J79: =I79/$I$111 -> 0.031369112 | K79: =+I79/(1-$K$19) -> 1846153.8
B81: 8 | C81: MAQUINARIA Y EQUIPOS | D81: =SUM(J82:J87) -> 0.0053784956
B82: 8.1 | C82: Amortización de máquina de aplicación | D82: CLP$/bolsa | E82: 0.01 | F82: =+G25+G26+G27 -> 20575000 | G82: =+F82*E82 -> 205750 | H82: 0 | I82: =+(G82*H82)+G82 -> 205750 | J82: =I82/$I$111 -> 0.0053784956 | K82: =+I82/(1-$K$17) -> 316538.46
B83: 8.2 | C83: Sistema de elevacion , brazo articulado | D83: mes | E83: 0 | F83: 1200000 | G83: =+F83*E83 -> 0 | H83: 0 | I83: =+(G83*H83)+G83 -> 0 | J83: =I83/$I$111 -> 0 | K83: =+I83/(1-$K$17) -> 0
B84: 8.3 | C84: Petroleo sistema de elevacion | D84: lt/dia | E84: 0 | F84: =(8*8)*38*500 -> 1216000 | G84: =+F84*E84 -> 0 | H84: 0 | I84: =+(G84*H84)+G84 -> 0 | J84: =I84/$I$111 -> 0 | K84: =+I84/(1-$K$17) -> 0
B85: 8.4 | C85: Pistola Hilti y mantencion | D85: Global | E85: 0 | F85: 3000000 | G85: =+F85*E85 -> 0 | H85: 0 | I85: =+(G85*H85)+G85 -> 0 | J85: =I85/$I$111 -> 0 | K85: =+I85/(1-$K$17) -> 0
B86: 8.5 | C86: Airles Pte adherente | D86: dias | E86: 0 | F86: 1000000 | G86: =+F86*E86 -> 0 | H86: 0 | I86: =+(G86*H86)+G86 -> 0 | J86: =I86/$I$111 -> 0 | K86: =+I86/(1-$K$17) -> 0
B87: 8.6 | C87: Andamios | D87: dias | I87: =+(G87*H87)+G87 -> 0 | J87: =I87/$I$111 -> 0 | K87: =+I87/(1-$K$17) -> 0
B89: 9 | C89: GG INSTALACION DE FAENA | D89: =SUM(J90:J94) -> 0
B90: 9.1 | C90: Contenedor oficina tecnica | D90: mes | E90: 0 | F90: 250000 | G90: =+F90*E90 -> 0 | H90: 0 | I90: =+(G90*H90)+G90 -> 0 | J90: =I90/$I$111 -> 0 | K90: =+I90/(1-$K$19) -> 0
B91: 9.2 | C91: Contenedor camarines y duchas | D91: mes | E91: 0 | F91: 132000 | G91: =+F91*E91 -> 0 | H91: 0 | I91: =+(G91*H91)+G91 -> 0 | J91: =I91/$I$111 -> 0 | K91: =+I91/(1-$K$19) -> 0
B92: 9.3 | C92: Caseta Vestidor | D92: mes | E92: 0 | F92: 132000 | G92: =+F92*E92 -> 0 | H92: 0 | I92: =+(G92*H92)+G92 -> 0 | J92: =I92/$I$111 -> 0 | K92: =+I92/(1-$K$19) -> 0
B93: 9.4 | C93: Baños Quimicos | D93: mes | E93: 0 | F93: 156000 | G93: =+F93*E93 -> 0 | H93: 0 | I93: =+(G93*H93)+G93 -> 0 | J93: =I93/$I$111 -> 0 | K93: =+I93/(1-$K$19) -> 0
B94: 9.5 | C94: Contenedor Bodega | D94: mes | E94: 0 | F94: 150000 | G94: =+F94*E94 -> 0 | H94: 0 | I94: =+(G94*H94)+G94 -> 0 | J94: =I94/$I$111 -> 0 | K94: =+I94/(1-$K$19) -> 0
B96: 10 | C96: GG | D96: =SUM(J97:J106) -> 0.014704271
B97: 10.1 | C97: Tape | D97: un | E97: 10 | F97: 1000 | G97: =+F97*E97 -> 10000 | H97: 0 | I97: =+(G97*H97)+G97 -> 10000 | J97: =I97/$I$111 -> 0.00026140926 | K97: =+I97/(1-$K$19) -> 15384.615
B98: 10.2 | C98: Escobillones | D98: un | E98: 10 | F98: 2000 | G98: =+F98*E98 -> 20000 | H98: 0 | I98: =+(G98*H98)+G98 -> 20000 | J98: =I98/$I$111 -> 0.00052281853 | K98: =+I98/(1-$K$19) -> 30769.231
B99: 10.3 | C99: Varios, caja chica 6 días | D99: sem | E99: =(ROUNDUP(E36/5,0)*E41) -> 5 | F99: 60000 | G99: =+F99*E99 -> 300000 | H99: 0 | I99: =+(G99*H99)+G99 -> 300000 | J99: =I99/$I$111 -> 0.0078422779 | K99: =+I99/(1-$K$19) -> 461538.46
B100: 10.4 | C100: Extensiones electricas | D100: un | E100: 0 | F100: 90000 | G100: =+F100*E100 -> 0 | H100: 0 | I100: =+(G100*H100)+G100 -> 0 | J100: =I100/$I$111 -> 0 | K100: =+I100/(1-$K$19) -> 0
B101: 10.5 | C101: Accesorios maquinas (mangera y tarjeta) | D101: un | E101: 0 | F101: 400000 | G101: =+F101*E101 -> 0 | H101: 0 | I101: =+(G101*H101)+G101 -> 0 | J101: =I101/$I$111 -> 0 | K101: =+I101/(1-$K$19) -> 0
B102: 10.6 | C102: Rodillos/Brochas | D102: un | E102: 5 | F102: 2500 | G102: =+F102*E102 -> 12500 | H102: 0 | I102: =+(G102*H102)+G102 -> 12500 | J102: =I102/$I$111 -> 0.00032676158 | K102: =+I102/(1-$K$19) -> 19230.769
B103: 10.7 | C103: Poliesterino | D103: global | E103: 0 | F103: 80000 | G103: =+F103*E103 -> 0 | H103: 0 | I103: =+(G103*H103)+G103 -> 0 | J103: =I103/$I$111 -> 0 | K103: =+I103/(1-$K$19) -> 0
B104: 10.8 | C104: Iluminacion | D104: un | E104: 0 | F104: 60000 | G104: =+F104*E104 -> 0 | H104: 0 | I104: =+(G104*H104)+G104 -> 0 | J104: =I104/$I$111 -> 0 | K104: =+I104/(1-$K$19) -> 0
B105: 10.9 | C105: Examenes de altura | D105: un | E105: 3 | F105: 40000 | G105: =+F105*E105 -> 120000 | H105: 0 | I105: =+(G105*H105)+G105 -> 120000 | J105: =I105/$I$111 -> 0.0031369112 | K105: =+I105/(1-$K$19) -> 184615.38
B106: 10.10 | C106: poliza anticipo | D106: Global | E106: 1 | F106: 100000 | G106: =+F106*E106 -> 100000 | H106: 0 | I106: =+(G106*H106)+G106 -> 100000 | J106: =I106/$I$111 -> 0.0026140926 | K106: =+I106/(1-$K$19) -> 153846.15
B108: 11 | C108: GG ELEMENTOS DE PROTECCION PERSONAL | D108: =SUM(J109) -> 0.0096967544
B109: 11.1 | C109: elementos de proteccion personal | D109: gl | E109: 0.01 | G109: =(SUM(G25:G106))*E109 -> 370941.5 | H109: 0 | I109: =+(G109*H109)+G109 -> 370941.5 | J109: =I109/$I$111 -> 0.0096967544 | K109: =+I109/(1-$K$19) -> 570679.23
F111: TOTALES | G111: =SUM(G23:G109) -> 37465092 | I111: =SUM(I23:I109) -> 38254192 | J111: =SUM(J23:J109) -> 1 | K111: =SUM(K25:K109) -> 58852602
K112: =1-(I111/K111) -> 0.35
B115: NOTAS:

Sheet COT. F.CONTROL
B2: PRESUPUESTO: | C2: F-30
B3: OBRA: | C3: TORRE KENNEDY
B4: PRODUCTO: | C4: PINTURA INTUMESCENTE
B5: ING. A CARGO:
N6: EN ANDAMIOS SE REQUIERE 100M2 DISPONIBLES DIARIAMENTE
B7: RESUMEN | F7: RESUMEN ECONIMICO | N7: SE CONSIDERA DAR CAPAS DE 325 CAPAS POR CADA MANO, POR LO TANTO EN CADA POSCICION SE OCUPARAN LOS ANDAMIOS 4 DIAS
I8: =+I19/C9 -> 2.3106811 | J8: uf/m2 | N8: SI LA APLICACIÓN DE P.I SE DEBE APLICAR CON RODILLO PARA EVITAR CONTAMINACION DR RDTRUCUTS , ESTA SE DEBE ENTREGAR LIMPIA, ES DECIR SIN POLVO NI GRASAS
B9: SUPERFICIE 1 | C9: =+SUM(CUBICACION!U2:U6) -> 1877.384 | D9: m2 | F9: VALOR UF | G9: 40830 | H9: $ | I9: =+G19/C9 -> 94345.111 | J9: $/m2
B11: Superficie Topping | C11: 0 | D11: m2 | F11: VALOR DOLLAR | G11: 919.07 | H11: $ | K11: 0.15 | L11: Margen mat
B13: Rendimiento m2/día | C13: 0 | D13: m2/día | F13: COSTO | G13: =+I139 -> 1.3856968e+08 | H13: $ | I13: =+G13/G9 -> 3393.8202 | J13: UF | K13: 0.35 | L13: Margen MOI | O13: 703.2 | P13: 0.898 | Q13: =P13*O13 -> 631.4736
C15: 5 | D15: Tineta/máquina | F15: MARGEN DE VENTA | G15: =+L140 -> 0.21765971 | H15: % | I15: =+G15 -> 0.21765971 | J15: % | K15: 0.35 | L15: Margen MOD | P15: 0.52 | Q15: =P15*O13 -> 365.664
B17: Cantidad de equipos | C17: 2 | D17: Unidad | F17: MARGEN DE VENTA | G17: =+G19-G13 -> 38552324 | H17: $ | I17: =+G17/G9 -> 944.21563 | J17: UF | K17: 0.35 | L17: Margen Equipos | P17: 0.071 | Q17: =P17*O13 -> 49.9272
F19: PRECIO DE VENTA | G19: =+L139 -> 1.77122e+08 | H19: $ | I19: =+G19/G9 -> 4338.0358 | J19: UF | K19: 0.35 | L19: Margen GG | P19: =P13+P15+P17 -> 1.489 | Q19: =Q13+Q15+Q17 -> 1047.0648
Q21: =O13*P19 -> 1047.0648
B22: ÍTEM Nº | C22: Descripcion | D22: Unidad | E22: Cantidad | F22: Costo Unitario | G22: Costo Total | H22: PERDIDA (%) | I22: Costo Total C/Perdida | J22: INCIDENCIA (%) | K22: Margen (%) | L22: Precio de Venta | N22: CUADRO GENERAL
N23: Descripción | O23: Superficie m² | P23: UF/m² | Q23: Total P.U (UF) | R23: %
B24: 1 | C24: MATERIALES | D24: =SUM(J25:J29) -> 0.71892785 | F24: Actualizados Febrero '25 | N24: Materiales Directos | O24: =+$C$9 -> 1877.384 | P24: =+Q24/O24 -> 1.661213 | Q24: =+R24*Q27 -> 3118.7347 | R24: =+D24 -> 0.71892785
B25: 1.1 | C25: Fire Control | D25: Tinetas | E25: =+CUBICACION!V2 -> 0 | F25: 115000 | G25: =+F25*E25 -> 0 | H25: 0.05 | I25: =+(G25*H25)+G25 -> 0 | J25: =I25/$I$139 -> 0 | K25: =$K$11 -> 0.15 | L25: =+I25/(1-K25) -> 0 | N25: Mano de obra Directa e Indirecta | O25: =$C$9 -> 1877.384 | P25: =+Q25/O25 -> 0.29574086 | Q25: =+R25*Q27 -> 555.21916 | R25: =+D31+F40 -> 0.12798861
B26: 1.2 | C26: Fire Tex 5062 | D26: Tinetas | E26: =+CUBICACION!V3 -> 0 | F26: 163000 | G26: =F26*E26 -> 0 | H26: 0.05 | I26: =+(G26*H26)+G26 -> 0 | J26: =I26/$I$139 -> 0 | K26: =$K$11 -> 0.15 | L26: =+I26/(1-K26) -> 0 | N26: Gastos Generales | O26: =$C$9 -> 1877.384 | P26: =+Q26/O26 -> 0.35372726 | Q26: =+R26*Q27 -> 664.08189 | R26: =+D65+D77+D89+D102+D109+D117+D124+D136 -> 0.15308354
B27: 1.3 | C27: Fire Tex 5090 | D27: Tinetas | E27: =+CUBICACION!V4 -> 496 | F27: 195000 | G27: =F27*E27 -> 96720000 | H27: 0.03 | I27: =+(G27*H27)+G27 -> 99621600 | J27: =I27/$I$139 -> 0.71892785 | K27: =$K$11 -> 0.15 | L27: =+I27/(1-K27) -> 1.1720188e+08 | N27: Total | O27: =+O26 -> 1877.384 | P27: =+SUM(P24:P26) -> 2.3106811 | Q27: =+I19 -> 4338.0358
B28: 1.4 | C28: Fire Tex 5120 | D28: Tinetas | E28: =+CUBICACION!V5 -> 0 | F28: 195000 | G28: =F28*E28 -> 0 | H28: 0.03 | I28: =+(G28*H28)+G28 -> 0 | J28: =I28/$I$139 -> 0 | K28: =$K$11 -> 0.15 | L28: =+I28/(1-K28) -> 0
B29: 1.5 | C29: Topping | D29: Tinetas | G29: =F29*E29 -> 0 | H29: 0.05 | I29: =+(G29*H29)+G29 -> 0 | J29: =I29/$I$139 -> 0 | K29: =$K$11 -> 0.15 | L29: =+I29/(1-K29) -> 0
N30: Fire Control
B31: 2 | C31: MANO DE OBRA INDIRECTA | D31: =SUM(J32:J38) -> 0.038860017 | N31: Descripción | O31: Superficie m² | P31: UF/m² | Q31: Total P.U (UF) | R31: =+$E$25/($E$25+$E$26) -> #DIV/0!
B32: 2.1 | C32: HD Instalacion/retiro de Faena | D32: HD | E32: 1 | H32: 0.05 | I32: =+(G32*H32)+G32 -> 0 | J32: =I32/$I$139 -> 0 | K32: =+$K$13 -> 0.35 | L32: =+I32/(1-K32) -> 0 | N32: Materiales Directos | O32: =+$O$35 -> 0 | P32: =+Q32/O32 -> #DIV/0! | Q32: =+Q24*$R$31 -> #DIV/0!
B33: 2.2 | C33: HD induccion | D33: HD | E33: 1 | H33: 0.05 | I33: =+(G33*H33)+G33 -> 0 | J33: =I33/$I$139 -> 0 | K33: =+$K$13 -> 0.35 | L33: =+I33/(1-K33) -> 0 | N33: Mano de obra Directa e Indirecta | O33: =$O$35 -> 0 | P33: =+Q33/O33 -> #DIV/0! | Q33: =+Q25*$R$31 -> #DIV/0!
B34: 2.3 | C34: Supervisión 100% tiempo efectivo | D34: HD | E34: =+ROUNDUP(E38,0)*1 -> 52 | F34: =74000*1.3 -> 96200 | G34: =+F34*E34 -> 5002400 | H34: 0.05 | I34: =+(G34*H34)+G34 -> 5252520 | J34: =I34/$I$139 -> 0.037905263 | K34: =+$K$13 -> 0.35 | L34: =+I34/(1-K34) -> 8080800 | N34: Gastos Generales | O34: =$O$35 -> 0 | P34: =+Q34/O34 -> #DIV/0! | Q34: =+Q26*$R$31 -> #DIV/0!
B35: 2.4 | C35: Prevencionista 100% tiempo efectivo | D35: HD | E35: 3 | F35: 42000 | G35: =+F35*E35 -> 126000 | H35: 0.05 | I35: =+(G35*H35)+G35 -> 132300 | J35: =I35/$I$139 -> 0.00095475433 | K35: =+$K$13 -> 0.35 | L35: =+I35/(1-K35) -> 203538.46 | N35: Total | O35: =+CUBICACION!U2 -> 0 | P35: =+SUM(P32:P34) -> #DIV/0! | Q35: =+SUM(Q32:Q34) -> #DIV/0!
B36: 2.5 | C36: Administrador /oficina técnica | D36: HD | E36: 0 | F36: =62500+26000 -> 88500 | G36: =+F36*E36 -> 0 | H36: 0.05 | I36: =+(G36*H36)+G36 -> 0 | J36: =I36/$I$139 -> 0 | K36: =+$K$13 -> 0.35 | L36: =+I36/(1-K36) -> 0
C38: Duracion obra | D38: HD | E38: =+ROUNDUP(($E$25+$E$26+$E$27+$E$28+$E$29)/($C$15*$C$17),0)+$E$32+$E$33 -> 52 | N38: Fire Tex
N39: Descripción | O39: Superficie m² | P39: UF/m² | Q39: Total P.U (UF) | R39: =+$E$26/($E$25+$E$26) -> #DIV/0!
B40: 3 | C40: MANO DE OBRA DIRECTA | D40: cantidad de equipos | F40: =SUM(J41:J63) -> 0.08912859 | G40: fondo de reserva | H40: 0.05 | N40: Materiales Directos | O40: =+$O$43 -> 0 | P40: =+Q40/O40 -> #DIV/0! | Q40: =+R39*Q24 -> #DIV/0!
B41: SUBCONTRATO 2 | C41: Aplicador | D41: HD | E41: =$E$38 -> 52 | F41: =45000*1.3*$C$17 -> 117000 | G41: =+F41*E41 -> 6084000 | H41: =+H40 -> 0.05 | I41: =+(G41*H41)+G41 -> 6388200 | J41: =I41/$I$139 -> 0.046100995 | K41: =+K15 -> 0.35 | L41: =+I41/(1-K41) -> 9828000 | N41: Mano de obra Directa e Indirecta | O41: =+$O$43 -> 0 | P41: =+Q41/O41 -> #DIV/0! | Q41: =+R39*Q25 -> #DIV/0!
C42: Ayudante | D42: HD | E42: =$E$38 -> 52 | F42: =42000*1.3*$C$17 -> 109200 | G42: =+F42*E42 -> 5678400 | H42: =+H40 -> 0.05 | I42: =+(G42*H42)+G42 -> 5962320 | J42: =I42/$I$139 -> 0.043027595 | K42: =+K15 -> 0.35 | L42: =+I42/(1-K42) -> 9172800 | N42: Gastos Generales | O42: =+$O$43 -> 0 | P42: =+Q42/O42 -> #DIV/0! | Q42: =+R39*Q27 -> #DIV/0!
C43: Maquinista | D43: HD | E43: 0 | F43: =33000 -> 33000 | G43: =+F43*E43 -> 0 | H43: =+H40 -> 0.05 | I43: =+(G43*H43)+G43 -> 0 | J43: =I43/$I$139 -> 0 | K43: =+K15 -> 0.35 | L43: =+I43/(1-K43) -> 0 | N43: Total | O43: =CUBICACION!U3 -> 0 | P43: =+SUM(P40:P42) -> #DIV/0! | Q43: =+SUM(Q40:Q42) -> #DIV/0!
C44: mallero | D44: HD | E44: 0 | F44: =28000 -> 28000 | G44: =+F44*E44 -> 0 | H44: =+H40 -> 0.05 | I44: =+(G44*H44)+G44 -> 0 | J44: =I44/$I$139 -> 0 | K44: =+K15 -> 0.35 | L44: =+I44/(1-K44) -> 0
C45: Variable HH | D45: HD | E45: 0 | G45: =+F45*E45 -> 0 | H45: =+H40 -> 0.05 | I45: =+(G45*H45)+G45 -> 0 | J45: =I45/$I$139 -> 0 | K45: =+K15 -> 0.35 | L45: =+I45/(1-K45) -> 0
B46: 2.6 | C46: ="Instalación Pintura SUB-CONTRATO ("&E46&" personas)" -> Instalación Pintura SUB-CONTRATO (4 personas) | D46: N° | E46: =2*C17 -> 4
B47: 2.6.0 | D47: M2 | G47: =+F47*E47 -> 0 | H47: 0.05 | I47: =+(G47*H47)+G47 -> 0 | J47: =I47/$I$139 -> 0 | K47: =+$K$13 -> 0.35 | L47: =+I47/(1-K47) -> 0
B48: 2.6.1 | D48: M2 | G48: =+F48*E48 -> 0 | H48: 0.05 | I48: =+(G48*H48)+G48 -> 0 | J48: =I48/$I$139 -> 0 | K48: =+$K$13 -> 0.35 | L48: =+I48/(1-K48) -> 0
B49: 2.6.2 | D49: M2 | G49: =+F49*E49 -> 0 | H49: 0.05 | I49: =+(G49*H49)+G49 -> 0 | J49: =I49/$I$139 -> 0 | K49: =+$K$13 -> 0.35 | L49: =+I49/(1-K49) -> 0
B50: 2.6.3 | D50: M2 | G50: =+F50*E50 -> 0 | H50: 0.05 | I50: =+(G50*H50)+G50 -> 0 | J50: =I50/$I$139 -> 0 | K50: =+$K$13 -> 0.35 | L50: =+I50/(1-K50) -> 0
B51: 2.6.4 | D51: M2 | G51: =+F51*E51 -> 0 | H51: 0.05 | I51: =+(G51*H51)+G51 -> 0 | J51: =I51/$I$139 -> 0 | K51: =+$K$13 -> 0.35 | L51: =+I51/(1-K51) -> 0
B52: 2.6.5 | D52: M2 | G52: =+F52*E52 -> 0 | H52: 0.05 | I52: =+(G52*H52)+G52 -> 0 | J52: =I52/$I$139 -> 0 | K52: =+$K$13 -> 0.35 | L52: =+I52/(1-K52) -> 0
B53: 2.6.6 | D53: M2 | G53: =+F53*E53 -> 0 | H53: 0.05 | I53: =+(G53*H53)+G53 -> 0 | J53: =I53/$I$139 -> 0 | K53: =+$K$13 -> 0.35 | L53: =+I53/(1-K53) -> 0
D54: M2 | G54: =+F54*E54 -> 0 | H54: 0.05 | I54: =+(G54*H54)+G54 -> 0 | J54: =I54/$I$139 -> 0 | K54: =+$K$13 -> 0.35 | L54: =+I54/(1-K54) -> 0
D55: M2 | G55: =+F55*E55 -> 0 | H55: 0.05 | I55: =+(G55*H55)+G55 -> 0 | J55: =I55/$I$139 -> 0 | K55: =+$K$13 -> 0.35 | L55: =+I55/(1-K55) -> 0
D56: M2 | G56: =+F56*E56 -> 0 | H56: 0.05 | I56: =+(G56*H56)+G56 -> 0 | J56: =I56/$I$139 -> 0 | K56: =+$K$13 -> 0.35 | L56: =+I56/(1-K56) -> 0
D57: M2 | G57: =+F57*E57 -> 0 | H57: 0.05 | I57: =+(G57*H57)+G57 -> 0 | J57: =I57/$I$139 -> 0 | K57: =+$K$13 -> 0.35 | L57: =+I57/(1-K57) -> 0
D58: M2 | G58: =+F58*E58 -> 0 | H58: 0.05 | I58: =+(G58*H58)+G58 -> 0 | J58: =I58/$I$139 -> 0 | K58: =+$K$13 -> 0.35 | L58: =+I58/(1-K58) -> 0
D59: M2 | G59: =+F59*E59 -> 0 | H59: 0.05 | I59: =+(G59*H59)+G59 -> 0 | J59: =I59/$I$139 -> 0 | K59: =+$K$13 -> 0.35 | L59: =+I59/(1-K59) -> 0
D60: M2 | G60: =+F60*E60 -> 0 | H60: 0.05 | I60: =+(G60*H60)+G60 -> 0 | J60: =I60/$I$139 -> 0 | K60: =+$K$13 -> 0.35 | L60: =+I60/(1-K60) -> 0
D61: M2 | G61: =+F61*E61 -> 0 | H61: 0.05 | I61: =+(G61*H61)+G61 -> 0 | J61: =I61/$I$139 -> 0 | K61: =+$K$13 -> 0.35 | L61: =+I61/(1-K61) -> 0
B63: 2.7 | C63: Variable HH | D63: día | H63: =+H40 -> 0.05 | I63: =+(G63*H63)+G63 -> 0 | J63: =I63/$I$139 -> 0 | K63: =+$K$13 -> 0.35 | L63: =+I63/(1-K63) -> 0
B65: 4 | C65: GG VIAJES (ida y vuelta) | D65: =SUM(J66:J75) -> 0.047629468 | E65: valor asignado | F65: 200000
B66: 4.1 | C66: Aplicador | D66: Unid | E66: =+IF(F65>0,ROUNDUP(E41/5,0),0) -> 11 | F66: =$F$65 -> 200000 | G66: =+F66*E66 -> 2200000 | H66: 0 | I66: =+(G66*H66)+G66 -> 2200000 | J66: =I66/$I$139 -> 0.015876489 | K66: =+K19 -> 0.35 | L66: =+I66/(1-K66) -> 3384615.4
B67: 4.2 | C67: Ayudante | D67: Unid | E67: =+IF(F65>0,ROUNDUP(E42/5,0),0) -> 11 | F67: =$F$65 -> 200000 | G67: =+F67*E67 -> 2200000 | H67: 0 | I67: =+(G67*H67)+G67 -> 2200000 | J67: =I67/$I$139 -> 0.015876489 | K67: =+K19 -> 0.35 | L67: =+I67/(1-K67) -> 3384615.4
B68: 4.3 | C68: Maquinista | D68: Unid | F68: =$F$65 -> 200000 | G68: =+F68*E68 -> 0 | H68: 0 | I68: =+(G68*H68)+G68 -> 0 | J68: =I68/$I$139 -> 0 | K68: =+K19 -> 0.35 | L68: =+I68/(1-K68) -> 0
B69: 4.5 | C69: mallero | D69: Unid | F69: =$F$65 -> 200000 | G69: =+F69*E69 -> 0 | H69: 0 | I69: =+(G69*H69)+G69 -> 0 | J69: =I69/$I$139 -> 0 | K69: =+K19 -> 0.35 | L69: =+I69/(1-K69) -> 0
B70: 4.6 | C70: =$C$34 -> Supervisión 100% tiempo efectivo | D70: Unid | E70: =+IF(F65>0,ROUNDUP(E34/5,0),0) -> 11 | F70: =$F$65 -> 200000 | G70: =+F70*E70 -> 2200000 | H70: 0 | I70: =+(G70*H70)+G70 -> 2200000 | J70: =I70/$I$139 -> 0.015876489 | K70: =+K19 -> 0.35 | L70: =+I70/(1-K70) -> 3384615.4
B71: 4.7 | C71: =$C$35 -> Prevencionista 100% tiempo efectivo | D71: Unid | E71: 0 | F71: =$F$65 -> 200000 | G71: =+F71*E71 -> 0 | H71: 0 | I71: =+(G71*H71)+G71 -> 0 | J71: =I71/$I$139 -> 0 | K71: =+K19 -> 0.35 | L71: =+I71/(1-K71) -> 0
B72: 4.8 | C72: Variable HH | D72: Unid | F72: =$F$65 -> 200000 | G72: =+F72*E72 -> 0 | H72: 0 | I72: =+(G72*H72)+G72 -> 0 | J72: =I72/$I$139 -> 0 | K72: =+K19 -> 0.35 | L72: =+I72/(1-K72) -> 0
B73: 4.10 | D73: Unid | F73: =$F$65 -> 200000 | G73: =+F73*E73 -> 0 | H73: 0 | I73: =+(G73*H73)+G73 -> 0 | J73: =I73/$I$139 -> 0 | K73: =+K19 -> 0.35 | L73: =+I73/(1-K73) -> 0
B74: 4.11 | C74: ="Viaje Subcontrato ("&$E$46&" personas)" -> Viaje Subcontrato (4 personas) | D74: Unid | F74: =$F$65 -> 200000 | G74: =+F74*E74 -> 0 | H74: 0 | I74: =+(G74*H74)+G74 -> 0 | J74: =I74/$I$139 -> 0 | K74: =+K19 -> 0.35 | L74: =+I74/(1-K74) -> 0
B75: 4.12 | C75: otro | D75: Unid | F75: =$F$65 -> 200000 | G75: =+F75*E75 -> 0 | H75: 0 | I75: =+(G75*H75)+G75 -> 0 | J75: =I75/$I$139 -> 0 | K75: =+K19 -> 0.35 | L75: =+I75/(1-K75) -> 0
B77: 5 | C77: GG TRASLADOS INTERNOS | D77: =SUM(J78:J86) -> 0 | E77: valor asignado | F77: 0
B78: 5.1 | C78: Aplicador | D78: Unid | E78: =+$E$38 -> 52 | F78: =$F$77*ROUNDUP($E$34/5,0) -> 0 | G78: =+F78*E78 -> 0 | H78: 0 | I78: =+(G78*H78)+G78 -> 0 | J78: =I78/$I$139 -> 0 | K78: =+K19 -> 0.35 | L78: =+I78/(1-K78) -> 0
B79: 5.2 | C79: Ayudante | D79: Unid | E79: =+$E$38 -> 52 | F79: =$F$77*ROUNDUP($E$34/5,0) -> 0 | G79: =+F79*E79 -> 0 | H79: 0 | I79: =+(G79*H79)+G79 -> 0 | J79: =I79/$I$139 -> 0 | K79: =+K19 -> 0.35 | L79: =+I79/(1-K79) -> 0
B80: 5.3 | C80: Maquinista | D80: Unid | F80: =$F$77*ROUNDUP($E$34/5,0) -> 0 | G80: =+F80*E80 -> 0 | H80: 0 | I80: =+(G80*H80)+G80 -> 0 | J80: =I80/$I$139 -> 0 | K80: =+K19 -> 0.35 | L80: =+I80/(1-K80) -> 0
B81: 5.4 | C81: mallero | D81: Unid | F81: =$F$77*ROUNDUP($E$34/5,0) -> 0 | G81: =+F81*E81 -> 0 | H81: 0 | I81: =+(G81*H81)+G81 -> 0 | J81: =I81/$I$139 -> 0 | K81: =+K19 -> 0.35 | L81: =+I81/(1-K81) -> 0
B82: 5.5 | C82: =$C$34 -> Supervisión 100% tiempo efectivo | D82: Unid | E82: =+$E$38 -> 52 | F82: =$F$77*ROUNDUP($E$34/5,0) -> 0 | G82: =+F82*E82 -> 0 | H82: 0 | I82: =+(G82*H82)+G82 -> 0 | J82: =I82/$I$139 -> 0 | K82: =+K19 -> 0.35 | L82: =+I82/(1-K82) -> 0
B83: 5.6 | C83: =$C$35 -> Prevencionista 100% tiempo efectivo | D83: Unid | E83: 0 | F83: =$F$77*ROUNDUP($E$34/5,0) -> 0 | G83: =+F83*E83 -> 0 | H83: 0 | I83: =+(G83*H83)+G83 -> 0 | J83: =I83/$I$139 -> 0 | K83: =+K20 -> 0 | L83: =+I83/(1-K83) -> 0
B84: 5.7 | C84: Variable HH | D84: Unid | F84: =$F$77*ROUNDUP($E$34/5,0) -> 0 | G84: =+F84*E84 -> 0 | H84: 0 | I84: =+(G84*H84)+G84 -> 0 | J84: =I84/$I$139 -> 0 | K84: =+K19 -> 0.35 | L84: =+I84/(1-K84) -> 0
B85: 5.9 | C85: Prevensionista 10% | D85: Unid | F85: =$F$77*ROUNDUP($E$34/5,0) -> 0 | G85: =E85*F85 -> 0 | H85: 0 | I85: =+(G85*H85)+G85 -> 0 | J85: =I85/$I$139 -> 0 | K85: =+K19 -> 0.35 | L85: =+I85/(1-K85) -> 0
B86: 5.10 | C86: ="Viaje Subcontrato ("&$E$46&" personas)" -> Viaje Subcontrato (4 personas) | D86: Unid | F86: =$F$77*ROUNDUP($E$34/5,0) -> 0 | G86: =+F86*E86 -> 0 | H86: 0 | I86: =+(G86*H86)+G86 -> 0 | J86: =I86/$I$139 -> 0 | K86: =+K19 -> 0.35 | L86: =+I86/(1-K86) -> 0
B87: 5.11 | C87: otro | D87: Unid
B89: 6 | C89: GG VIATICO | D89: =SUM(J90:J100) -> 0.053662534 | E89: valor asignado | F89: 28000
B90: 6.1 | C90: Supervisor | D90: día | E90: =+IF($F$65>0,E34,0) -> 52 | F90: =$F$89+3000 -> 31000 | G90: =+F90*E90 -> 1612000 | H90: 0 | I90: =+(G90*H90)+G90 -> 1612000 | J90: =I90/$I$139 -> 0.011633137 | K90: =+K19 -> 0.35 | L90: =+I90/(1-K90) -> 2480000
B91: 6.2 | C91: Prevencionista de Riesgo | D91: día | E91: 0 | F91: =$F$89 -> 28000 | G91: =+F91*E91 -> 0 | H91: 0 | I91: =+(G91*H91)+G91 -> 0 | J91: =I91/$I$139 -> 0 | K91: =+K19 -> 0.35 | L91: =+I91/(1-K91) -> 0
B92: 6.3 | C92: Administrador /oficina técnica | D92: día | F92: =$F$89 -> 28000 | G92: =+F92*E92 -> 0 | H92: 0 | I92: =+(G92*H92)+G92 -> 0 | J92: =I92/$I$139 -> 0 | K92: =+K19 -> 0.35 | L92: =+I92/(1-K92) -> 0
B93: 6.4 | C93: Aplicador | D93: día | E93: =+IF($F$65>0,E41*$C$17,0) -> 104 | F93: =$F$89 -> 28000 | G93: =+F93*E93 -> 2912000 | H93: 0 | I93: =+(G93*H93)+G93 -> 2912000 | J93: =I93/$I$139 -> 0.021014699 | K93: =+K19 -> 0.35 | L93: =+I93/(1-K93) -> 4480000
B94: 6.5 | C94: Ayudante | D94: día | E94: =+IF($F$65>0,E42*$C$17,0) -> 104 | F94: =$F$89 -> 28000 | G94: =+F94*E94 -> 2912000 | H94: 0 | I94: =+(G94*H94)+G94 -> 2912000 | J94: =I94/$I$139 -> 0.021014699 | K94: =+K19 -> 0.35 | L94: =+I94/(1-K94) -> 4480000
B95: 6.6 | C95: Maquinista | D95: día | E95: =+IF($F$65>0,E43*$C$17,0) -> 0 | F95: =$F$89 -> 28000 | G95: =+F95*E95 -> 0 | H95: 0 | I95: =+(G95*H95)+G95 -> 0 | J95: =I95/$I$139 -> 0 | K95: =+K19 -> 0.35 | L95: =+I95/(1-K95) -> 0
B96: 6.7 | C96: Jornal | D96: día | F96: =$F$89 -> 28000 | G96: =+F96*E96 -> 0 | H96: 0 | I96: =+(G96*H96)+G96 -> 0 | J96: =I96/$I$139 -> 0 | K96: =+K19 -> 0.35 | L96: =+I96/(1-K96) -> 0
B97: 6.8 | C97: Operario Elevador | D97: día | F97: =$F$89 -> 28000 | G97: =+F97*E97 -> 0 | H97: 0 | I97: =+(G97*H97)+G97 -> 0 | J97: =I97/$I$139 -> 0 | K97: =+K19 -> 0.35 | L97: =+I97/(1-K97) -> 0
B98: 6.9 | C98: Andamieros | D98: día | F98: =$F$89 -> 28000 | G98: =+F98*E98 -> 0 | H98: 0 | I98: =+(G98*H98)+G98 -> 0 | J98: =I98/$I$139 -> 0 | K98: =+K19 -> 0.35 | L98: =+I98/(1-K98) -> 0
B99: 6.10 | C99: Sub contrato | D99: día | F99: =$F$89 -> 28000 | G99: =+F99*E99 -> 0 | H99: 0 | I99: =+(G99*H99)+G99 -> 0 | J99: =I99/$I$139 -> 0 | K99: =+K19 -> 0.35 | L99: =+I99/(1-K99) -> 0
B100: 6.11 | C100: otro | D100: día | F100: =$F$89 -> 28000 | G100: =+F100*E100 -> 0 | H100: 0 | I100: =+(G100*H100)+G100 -> 0 | J100: =I100/$I$139 -> 0 | K100: =+K19 -> 0.35 | L100: =+I100/(1-K100) -> 0
B102: 7 | C102: GG TRASLADOS | D102: =SUM(J103:J107) -> 0.030923071
B103: 7.1 | C103: Flete material | D103: unid | E103: 1 | F103: 50000 | G103: =+F103*E103 -> 50000 | H103: 0 | I103: =+(G103*H103)+G103 -> 50000 | J103: =I103/$I$139 -> 0.0003608293 | K103: =+K19 -> 0.35 | L103: =+I103/(1-K103) -> 76923.077
B104: 7.2 | C104: Flete Contenedor | D104: unid | E104: 0 | F104: 300000 | G104: =+F104*E104 -> 0 | H104: 0 | I104: =+(G104*H104)+G104 -> 0 | J104: =I104/$I$139 -> 0 | K104: =+K19 -> 0.35 | L104: =+I104/(1-K104) -> 0
B105: 7.3 | C105: Flete Elevador | D105: unid | E105: 0 | F105: 480000 | G105: =+F105*E105 -> 0 | H105: 0 | I105: =+(G105*H105)+G105 -> 0 | J105: =I105/$I$139 -> 0 | K105: =+K19 -> 0.35 | L105: =+I105/(1-K105) -> 0
B106: 7.5 | C106: Arriendo camioneta C/combustible | D106: días | E106: =E38 -> 52 | F106: 80000 | G106: =+F106*E106 -> 4160000 | H106: 0 | I106: =+(G106*H106)+G106 -> 4160000 | J106: =I106/$I$139 -> 0.030020998 | K106: =+K19 -> 0.35 | L106: =+I106/(1-K106) -> 6400000
B107: 7.6 | C107: Flete retorno | D107: unid | E107: 1 | F107: 75000 | G107: =+F107*E107 -> 75000 | H107: 0 | I107: =+(G107*H107)+G107 -> 75000 | J107: =I107/$I$139 -> 0.00054124395 | K107: =+K19 -> 0.35 | L107: =+I107/(1-K107) -> 115384.62
B109: 8 | C109: MAQUINARIA Y EQUIPOS | D109: =SUM(J110:J115) -> 0
B110: 8.1 | C110: Amortización de máquina de aplicación | D110: CLP$/bolsa | E110: =+E25+E26 -> 0 | F110: 360 | G110: =+F110*E110 -> 0 | H110: 0 | I110: =+(G110*H110)+G110 -> 0 | J110: =I110/$I$139 -> 0 | K110: =+K17 -> 0.35 | L110: =+I110/(1-K110) -> 0
B111: 8.2 | C111: Sistema de elevacion tipo manlift | D111: dias | E111: 0 | F111: 1200000 | G111: =+F111*E111 -> 0 | H111: 0 | I111: =+(G111*H111)+G111 -> 0 | J111: =I111/$I$139 -> 0 | K111: =+K17 -> 0.35 | L111: =+I111/(1-K111) -> 0
B112: 8.3 | C112: Petroleo sistema de elevacion | D112: lt/dia | E112: 0 | F112: =(8*8)*38*500 -> 1216000 | G112: =+F112*E112 -> 0 | H112: 0 | I112: =+(G112*H112)+G112 -> 0 | J112: =I112/$I$139 -> 0 | K112: =+K17 -> 0.35 | L112: =+I112/(1-K112) -> 0
B113: 8.4 | C113: Pistola Hilti y mantencion | D113: Global | E113: 0 | F113: 3000000 | G113: =+F113*E113 -> 0 | H113: 0 | I113: =+(G113*H113)+G113 -> 0 | J113: =I113/$I$139 -> 0 | K113: =+K17 -> 0.35 | L113: =+I113/(1-K113) -> 0
B114: 8.5 | C114: Airles Pte adherente | D114: dias | E114: 0 | F114: 1000000 | G114: =+F114*E114 -> 0 | H114: 0 | I114: =+(G114*H114)+G114 -> 0 | J114: =I114/$I$139 -> 0 | K114: =+K17 -> 0.35 | L114: =+I114/(1-K114) -> 0
...

Sheet resumen
A3: ESTRUCTURA | B3: DIMENSIONES | C3: RESIST. AL FUEGO | D3: MASIV. (M-1) | E3: CARAS EXPTAS. | F3: MATERIAL | G3: Suma de ÁREA EXPUESTA [m2]
A4: ARRIOSTRAMINETO VERTICAL | B4: 100X100X3 | C4: F-60 | D4: 333 | E4: 4 | F4: Fire Tex 5090 | G4: 150.32
A5: COSTANERA | B5: 125X50X15X2 | C5: 60 | D5: 1057 | E5: 3 | F5: Blaze Shield II | G5: 1161.7348
A6: LOSA | B6: - | C6: 60 | D6: - | E6: 1 | F6: Blaze Shield II | G6: 328.581
A7: PILAR | B7: 100X100X3 | C7: F-60 | D7: 333 | E7: 4 | F7: Fire Tex 5090 | G7: 6.2
A8: PILAR | B8: 150X150X5 | C8: F-60 | D8: 200 | E8: 4 | F8: Fire Tex 5090 | G8: 114.96
A9: PILAR | B9: 200X100X3 | C9: F-60 | D9: 333 | E9: 4 | F9: Fire Tex 5090 | G9: 20.16
A10: PILAR | B10: 200X100X4 | C10: F-60 | D10: 250 | E10: 4 | F10: Fire Tex 5090 | G10: 51.18
A11: PILAR | B11: MM 400X200X4 | C11: F-60 | D11: 236 | E11: 4 | F11: Fire Tex 5090 | G11: 326.4
A12: PUNTAL | B12: 100X100X3 | C12: F-60 | D12: 333 | E12: 4 | F12: Fire Tex 5090 | G12: 77.928
A13: VIGA | B13: M1 MM600X225X4 | C13: F-60 | D13: 250 | E13: 4 | F13: Fire Tex 5090 | G13: 891
A14: VIGA | B14: 100X100X3 | C14: F-60 | D14: 333 | E14: 4 | F14: Fire Tex 5090 | G14: 54.712
A15: VIGA | B15: 200X100X3 | C15: F-60 | D15: 333 | E15: 4 | F15: Fire Tex 5090 | G15: 13.644
A16: VIGA | B16: 200X100X4 | C16: F-60 | D16: 250 | E16: 4 | F16: Fire Tex 5090 | G16: 2.4
A17: VIGA | B17: M1 MM400X200X4 | C17: F-60 | D17: 236 | E17: 4 | F17: Fire Tex 5090 | G17: 168.48
A18: VIGA BAJO LOSA | B18: 200X100X8,5X5,6 | C18: 60 | D18: 265 | E18: 3 | F18: Blaze Shield II | G18: 145.0873
A19: VIGA BAJO LOSA | B19: 240X120X9,8X6,2 | C19: 60 | D19: 233 | E19: 3 | F19: Blaze Shield II | G19: 60.6033
A20: (en blanco) | B20: (en blanco) | C20: (en blanco) | D20: (en blanco) | E20: 4 | F20: (en blanco) | G20: 0
A21: Total general | G21: 3573.3904
A24: ESTRUCTURA | B24: DIMENSIONES | C24: RESIST. AL FUEGO | D24: MASIV. (M-1) | E24: CARAS EXPTAS. | F24: MATERIAL | G24: ÁREA EXPUESTA [m2] | H24: COMENTARIO
A25: ARRIOSTRAMINETO VERTICAL | B25: 100X100X3 | C25: F-60 | D25: 333 | E25: 4 | F25: Fire Tex 5090 | G25: 150.32 | H25: CERTIFICABLE
A26: COSTANERA | B26: 125X50X15X2 | C26: F-60 | D26: 1057 | E26: 3 | F26: Blaze Shield II | G26: 1161.7348 | H26: CERTIFICABLE
A27: LOSA | B27: - | C27: F-60 | D27: - | E27: 1 | F27: Blaze Shield II | G27: 328.581 | H27: CERTIFICABLE
A28: PILAR | B28: 100X100X3 | C28: F-60 | D28: 333 | E28: 4 | F28: Fire Tex 5090 | G28: 6.2 | H28: CERTIFICABLE
A29: PILAR | B29: 150X150X5 | C29: F-60 | D29: 200 | E29: 4 | F29: Fire Tex 5090 | G29: 114.96 | H29: CERTIFICABLE
A30: PILAR | B30: 200X100X3 | C30: F-60 | D30: 333 | E30: 4 | F30: Fire Tex 5090 | G30: 20.16 | H30: CERTIFICABLE
A31: PILAR | B31: 200X100X4 | C31: F-60 | D31: 250 | E31: 4 | F31: Fire Tex 5090 | G31: 51.18 | H31: CERTIFICABLE
A32: PILAR | B32: MM 400X200X4 | C32: F-60 | D32: 236 | E32: 4 | F32: Fire Tex 5090 | G32: 326.4 | H32: CERTIFICABLE
A33: PUNTAL | B33: 100X100X3 | C33: F-60 | D33: 333 | E33: 4 | F33: Fire Tex 5090 | G33: 77.928 | H33: CERTIFICABLE
A34: VIGA | B34: M1 MM600X225X4 | C34: F-60 | D34: 250 | E34: 4 | F34: Fire Tex 5090 | G34: 891 | H34: CERTIFICABLE
A35: VIGA | B35: 100X100X3 | C35: F-60 | D35: 333 | E35: 4 | F35: Fire Tex 5090 | G35: 54.712 | H35: CERTIFICABLE
A36: VIGA | B36: 200X100X3 | C36: F-60 | D36: 333 | E36: 4 | F36: Fire Tex 5090 | G36: 13.644 | H36: CERTIFICABLE
A37: VIGA | B37: 200X100X4 | C37: F-60 | D37: 250 | E37: 4 | F37: Fire Tex 5090 | G37: 2.4 | H37: CERTIFICABLE
A38: VIGA | B38: M1 MM400X200X4 | C38: F-60 | D38: 236 | E38: 4 | F38: Fire Tex 5090 | G38: 168.48 | H38: CERTIFICABLE
A39: VIGA BAJO LOSA | B39: 200X100X8,5X5,6 | C39: F-60 | D39: 265 | E39: 3 | F39: Blaze Shield II | G39: 145.0873 | H39: CERTIFICABLE
A40: VIGA BAJO LOSA | B40: 240X120X9,8X6,2 | C40: F-60 | D40: 233 | E40: 3 | F40: Blaze Shield II | G40: 60.6033 | H40: CERTIFICABLE
A41: Total general | G41: 3573.3904

Sheet CUBICACION
P1: Material | Q1: M2 | R1: Total bolsas | T1: Material | U1: M2 | V1: Total tinetas
P2: Blaze Shield II | Q2: =+SUMIF($O$9:$O$1620,P2,$N$9:$N$1620) -> 1696.0064 | R2: =+ROUNDUP(SUMIF($O$9:$O$1620,P2,$U$9:$U$1620),0) -> 823 | T2: Fire Control | U2: =(SUMIF($O$9:$O$1620,T2,$N$9:$N$1620)) -> 0 | V2: =ROUNDUP(SUMIF($O$9:$O$1620,T2,$S$9:$S$1620),0) -> 0
P3: Cafco 400 | Q3: =+SUMIF($O$9:$O$1620,P3,$N$9:$N$1620) -> 0 | R3: =+ROUNDUP(SUMIF($O$9:$O$1620,P3,$U$9:$U$1620),0) -> 0 | T3: Fire Tex 5062 | U3: =(SUMIF($O$9:$O$1620,T3,$N$9:$N$1620)) -> 0 | V3: =ROUNDUP(SUMIF($O$9:$O$1620,T3,$S$9:$S$1620),0) -> 0
P4: Cafco 300 | Q4: =+SUMIF($O$9:$O$1620,P4,$N$9:$N$1620) -> 0 | R4: =+ROUNDUP(SUMIF($O$9:$O$1620,P4,$U$9:$U$1620),0) -> 0 | T4: Fire Tex 5090 | U4: =(SUMIF($O$9:$O$1620,T4,$N$9:$N$1620)) -> 1877.384 | V4: =ROUNDUP(SUMIF($O$9:$O$1620,T4,$S$9:$S$1620),0) -> 496
T5: Fire Tex 5120 | U5: =(SUMIF($O$9:$O$1620,T5,$N$9:$N$1620)) -> 0 | V5: =ROUNDUP(SUMIF($O$9:$O$1620,T5,$S$9:$S$1620),0) -> 0
N6: TOTAL | Q6: MAX
N7: =SUM(N9:N1620) -> 3573.3904 | Q7: =MAX(Q9:Q1620) -> 2828
A8: UBICACIÓN | B8: PLANO | C8: DESCRIPCIÓN EN PLANO | D8: ESTRUCTURA | E8: DIMENSIONES | F8: PERFIL | G8: CANT. | H8: CANTIDAD ESTRUCTURAS | I8: LARGO [mm] | J8: CARAS EXPTAS. | K8: PERÍMETRO EXPUESTO [mm] | L8: RESIST. AL FUEGO | M8: MASIV. (M-1) | N8: ÁREA EXPUESTA [m2] | O8: MATERIAL | P8: CERTIFICACION | Q8: MICRAS | R8: FORMULA | S8: TINETAS | T8: ESPESOR (mm) | U8: SACOS | V8: ANOTACIONES
A9: ELEVACION EJE A | B9: 107-B | C9: PM1 | D9: PILAR | E9: MM 400X200X4 | F9: CJ | G9: 2 | H9: 1 | I9: 5000 | J9: 4 | K9: 1200 | L9: F-60 | M9: 236 | N9: =+IF(F9="","",(K9*I9*H9*G9)/1000000) -> 12 | O9: Fire Tex 5090 | P9: Software Idiem | Q9: =+IF(OR(O9="Fire Control",O9="Fire Tex 5062",O9="Fire Tex 5090",O9="Fire Tex 5120"),'CALCULO PINTURA'!P10," ") -> 2196 | R9: =+IF(OR(O9="Fire Control",O9="Fire Tex 5062",O9="Fire Tex 5090",O9="Fire Tex 5120"),'CALCULO PINTURA'!R10," ") -> 4.0077949 | S9: =+IF(OR(O9="Fire Control",O9="Fire Tex 5062",O9="Fire Tex 5090",O9="Fire Tex 5120"),'CALCULO PINTURA'!S10," ") -> 2.9941652 | T9: =+IF(OR(O9="Blaze Shield II",O9="Cafco 400",O9="Cafco 300"),'CALCULO MORTERO'!N10," ") | U9: =+IF(OR(O9="Blaze Shield II",O9="Cafco 400",O9="Cafco 300"),'CALCULO MORTERO'!O10," ") | V9: {=_xlfn.IFS(O9="Blaze Shield II",'CALCULO MORTERO'!P10, O9="Cafco 400",'CALCULO MORTERO'!Q10,O9="Cafco 300",'CALCULO MORTERO'!S10, AND(OR(O9="Fire tex 5090", O9="Fire Tex 5062", O9="Fire Tex 5120", O9="Fire Control"),Q9>0), "CERT.",TRUE,"-")} -> CERT. | AM9: Blaze Shield II | AO9: Software Idiem
A10: ELEVACION EJE A | B10: 107-B | C10: PM1 | D10: PILAR | E10: MM 400X200X4 | F10: CJ | G10: 10 | H10: 1 | I10: 6000 | J10: 4 | K10: 1200 | L10: F-60 | M10: 236 | N10: =+IF(F10="","",(K10*I10*H10*G10)/1000000) -> 72 | O10: Fire Tex 5090 | P10: Software Idiem | Q10: =+IF(OR(O10="Fire Control",O10="Fire Tex 5062",O10="Fire Tex 5090",O10="Fire Tex 5120"),'CALCULO PINTURA'!P11," ") -> 2196 | R10: =+IF(OR(O10="Fire Control",O10="Fire Tex 5062",O10="Fire Tex 5090",O10="Fire Tex 5120"),'CALCULO PINTURA'!R11," ") -> 4.0077949 | S10: =+IF(OR(O10="Fire Control",O10="Fire Tex 5062",O10="Fire Tex 5090",O10="Fire Tex 5120"),'CALCULO PINTURA'!S11," ") -> 17.964991 | T10: =+IF(OR(O10="Blaze Shield II",O10="Cafco 400",O10="Cafco 300"),'CALCULO MORTERO'!N11," ") | U10: =+IF(OR(O10="Blaze Shield II",O10="Cafco 400",O10="Cafco 300"),'CALCULO MORTERO'!O11," ") | V10: {=_xlfn.IFS(O10="Blaze Shield II",'CALCULO MORTERO'!P11, O10="Cafco 400",'CALCULO MORTERO'!Q11,O10="Cafco 300",'CALCULO MORTERO'!S11, AND(OR(O10="Fire tex 5090", O10="Fire Tex 5062", O10="Fire Tex 5120", O10="Fire Control"),Q10>0), "CERT.",TRUE,"-")} -> CERT. | AM10: Cafco 400 | AO10: Ensayo Idiem
A11: ELEVACION EJE A | B11: 107-B | C11: PM3 | D11: PILAR | E11: 150X150X5 | F11: CJ | G11: 4 | H11: 1 | I11: 4000 | J11: 4 | K11: 600 | L11: F-60 | M11: 200 | N11: =+IF(F11="","",(K11*I11*H11*G11)/1000000) -> 9.6 | O11: Fire Tex 5090 | P11: Software Idiem | Q11: =+IF(OR(O11="Fire Control",O11="Fire Tex 5062",O11="Fire Tex 5090",O11="Fire Tex 5120"),'CALCULO PINTURA'!P12," ") -> 1930 | R11: =+IF(OR(O11="Fire Control",O11="Fire Tex 5062",O11="Fire Tex 5090",O11="Fire Tex 5120"),'CALCULO PINTURA'!R12," ") -> 4.5601646 | S11: =+IF(OR(O11="Fire Control",O11="Fire Tex 5062",O11="Fire Tex 5090",O11="Fire Tex 5120"),'CALCULO PINTURA'!S12," ") -> 2.1051872 | T11: =+IF(OR(O11="Blaze Shield II",O11="Cafco 400",O11="Cafco 300"),'CALCULO MORTERO'!N12," ") | U11: =+IF(OR(O11="Blaze Shield II",O11="Cafco 400",O11="Cafco 300"),'CALCULO MORTERO'!O12," ") | V11: {=_xlfn.IFS(O11="Blaze Shield II",'CALCULO MORTERO'!P12, O11="Cafco 400",'CALCULO MORTERO'!Q12,O11="Cafco 300",'CALCULO MORTERO'!S12, AND(OR(O11="Fire tex 5090", O11="Fire Tex 5062", O11="Fire Tex 5120", O11="Fire Control"),Q11>0), "CERT.",TRUE,"-")} -> CERT. | AM11: Cafco 300
A12: ELEVACION EJE A | B12: 107-B | C12: CJ200X100X3 | D12: PILAR | E12: 200X100X3 | F12: CJ | G12: 2 | H12: 1 | I12: 6200 | J12: 4 | K12: 600 | L12: F-60 | M12: 333 | N12: =+IF(F12="","",(K12*I12*H12*G12)/1000000) -> 7.44 | O12: Fire Tex 5090 | P12: Software Idiem | Q12: =+IF(OR(O12="Fire Control",O12="Fire Tex 5062",O12="Fire Tex 5090",O12="Fire Tex 5120"),'CALCULO PINTURA'!P13," ") -> 2828 | R12: =+IF(OR(O12="Fire Control",O12="Fire Tex 5062",O12="Fire Tex 5090",O12="Fire Tex 5120"),'CALCULO PINTURA'!R13," ") -> 3.1121349 | S12: =+IF(OR(O12="Fire Control",O12="Fire Tex 5062",O12="Fire Tex 5090",O12="Fire Tex 5120"),'CALCULO PINTURA'!S13," ") -> 2.3906418 | T12: =+IF(OR(O12="Blaze Shield II",O12="Cafco 400",O12="Cafco 300"),'CALCULO MORTERO'!N13," ") | U12: =+IF(OR(O12="Blaze Shield II",O12="Cafco 400",O12="Cafco 300"),'CALCULO MORTERO'!O13," ") | V12: {=_xlfn.IFS(O12="Blaze Shield II",'CALCULO MORTERO'!P13, O12="Cafco 400",'CALCULO MORTERO'!Q13,O12="Cafco 300",'CALCULO MORTERO'!S13, AND(OR(O12="Fire tex 5090", O12="Fire Tex 5062", O12="Fire Tex 5120", O12="Fire Control"),Q12>0), "CERT.",TRUE,"-")} -> CERT. | AM12: Fire Control
A13: ELEVACION EJE A | B13: 107-B | C13: PUNTAL. TIP | D13: PUNTAL | E13: 100X100X3 | F13: CJ | G13: 1 | H13: 1 | I13: 68200 | J13: 4 | K13: 400 | L13: F-60 | M13: 333 | N13: =+IF(F13="","",(K13*I13*H13*G13)/1000000) -> 27.28 | O13: Fire Tex 5090 | P13: Software Idiem | Q13: =+IF(OR(O13="Fire Control",O13="Fire Tex 5062",O13="Fire Tex 5090",O13="Fire Tex 5120"),'CALCULO PINTURA'!P14," ") -> 2828 | R13: =+IF(OR(O13="Fire Control",O13="Fire Tex 5062",O13="Fire Tex 5090",O13="Fire Tex 5120"),'CALCULO PINTURA'!R14," ") -> 3.1121349 | S13: =+IF(OR(O13="Fire Control",O13="Fire Tex 5062",O13="Fire Tex 5090",O13="Fire Tex 5120"),'CALCULO PINTURA'!S14," ") -> 8.7656868 | T13: =+IF(OR(O13="Blaze Shield II",O13="Cafco 400",O13="Cafco 300"),'CALCULO MORTERO'!N14," ") | U13: =+IF(OR(O13="Blaze Shield II",O13="Cafco 400",O13="Cafco 300"),'CALCULO MORTERO'!O14," ") | V13: {=_xlfn.IFS(O13="Blaze Shield II",'CALCULO MORTERO'!P14, O13="Cafco 400",'CALCULO MORTERO'!Q14,O13="Cafco 300",'CALCULO MORTERO'!S14, AND(OR(O13="Fire tex 5090", O13="Fire Tex 5062", O13="Fire Tex 5120", O13="Fire Control"),Q13>0), "CERT.",TRUE,"-")} -> CERT. | AM13: Fire Tex 5120
A14: ELEVACION EJE A | B14: 107-B | C14: ARRIOSTRA | D14: ARRIOSTRAMINETO VERTICAL | E14: 100X100X3 | F14: CJ | G14: 8 | H14: 1 | I14: 7500 | J14: 4 | K14: 400 | L14: F-60 | M14: 333 | N14: =+IF(F14="","",(K14*I14*H14*G14)/1000000) -> 24 | O14: Fire Tex 5090 | P14: Software Idiem | Q14: =+IF(OR(O14="Fire Control",O14="Fire Tex 5062",O14="Fire Tex 5090",O14="Fire Tex 5120"),'CALCULO PINTURA'!P15," ") -> 2828 | R14: =+IF(OR(O14="Fire Control",O14="Fire Tex 5062",O14="Fire Tex 5090",O14="Fire Tex 5120"),'CALCULO PINTURA'!R15," ") -> 3.1121349 | S14: =+IF(OR(O14="Fire Control",O14="Fire Tex 5062",O14="Fire Tex 5090",O14="Fire Tex 5120"),'CALCULO PINTURA'!S15," ") -> 7.7117479 | T14: =+IF(OR(O14="Blaze Shield II",O14="Cafco 400",O14="Cafco 300"),'CALCULO MORTERO'!N15," ") | U14: =+IF(OR(O14="Blaze Shield II",O14="Cafco 400",O14="Cafco 300"),'CALCULO MORTERO'!O15," ") | V14: {=_xlfn.IFS(O14="Blaze Shield II",'CALCULO MORTERO'!P15, O14="Cafco 400",'CALCULO MORTERO'!Q15,O14="Cafco 300",'CALCULO MORTERO'!S15, AND(OR(O14="Fire tex 5090", O14="Fire Tex 5062", O14="Fire Tex 5120", O14="Fire Control"),Q14>0), "CERT.",TRUE,"-")} -> CERT. | AM14: Fire Tex 5090
A15: ELEVACION EJE F | B15: 107-B | C15: PM1 | D15: PILAR | E15: MM 400X200X4 | F15: CJ | G15: 2 | H15: 1 | I15: 5000 | J15: 4 | K15: 1200 | L15: F-60 | M15: 236 | N15: =+IF(F15="","",(K15*I15*H15*G15)/1000000) -> 12 | O15: Fire Tex 5090 | P15: Software Idiem | Q15: =+IF(OR(O15="Fire Control",O15="Fire Tex 5062",O15="Fire Tex 5090",O15="Fire Tex 5120"),'CALCULO PINTURA'!P16," ") -> 2196 | R15: =+IF(OR(O15="Fire Control",O15="Fire Tex 5062",O15="Fire Tex 5090",O15="Fire Tex 5120"),'CALCULO PINTURA'!R16," ") -> 4.0077949 | S15: =+IF(OR(O15="Fire Control",O15="Fire Tex 5062",O15="Fire Tex 5090",O15="Fire Tex 5120"),'CALCULO PINTURA'!S16," ") -> 2.9941652 | T15: =+IF(OR(O15="Blaze Shield II",O15="Cafco 400",O15="Cafco 300"),'CALCULO MORTERO'!N16," ") | U15: =+IF(OR(O15="Blaze Shield II",O15="Cafco 400",O15="Cafco 300"),'CALCULO MORTERO'!O16," ") | V15: {=_xlfn.IFS(O15="Blaze Shield II",'CALCULO MORTERO'!P16, O15="Cafco 400",'CALCULO MORTERO'!Q16,O15="Cafco 300",'CALCULO MORTERO'!S16, AND(OR(O15="Fire tex 5090", O15="Fire Tex 5062", O15="Fire Tex 5120", O15="Fire Control"),Q15>0), "CERT.",TRUE,"-")} -> CERT. | AM15: Fire Tex 5062
A16: ELEVACION EJE F | B16: 107-B | C16: PM1 | D16: PILAR | E16: MM 400X200X4 | F16: CJ | G16: 10 | H16: 1 | I16: 6000 | J16: 4 | K16: 1200 | L16: F-60 | M16: 236 | N16: =+IF(F16="","",(K16*I16*H16*G16)/1000000) -> 72 | O16: Fire Tex 5090 | P16: Software Idiem | Q16: =+IF(OR(O16="Fire Control",O16="Fire Tex 5062",O16="Fire Tex 5090",O16="Fire Tex 5120"),'CALCULO PINTURA'!P17," ") -> 2196 | R16: =+IF(OR(O16="Fire Control",O16="Fire Tex 5062",O16="Fire Tex 5090",O16="Fire Tex 5120"),'CALCULO PINTURA'!R17," ") -> 4.0077949 | S16: =+IF(OR(O16="Fire Control",O16="Fire Tex 5062",O16="Fire Tex 5090",O16="Fire Tex 5120"),'CALCULO PINTURA'!S17," ") -> 17.964991 | T16: =+IF(OR(O16="Blaze Shield II",O16="Cafco 400",O16="Cafco 300"),'CALCULO MORTERO'!N17," ") | U16: =+IF(OR(O16="Blaze Shield II",O16="Cafco 400",O16="Cafco 300"),'CALCULO MORTERO'!O17," ") | V16: {=_xlfn.IFS(O16="Blaze Shield II",'CALCULO MORTERO'!P17, O16="Cafco 400",'CALCULO MORTERO'!Q17,O16="Cafco 300",'CALCULO MORTERO'!S17, AND(OR(O16="Fire tex 5090", O16="Fire Tex 5062", O16="Fire Tex 5120", O16="Fire Control"),Q16>0), "CERT.",TRUE,"-")} -> CERT.
A17: ELEVACION EJE F | B17: 107-B | C17: PM3 | D17: PILAR | E17: 150X150X5 | F17: CJ | G17: 2 | H17: 1 | I17: 4000 | J17: 4 | K17: 600 | L17: F-60 | M17: 200 | N17: =+IF(F17="","",(K17*I17*H17*G17)/1000000) -> 4.8 | O17: Fire Tex 5090 | P17: Software Idiem | Q17: =+IF(OR(O17="Fire Control",O17="Fire Tex 5062",O17="Fire Tex 5090",O17="Fire Tex 5120"),'CALCULO PINTURA'!P18," ") -> 1930 | R17: =+IF(OR(O17="Fire Control",O17="Fire Tex 5062",O17="Fire Tex 5090",O17="Fire Tex 5120"),'CALCULO PINTURA'!R18," ") -> 4.5601646 | S17: =+IF(OR(O17="Fire Control",O17="Fire Tex 5062",O17="Fire Tex 5090",O17="Fire Tex 5120"),'CALCULO PINTURA'!S18," ") -> 1.0525936 | T17: =+IF(OR(O17="Blaze Shield II",O17="Cafco 400",O17="Cafco 300"),'CALCULO MORTERO'!N18," ") | U17: =+IF(OR(O17="Blaze Shield II",O17="Cafco 400",O17="Cafco 300"),'CALCULO MORTERO'!O18," ") | V17: {=_xlfn.IFS(O17="Blaze Shield II",'CALCULO MORTERO'!P18, O17="Cafco 400",'CALCULO MORTERO'!Q18,O17="Cafco 300",'CALCULO MORTERO'!S18, AND(OR(O17="Fire tex 5090", O17="Fire Tex 5062", O17="Fire Tex 5120", O17="Fire Control"),Q17>0), "CERT.",TRUE,"-")} -> CERT.
A18: ELEVACION EJE F | B18: 107-B | C18: CJ200X100X3 | D18: PILAR | E18: 200X100X3 | F18: CJ | G18: 1 | H18: 1 | I18: 6200 | J18: 4 | K18: 600 | L18: F-60 | M18: 333 | N18: =+IF(F18="","",(K18*I18*H18*G18)/1000000) -> 3.72 | O18: Fire Tex 5090 | P18: Software Idiem | Q18: =+IF(OR(O18="Fire Control",O18="Fire Tex 5062",O18="Fire Tex 5090",O18="Fire Tex 5120"),'CALCULO PINTURA'!P19," ") -> 2828 | R18: =+IF(OR(O18="Fire Control",O18="Fire Tex 5062",O18="Fire Tex 5090",O18="Fire Tex 5120"),'CALCULO PINTURA'!R19," ") -> 3.1121349 | S18: =+IF(OR(O18="Fire Control",O18="Fire Tex 5062",O18="Fire Tex 5090",O18="Fire Tex 5120"),'CALCULO PINTURA'!S19," ") -> 1.1953209 | T18: =+IF(OR(O18="Blaze Shield II",O18="Cafco 400",O18="Cafco 300"),'CALCULO MORTERO'!N19," ") | U18: =+IF(OR(O18="Blaze Shield II",O18="Cafco 400",O18="Cafco 300"),'CALCULO MORTERO'!O19," ") | V18: {=_xlfn.IFS(O18="Blaze Shield II",'CALCULO MORTERO'!P19, O18="Cafco 400",'CALCULO MORTERO'!Q19,O18="Cafco 300",'CALCULO MORTERO'!S19, AND(OR(O18="Fire tex 5090", O18="Fire Tex 5062", O18="Fire Tex 5120", O18="Fire Control"),Q18>0), "CERT.",TRUE,"-")} -> CERT.
A19: ELEVACION EJE F | B19: 107-B | C19: PUNTAL. TIP | D19: PUNTAL | E19: 100X100X3 | F19: CJ | G19: 1 | H19: 1 | I19: 68200 | J19: 4 | K19: 400 | L19: F-60 | M19: 333 | N19: =+IF(F19="","",(K19*I19*H19*G19)/1000000) -> 27.28 | O19: Fire Tex 5090 | P19: Software Idiem | Q19: =+IF(OR(O19="Fire Control",O19="Fire Tex 5062",O19="Fire Tex 5090",O19="Fire Tex 5120"),'CALCULO PINTURA'!P20," ") -> 2828 | R19: =+IF(OR(O19="Fire Control",O19="Fire Tex 5062",O19="Fire Tex 5090",O19="Fire Tex 5120"),'CALCULO PINTURA'!R20," ") -> 3.1121349 | S19: =+IF(OR(O19="Fire Control",O19="Fire Tex 5062",O19="Fire Tex 5090",O19="Fire Tex 5120"),'CALCULO PINTURA'!S20," ") -> 8.7656868 | T19: =+IF(OR(O19="Blaze Shield II",O19="Cafco 400",O19="Cafco 300"),'CALCULO MORTERO'!N20," ") | U19: =+IF(OR(O19="Blaze Shield II",O19="Cafco 400",O19="Cafco 300"),'CALCULO MORTERO'!O20," ") | V19: {=_xlfn.IFS(O19="Blaze Shield II",'CALCULO MORTERO'!P20, O19="Cafco 400",'CALCULO MORTERO'!Q20,O19="Cafco 300",'CALCULO MORTERO'!S20, AND(OR(O19="Fire tex 5090", O19="Fire Tex 5062", O19="Fire Tex 5120", O19="Fire Control"),Q19>0), "CERT.",TRUE,"-")} -> CERT.
A20: ELEVACION EJE F | B20: 107-B | C20: ARRIOSTRA | D20: ARRIOSTRAMINETO VERTICAL | E20: 100X100X3 | F20: CJ | G20: 8 | H20: 1 | I20: 7500 | J20: 4 | K20: 400 | L20: F-60 | M20: 333 | N20: =+IF(F20="","",(K20*I20*H20*G20)/1000000) -> 24 | O20: Fire Tex 5090 | P20: Software Idiem | Q20: =+IF(OR(O20="Fire Control",O20="Fire Tex 5062",O20="Fire Tex 5090",O20="Fire Tex 5120"),'CALCULO PINTURA'!P21," ") -> 2828 | R20: =+IF(OR(O20="Fire Control",O20="Fire Tex 5062",O20="Fire Tex 5090",O20="Fire Tex 5120"),'CALCULO PINTURA'!R21," ") -> 3.1121349 | S20: =+IF(OR(O20="Fire Control",O20="Fire Tex 5062",O20="Fire Tex 5090",O20="Fire Tex 5120"),'CALCULO PINTURA'!S21," ") -> 7.7117479 | T20: =+IF(OR(O20="Blaze Shield II",O20="Cafco 400",O20="Cafco 300"),'CALCULO MORTERO'!N21," ") | U20: =+IF(OR(O20="Blaze Shield II",O20="Cafco 400",O20="Cafco 300"),'CALCULO MORTERO'!O21," ") | V20: {=_xlfn.IFS(O20="Blaze Shield II",'CALCULO MORTERO'!P21, O20="Cafco 400",'CALCULO MORTERO'!Q21,O20="Cafco 300",'CALCULO MORTERO'!S21, AND(OR(O20="Fire tex 5090", O20="Fire Tex 5062", O20="Fire Tex 5120", O20="Fire Control"),Q20>0), "CERT.",TRUE,"-")} -> CERT.
A21: ELEVACION EJE B | B21: 107-B | C21: PM2 | D21: PILAR | E21: 200X100X4 | F21: CJ | G21: 2 | H21: 1 | I21: 7500 | J21: 4 | K21: 600 | L21: F-60 | M21: 250 | N21: =+IF(F21="","",(K21*I21*H21*G21)/1000000) -> 9 | O21: Fire Tex 5090 | P21: Software Idiem | Q21: =+IF(OR(O21="Fire Control",O21="Fire Tex 5062",O21="Fire Tex 5090",O21="Fire Tex 5120"),'CALCULO PINTURA'!P22," ") -> 2262 | R21: =+IF(OR(O21="Fire Control",O21="Fire Tex 5062",O21="Fire Tex 5090",O21="Fire Tex 5120"),'CALCULO PINTURA'!R22," ") -> 3.8908566 | S21: =+IF(OR(O21="Fire Control",O21="Fire Tex 5062",O21="Fire Tex 5090",O21="Fire Tex 5120"),'CALCULO PINTURA'!S22," ") -> 2.3131153 | T21: =+IF(OR(O21="Blaze Shield II",O21="Cafco 400",O21="Cafco 300"),'CALCULO MORTERO'!N22," ") | U21: =+IF(OR(O21="Blaze Shield II",O21="Cafco 400",O21="Cafco 300"),'CALCULO MORTERO'!O22," ") | V21: {=_xlfn.IFS(O21="Blaze Shield II",'CALCULO MORTERO'!P22, O21="Cafco 400",'CALCULO MORTERO'!Q22,O21="Cafco 300",'CALCULO MORTERO'!S22, AND(OR(O21="Fire tex 5090", O21="Fire Tex 5062", O21="Fire Tex 5120", O21="Fire Control"),Q21>0), "CERT.",TRUE,"-")} -> CERT.
A22: ELEVACION EJE B | B22: 107-B | C22: PM3 | D22: PILAR | E22: 150X150X5 | F22: CJ | G22: 9 | H22: 1 | I22: 6400 | J22: 4 | K22: 600 | L22: F-60 | M22: 200 | N22: =+IF(F22="","",(K22*I22*H22*G22)/1000000) -> 34.56 | O22: Fire Tex 5090 | P22: Software Idiem | Q22: =+IF(OR(O22="Fire Control",O22="Fire Tex 5062",O22="Fire Tex 5090",O22="Fire Tex 5120"),'CALCULO PINTURA'!P23," ") -> 1930 | R22: =+IF(OR(O22="Fire Control",O22="Fire Tex 5062",O22="Fire Tex 5090",O22="Fire Tex 5120"),'CALCULO PINTURA'!R23," ") -> 4.5601646 | S22: =+IF(OR(O22="Fire Control",O22="Fire Tex 5062",O22="Fire Tex 5090",O22="Fire Tex 5120"),'CALCULO PINTURA'!S23," ") -> 7.5786739 | T22: =+IF(OR(O22="Blaze Shield II",O22="Cafco 400",O22="Cafco 300"),'CALCULO MORTERO'!N23," ") | U22: =+IF(OR(O22="Blaze Shield II",O22="Cafco 400",O22="Cafco 300"),'CALCULO MORTERO'!O23," ") | V22: {=_xlfn.IFS(O22="Blaze Shield II",'CALCULO MORTERO'!P23, O22="Cafco 400",'CALCULO MORTERO'!Q23,O22="Cafco 300",'CALCULO MORTERO'!S23, AND(OR(O22="Fire tex 5090", O22="Fire Tex 5062", O22="Fire Tex 5120", O22="Fire Control"),Q22>0), "CERT.",TRUE,"-")} -> CERT.
A23: ELEVACION EJE B | B23: 107-B | C23: PM3 | D23: PILAR | E23: 150X150X5 | F23: CJ | G23: 3 | H23: 1 | I23: 7500 | J23: 4 | K23: 600 | L23: F-60 | M23: 200 | N23: =+IF(F23="","",(K23*I23*H23*G23)/1000000) -> 13.5 | O23: Fire Tex 5090 | P23: Software Idiem | Q23: =+IF(OR(O23="Fire Control",O23="Fire Tex 5062",O23="Fire Tex 5090",O23="Fire Tex 5120"),'CALCULO PINTURA'!P24," ") -> 1930 | R23: =+IF(OR(O23="Fire Control",O23="Fire Tex 5062",O23="Fire Tex 5090",O23="Fire Tex 5120"),'CALCULO PINTURA'!R24," ") -> 4.5601646 | S23: =+IF(OR(O23="Fire Control",O23="Fire Tex 5062",O23="Fire Tex 5090",O23="Fire Tex 5120"),'CALCULO PINTURA'!S24," ") -> 2.9604195 | T23: =+IF(OR(O23="Blaze Shield II",O23="Cafco 400",O23="Cafco 300"),'CALCULO MORTERO'!N24," ") | U23: =+IF(OR(O23="Blaze Shield II",O23="Cafco 400",O23="Cafco 300"),'CALCULO MORTERO'!O24," ") | V23: {=_xlfn.IFS(O23="Blaze Shield II",'CALCULO MORTERO'!P24, O23="Cafco 400",'CALCULO MORTERO'!Q24,O23="Cafco 300",'CALCULO MORTERO'!S24, AND(OR(O23="Fire tex 5090", O23="Fire Tex 5062", O23="Fire Tex 5120", O23="Fire Control"),Q23>0), "CERT.",TRUE,"-")} -> CERT.
J24: 4 | N24: 0 | P24: Software Idiem | Q24: =+IF(OR(O24="Fire Control",O24="Fire Tex 5062",O24="Fire Tex 5090",O24="Fire Tex 5120"),'CALCULO PINTURA'!P25," ") | R24: =+IF(OR(O24="Fire Control",O24="Fire Tex 5062",O24="Fire Tex 5090",O24="Fire Tex 5120"),'CALCULO PINTURA'!R25," ") | S24: =+IF(OR(O24="Fire Control",O24="Fire Tex 5062",O24="Fire Tex 5090",O24="Fire Tex 5120"),'CALCULO PINTURA'!S25," ") | T24: =+IF(OR(O24="Blaze Shield II",O24="Cafco 400",O24="Cafco 300"),'CALCULO MORTERO'!N25," ") | U24: =+IF(OR(O24="Blaze Shield II",O24="Cafco 400",O24="Cafco 300"),'CALCULO MORTERO'!O25," ") | V24: {=_xlfn.IFS(O24="Blaze Shield II",'CALCULO MORTERO'!P25, O24="Cafco 400",'CALCULO MORTERO'!Q25,O24="Cafco 300",'CALCULO MORTERO'!S25, AND(OR(O24="Fire tex 5090", O24="Fire Tex 5062", O24="Fire Tex 5120", O24="Fire Control"),Q24>0), "CERT.",TRUE,"-")} -> -
J25: 4 | N25: 0 | P25: Software Idiem | Q25: =+IF(OR(O25="Fire Control",O25="Fire Tex 5062",O25="Fire Tex 5090",O25="Fire Tex 5120"),'CALCULO PINTURA'!P26," ") | R25: =+IF(OR(O25="Fire Control",O25="Fire Tex 5062",O25="Fire Tex 5090",O25="Fire Tex 5120"),'CALCULO PINTURA'!R26," ") | S25: =+IF(OR(O25="Fire Control",O25="Fire Tex 5062",O25="Fire Tex 5090",O25="Fire Tex 5120"),'CALCULO PINTURA'!S26," ") | T25: =+IF(OR(O25="Blaze Shield II",O25="Cafco 400",O25="Cafco 300"),'CALCULO MORTERO'!N26," ") | U25: =+IF(OR(O25="Blaze Shield II",O25="Cafco 400",O25="Cafco 300"),'CALCULO MORTERO'!O26," ") | V25: {=_xlfn.IFS(O25="Blaze Shield II",'CALCULO MORTERO'!P26, O25="Cafco 400",'CALCULO MORTERO'!Q26,O25="Cafco 300",'CALCULO MORTERO'!S26, AND(OR(O25="Fire tex 5090", O25="Fire Tex 5062", O25="Fire Tex 5120", O25="Fire Control"),Q25>0), "CERT.",TRUE,"-")} -> -
A26: ELEVACION EJE 10 | B26: 106-B | C26: M1 MM600X225X4 | D26: VIGA | E26: M1 MM600X225X4 | F26: CJ | G26: 2 | H26: 1 | I26: 15000 | J26: 4 | K26: 1650 | L26: F-60 | M26: 250 | N26: =+IF(F26="","",(K26*I26*H26*G26)/1000000) -> 49.5 | O26: Fire Tex 5090 | P26: Software Idiem | Q26: =+IF(OR(O26="Fire Control",O26="Fire Tex 5062",O26="Fire Tex 5090",O26="Fire Tex 5120"),'CALCULO PINTURA'!P27," ") -> 2262 | R26: =+IF(OR(O26="Fire Control",O26="Fire Tex 5062",O26="Fire Tex 5090",O26="Fire Tex 5120"),'CALCULO PINTURA'!R27," ") -> 3.8908566 | S26: =+IF(OR(O26="Fire Control",O26="Fire Tex 5062",O26="Fire Tex 5090",O26="Fire Tex 5120"),'CALCULO PINTURA'!S27," ") -> 12.722134 | T26: =+IF(OR(O26="Blaze Shield II",O26="Cafco 400",O26="Cafco 300"),'CALCULO MORTERO'!N27," ") | U26: =+IF(OR(O26="Blaze Shield II",O26="Cafco 400",O26="Cafco 300"),'CALCULO MORTERO'!O27," ") | V26: {=_xlfn.IFS(O26="Blaze Shield II",'CALCULO MORTERO'!P27, O26="Cafco 400",'CALCULO MORTERO'!Q27,O26="Cafco 300",'CALCULO MORTERO'!S27, AND(OR(O26="Fire tex 5090", O26="Fire Tex 5062", O26="Fire Tex 5120", O26="Fire Control"),Q26>0), "CERT.",TRUE,"-")} -> CERT.
A27: ELEVACION EJE 11 | B27: 106-B | C27: M1 MM600X225X4 | D27: VIGA | E27: M1 MM600X225X4 | F27: CJ | G27: 2 | H27: 1 | I27: 15000 | J27: 4 | K27: 1650 | L27: F-60 | M27: 250 | N27: =+IF(F27="","",(K27*I27*H27*G27)/1000000) -> 49.5 | O27: Fire Tex 5090 | P27: Software Idiem | Q27: =+IF(OR(O27="Fire Control",O27="Fire Tex 5062",O27="Fire Tex 5090",O27="Fire Tex 5120"),'CALCULO PINTURA'!P28," ") -> 2262 | R27: =+IF(OR(O27="Fire Control",O27="Fire Tex 5062",O27="Fire Tex 5090",O27="Fire Tex 5120"),'CALCULO PINTURA'!R28," ") -> 3.8908566 | S27: =+IF(OR(O27="Fire Control",O27="Fire Tex 5062",O27="Fire Tex 5090",O27="Fire Tex 5120"),'CALCULO PINTURA'!S28," ") -> 12.722134 | T27: =+IF(OR(O27="Blaze Shield II",O27="Cafco 400",O27="Cafco 300"),'CALCULO MORTERO'!N28," ") | U27: =+IF(OR(O27="Blaze Shield II",O27="Cafco 400",O27="Cafco 300"),'CALCULO MORTERO'!O28," ") | V27: {=_xlfn.IFS(O27="Blaze Shield II",'CALCULO MORTERO'!P28, O27="Cafco 400",'CALCULO MORTERO'!Q28,O27="Cafco 300",'CALCULO MORTERO'!S28, AND(OR(O27="Fire tex 5090", O27="Fire Tex 5062", O27="Fire Tex 5120", O27="Fire Control"),Q27>0), "CERT.",TRUE,"-")} -> CERT.
A28: ELEVACION EJE 02 | B28: 106-B | C28: M1 MM600X225X4 | D28: VIGA | E28: M1 MM600X225X4 | F28: CJ | G28: 2 | H28: 1 | I28: 15000 | J28: 4 | K28: 1650 | L28: F-60 | M28: 250 | N28: =+IF(F28="","",(K28*I28*H28*G28)/1000000) -> 49.5 | O28: Fire Tex 5090 | P28: Software Idiem | Q28: =+IF(OR(O28="Fire Control",O28="Fire Tex 5062",O28="Fire Tex 5090",O28="Fire Tex 5120"),'CALCULO PINTURA'!P29," ") -> 2262 | R28: =+IF(OR(O28="Fire Control",O28="Fire Tex 5062",O28="Fire Tex 5090",O28="Fire Tex 5120"),'CALCULO PINTURA'!R29," ") -> 3.8908566 | S28: =+IF(OR(O28="Fire Control",O28="Fire Tex 5062",O28="Fire Tex 5090",O28="Fire Tex 5120"),'CALCULO PINTURA'!S29," ") -> 12.722134 | T28: =+IF(OR(O28="Blaze Shield II",O28="Cafco 400",O28="Cafco 300"),'CALCULO MORTERO'!N29," ") | U28: =+IF(OR(O28="Blaze Shield II",O28="Cafco 400",O28="Cafco 300"),'CALCULO MORTERO'!O29," ") | V28: {=_xlfn.IFS(O28="Blaze Shield II",'CALCULO MORTERO'!P29, O28="Cafco 400",'CALCULO MORTERO'!Q29,O28="Cafco 300",'CALCULO MORTERO'!S29, AND(OR(O28="Fire tex 5090", O28="Fire Tex 5062", O28="Fire Tex 5120", O28="Fire Control"),Q28>0), "CERT.",TRUE,"-")} -> CERT.
A29: ELEVACION EJES 3, 4, 5, 6, 7,8 , 9 | B29: 106-B | C29: M1 MM600X225X4 | D29: VIGA | E29: M1 MM600X225X4 | F29: CJ | G29: 2 | H29: 7 | I29: 15000 | J29: 4 | K29: 1650 | L29: F-60 | M29: 250 | N29: =+IF(F29="","",(K29*I29*H29*G29)/1000000) -> 346.5 | O29: Fire Tex 5090 | P29: Software Idiem | Q29: =+IF(OR(O29="Fire Control",O29="Fire Tex 5062",O29="Fire Tex 5090",O29="Fire Tex 5120"),'CALCULO PINTURA'!P30," ") -> 2262 | R29: =+IF(OR(O29="Fire Control",O29="Fire Tex 5062",O29="Fire Tex 5090",O29="Fire Tex 5120"),'CALCULO PINTURA'!R30," ") -> 3.8908566 | S29: =+IF(OR(O29="Fire Control",O29="Fire Tex 5062",O29="Fire Tex 5090",O29="Fire Tex 5120"),'CALCULO PINTURA'!S30," ") -> 89.05494 | T29: =+IF(OR(O29="Blaze Shield II",O29="Cafco 400",O29="Cafco 300"),'CALCULO MORTERO'!N30," ") | U29: =+IF(OR(O29="Blaze Shield II",O29="Cafco 400",O29="Cafco 300"),'CALCULO MORTERO'!O30," ") | V29: {=_xlfn.IFS(O29="Blaze Shield II",'CALCULO MORTERO'!P30, O29="Cafco 400",'CALCULO MORTERO'!Q30,O29="Cafco 300",'CALCULO MORTERO'!S30, AND(OR(O29="Fire tex 5090", O29="Fire Tex 5062", O29="Fire Tex 5120", O29="Fire Control"),Q29>0), "CERT.",TRUE,"-")} -> CERT.
A30: ELEVACION EJE 12 | B30: 106-B | C30: M1 MM600X225X4 | D30: VIGA | E30: M1 MM600X225X4 | F30: CJ | G30: 2 | H30: 7 | I30: 15000 | J30: 4 | K30: 1650 | L30: F-60 | M30: 250 | N30: =+IF(F30="","",(K30*I30*H30*G30)/1000000) -> 346.5 | O30: Fire Tex 5090 | P30: Software Idiem | Q30: =+IF(OR(O30="Fire Control",O30="Fire Tex 5062",O30="Fire Tex 5090",O30="Fire Tex 5120"),'CALCULO PINTURA'!P31," ") -> 2262 | R30: =+IF(OR(O30="Fire Control",O30="Fire Tex 5062",O30="Fire Tex 5090",O30="Fire Tex 5120"),'CALCULO PINTURA'!R31," ") -> 3.8908566 | S30: =+IF(OR(O30="Fire Control",O30="Fire Tex 5062",O30="Fire Tex 5090",O30="Fire Tex 5120"),'CALCULO PINTURA'!S31," ") -> 89.05494 | T30: =+IF(OR(O30="Blaze Shield II",O30="Cafco 400",O30="Cafco 300"),'CALCULO MORTERO'!N31," ") | U30: =+IF(OR(O30="Blaze Shield II",O30="Cafco 400",O30="Cafco 300"),'CALCULO MORTERO'!O31," ") | V30: {=_xlfn.IFS(O30="Blaze Shield II",'CALCULO MORTERO'!P31, O30="Cafco 400",'CALCULO MORTERO'!Q31,O30="Cafco 300",'CALCULO MORTERO'!S31, AND(OR(O30="Fire tex 5090", O30="Fire Tex 5062", O30="Fire Tex 5120", O30="Fire Control"),Q30>0), "CERT.",TRUE,"-")} -> CERT.
A31: ELEVACION EJE 12 | B31: 106-B | C31: PM2 | D31: PILAR | E31: 200X100X4 | F31: CJ | G31: 2 | H31: 1 | I31: 6200 | J31: 4 | K31: 600 | L31: F-60 | M31: 250 | N31: =+IF(F31="","",(K31*I31*H31*G31)/1000000) -> 7.44 | O31: Fire Tex 5090 | P31: Software Idiem | Q31: =+IF(OR(O31="Fire Control",O31="Fire Tex 5062",O31="Fire Tex 5090",O31="Fire Tex 5120"),'CALCULO PINTURA'!P32," ") -> 2262 | R31: =+IF(OR(O31="Fire Control",O31="Fire Tex 5062",O31="Fire Tex 5090",O31="Fire Tex 5120"),'CALCULO PINTURA'!R32," ") -> 3.8908566 | S31: =+IF(OR(O31="Fire Control",O31="Fire Tex 5062",O31="Fire Tex 5090",O31="Fire Tex 5120"),'CALCULO PINTURA'!S32," ") -> 1.9121753 | T31: =+IF(OR(O31="Blaze Shield II",O31="Cafco 400",O31="Cafco 300"),'CALCULO MORTERO'!N32," ") | U31: =+IF(OR(O31="Blaze Shield II",O31="Cafco 400",O31="Cafco 300"),'CALCULO MORTERO'!O32," ") | V31: {=_xlfn.IFS(O31="Blaze Shield II",'CALCULO MORTERO'!P32, O31="Cafco 400",'CALCULO MORTERO'!Q32,O31="Cafco 300",'CALCULO MORTERO'!S32, AND(OR(O31="Fire tex 5090", O31="Fire Tex 5062", O31="Fire Tex 5120", O31="Fire Control"),Q31>0), "CERT.",TRUE,"-")} -> CERT.
A32: ELEVACION EJE 12 | B32: 106-B | C32: PM2 | D32: PILAR | E32: 200X100X4 | F32: CJ | G32: 1 | H32: 1 | I32: 7500 | J32: 4 | K32: 600 | L32: F-60 | M32: 250 | N32: =+IF(F32="","",(K32*I32*H32*G32)/1000000) -> 4.5 | O32: Fire Tex 5090 | P32: Software Idiem | Q32: =+IF(OR(O32="Fire Control",O32="Fire Tex 5062",O32="Fire Tex 5090",O32="Fire Tex 5120"),'CALCULO PINTURA'!P33," ") -> 2262 | R32: =+IF(OR(O32="Fire Control",O32="Fire Tex 5062",O32="Fire Tex 5090",O32="Fire Tex 5120"),'CALCULO PINTURA'!R33," ") -> 3.8908566 | S32: =+IF(OR(O32="Fire Control",O32="Fire Tex 5062",O32="Fire Tex 5090",O32="Fire Tex 5120"),'CALCULO PINTURA'!S33," ") -> 1.1565577 | T32: =+IF(OR(O32="Blaze Shield II",O32="Cafco 400",O32="Cafco 300"),'CALCULO MORTERO'!N33," ") | U32: =+IF(OR(O32="Blaze Shield II",O32="Cafco 400",O32="Cafco 300"),'CALCULO MORTERO'!O33," ") | V32: {=_xlfn.IFS(O32="Blaze Shield II",'CALCULO MORTERO'!P33, O32="Cafco 400",'CALCULO MORTERO'!Q33,O32="Cafco 300",'CALCULO MORTERO'!S33, AND(OR(O32="Fire tex 5090", O32="Fire Tex 5062", O32="Fire Tex 5120", O32="Fire Control"),Q32>0), "CERT.",TRUE,"-")} -> CERT.
A33: ELEVACION EJE 12 | B33: 106-B | C33: CJ200X100X3 | D33: PILAR | E33: 200X100X3 | F33: CJ | G33: 1 | H33: 1 | I33: 15000 | J33: 4 | K33: 600 | L33: F-60 | M33: 333 | N33: =+IF(F33="","",(K33*I33*H33*G33)/1000000) -> 9 | O33: Fire Tex 5090 | P33: Software Idiem | Q33: =+IF(OR(O33="Fire Control",O33="Fire Tex 5062",O33="Fire Tex 5090",O33="Fire Tex 5120"),'CALCULO PINTURA'!P34," ") -> 2828 | R33: =+IF(OR(O33="Fire Control",O33="Fire Tex 5062",O33="Fire Tex 5090",O33="Fire Tex 5120"),'CALCULO PINTURA'!R34," ") -> 3.1121349 | S33: =+IF(OR(O33="Fire Control",O33="Fire Tex 5062",O33="Fire Tex 5090",O33="Fire Tex 5120"),'CALCULO PINTURA'!S34," ") -> 2.8919055 | T33: =+IF(OR(O33="Blaze Shield II",O33="Cafco 400",O33="Cafco 300"),'CALCULO MORTERO'!N34," ") | U33: =+IF(OR(O33="Blaze Shield II",O33="Cafco 400",O33="Cafco 300"),'CALCULO MORTERO'!O34," ") | V33: {=_xlfn.IFS(O33="Blaze Shield II",'CALCULO MORTERO'!P34, O33="Cafco 400",'CALCULO MORTERO'!Q34,O33="Cafco 300",'CALCULO MORTERO'!S34, AND(OR(O33="Fire tex 5090", O33="Fire Tex 5062", O33="Fire Tex 5120", O33="Fire Control"),Q33>0), "CERT.",TRUE,"-")} -> CERT.
A34: ELEVACION EJE 12 | B34: 106-B | C34: PM3 | D34: PILAR | E34: 150X150X5 | F34: CJ | G34: 4 | H34: 1 | I34: 4000 | J34: 4 | K34: 600 | L34: F-60 | M34: 200 | N34: =+IF(F34="","",(K34*I34*H34*G34)/1000000) -> 9.6 | O34: Fire Tex 5090 | P34: Software Idiem | Q34: =+IF(OR(O34="Fire Control",O34="Fire Tex 5062",O34="Fire Tex 5090",O34="Fire Tex 5120"),'CALCULO PINTURA'!P35," ") -> 1930 | R34: =+IF(OR(O34="Fire Control",O34="Fire Tex 5062",O34="Fire Tex 5090",O34="Fire Tex 5120"),'CALCULO PINTURA'!R35," ") -> 4.5601646 | S34: =+IF(OR(O34="Fire Control",O34="Fire Tex 5062",O34="Fire Tex 5090",O34="Fire Tex 5120"),'CALCULO PINTURA'!S35," ") -> 2.1051872 | T34: =+IF(OR(O34="Blaze Shield II",O34="Cafco 400",O34="Cafco 300"),'CALCULO MORTERO'!N35," ") | U34: =+IF(OR(O34="Blaze Shield II",O34="Cafco 400",O34="Cafco 300"),'CALCULO MORTERO'!O35," ") | V34: {=_xlfn.IFS(O34="Blaze Shield II",'CALCULO MORTERO'!P35, O34="Cafco 400",'CALCULO MORTERO'!Q35,O34="Cafco 300",'CALCULO MORTERO'!S35, AND(OR(O34="Fire tex 5090", O34="Fire Tex 5062", O34="Fire Tex 5120", O34="Fire Control"),Q34>0), "CERT.",TRUE,"-")} -> CERT.
A35: ELEVACION EJE 1 | B35: 106-B | C35: PM2 | D35: PILAR | E35: 200X100X4 | F35: CJ | G35: 1 | H35: 1 | I35: 8000 | J35: 4 | K35: 600 | L35: F-60 | M35: 250 | N35: =+IF(F35="","",(K35*I35*H35*G35)/1000000) -> 4.8 | O35: Fire Tex 5090 | P35: Software Idiem | Q35: =+IF(OR(O35="Fire Control",O35="Fire Tex 5062",O35="Fire Tex 5090",O35="Fire Tex 5120"),'CALCULO PINTURA'!P36," ") -> 2262 | R35: =+IF(OR(O35="Fire Control",O35="Fire Tex 5062",O35="Fire Tex 5090",O35="Fire Tex 5120"),'CALCULO PINTURA'!R36," ") -> 3.8908566 | S35: =+IF(OR(O35="Fire Control",O35="Fire Tex 5062",O35="Fire Tex 5090",O35="Fire Tex 5120"),'CALCULO PINTURA'!S36," ") -> 1.2336615 | T35: =+IF(OR(O35="Blaze Shield II",O35="Cafco 400",O35="Cafco 300"),'CALCULO MORTERO'!N36," ") | U35: =+IF(OR(O35="Blaze Shield II",O35="Cafco 400",O35="Cafco 300"),'CALCULO MORTERO'!O36," ") | V35: {=_xlfn.IFS(O35="Blaze Shield II",'CALCULO MORTERO'!P36, O35="Cafco 400",'CALCULO MORTERO'!Q36,O35="Cafco 300",'CALCULO MORTERO'!S36, AND(OR(O35="Fire tex 5090", O35="Fire Tex 5062", O35="Fire Tex 5120", O35="Fire Control"),Q35>0), "CERT.",TRUE,"-")} -> CERT.
A36: ELEVACION EJE 1 | B36: 106-B | C36: PM2 | D36: PILAR | E36: 200X100X4 | F36: CJ | G36: 1 | H36: 1 | I36: 7500 | J36: 4 | K36: 600 | L36: F-60 | M36: 250 | N36: =+IF(F36="","",(K36*I36*H36*G36)/1000000) -> 4.5 | O36: Fire Tex 5090 | P36: Software Idiem | Q36: =+IF(OR(O36="Fire Control",O36="Fire Tex 5062",O36="Fire Tex 5090",O36="Fire Tex 5120"),'CALCULO PINTURA'!P37," ") -> 2262 | R36: =+IF(OR(O36="Fire Control",O36="Fire Tex 5062",O36="Fire Tex 5090",O36="Fire Tex 5120"),'CALCULO PINTURA'!R37," ") -> 3.8908566 | S36: =+IF(OR(O36="Fire Control",O36="Fire Tex 5062",O36="Fire Tex 5090",O36="Fire Tex 5120"),'CALCULO PINTURA'!S37," ") -> 1.1565577 | T36: =+IF(OR(O36="Blaze Shield II",O36="Cafco 400",O36="Cafco 300"),'CALCULO MORTERO'!N37," ") | U36: =+IF(OR(O36="Blaze Shield II",O36="Cafco 400",O36="Cafco 300"),'CALCULO MORTERO'!O37," ") | V36: {=_xlfn.IFS(O36="Blaze Shield II",'CALCULO MORTERO'!P37, O36="Cafco 400",'CALCULO MORTERO'!Q37,O36="Cafco 300",'CALCULO MORTERO'!S37, AND(OR(O36="Fire tex 5090", O36="Fire Tex 5062", O36="Fire Tex 5120", O36="Fire Control"),Q36>0), "CERT.",TRUE,"-")} -> CERT.
A37: ELEVACION EJE 1 | B37: 106-B | C37: PM2 | D37: PILAR | E37: 200X100X4 | F37: CJ | G37: 1 | H37: 1 | I37: 6500 | J37: 4 | K37: 600 | L37: F-60 | M37: 250 | N37: =+IF(F37="","",(K37*I37*H37*G37)/1000000) -> 3.9 | O37: Fire Tex 5090 | P37: Software Idiem | Q37: =+IF(OR(O37="Fire Control",O37="Fire Tex 5062",O37="Fire Tex 5090",O37="Fire Tex 5120"),'CALCULO PINTURA'!P38," ") -> 2262 | R37: =+IF(OR(O37="Fire Control",O37="Fire Tex 5062",O37="Fire Tex 5090",O37="Fire Tex 5120"),'CALCULO PINTURA'!R38," ") -> 3.8908566 | S37: =+IF(OR(O37="Fire Control",O37="Fire Tex 5062",O37="Fire Tex 5090",O37="Fire Tex 5120"),'CALCULO PINTURA'!S38," ") -> 1.00235 | T37: =+IF(OR(O37="Blaze Shield II",O37="Cafco 400",O37="Cafco 300"),'CALCULO MORTERO'!N38," ") | U37: =+IF(OR(O37="Blaze Shield II",O37="Cafco 400",O37="Cafco 300"),'CALCULO MORTERO'!O38," ") | V37: {=_xlfn.IFS(O37="Blaze Shield II",'CALCULO MORTERO'!P38, O37="Cafco 400",'CALCULO MORTERO'!Q38,O37="Cafco 300",'CALCULO MORTERO'!S38, AND(OR(O37="Fire tex 5090", O37="Fire Tex 5062", O37="Fire Tex 5120", O37="Fire Control"),Q37>0), "CERT.",TRUE,"-")} -> CERT.
... A43: ELEVACION EJA 9A | B43: 106-B | C43: PM3 | D43: PILAR | E43: 150X150X5 | F43: CJ | G43: 1 | H43: 1 | I43: 6500 | J43: 4 | K43: 600 | L43: F-60 | M43: 200 | N43: =+IF(F43="","",(K43*I43*H43*G43)/1000000) -> 3.9 | O43: Fire Tex 5090 | P43: Software Idiem | Q43: =+IF(OR(O43="Fire Control",O43="Fire Tex 5062",O43="Fire Tex 5090",O43="Fire Tex 5120"),'CALCULO PINTURA'!P44," ") -> 1930 | R43: =+IF(OR(O43="Fire Control",O43="Fire Tex 5062",O43="Fire Tex 5090",O43="Fire Tex 5120"),'CALCULO PINTURA'!R44," ") -> 4.5601646 | S43: =+IF(OR(O43="Fire Control",O43="Fire Tex 5062",O43="Fire Tex 5090",O43="Fire Tex 5120"),'CALCULO PINTURA'!S44," ") -> 0.85523229 | T43: =+IF(OR(O43="Blaze Shield II",O43="Cafco 400",O43="Cafco 300"),'CALCULO MORTERO'!N44," ") | U43: =+IF(OR(O43="Blaze Shield II",O43="Cafco 400",O43="Cafco 300"),'CALCULO MORTERO'!O44," ") | V43: {=_xlfn.IFS(O43="Blaze Shield II",'CALCULO MORTERO'!P44, O43="Cafco 400",'CALCULO MORTERO'!Q44,O43="Cafco 300",'CALCULO MORTERO'!S44, AND(OR(O43="Fire tex 5090", O43="Fire Tex 5062", O43="Fire Tex 5120", O43="Fire Control"),Q43>0), "CERT.",TRUE,"-")} -> CERT.
J44: 4 | N44: 0 | P44: Software Idiem | Q44: =+IF(OR(O44="Fire Control",O44="Fire Tex 5062",O44="Fire Tex 5090",O44="Fire Tex 5120"),'CALCULO PINTURA'!P45," ") | R44: =+IF(OR(O44="Fire Control",O44="Fire Tex 5062",O44="Fire Tex 5090",O44="Fire Tex 5120"),'CALCULO PINTURA'!R45," ") | S44: =+IF(OR(O44="Fire Control",O44="Fire Tex 5062",O44="Fire Tex 5090",O44="Fire Tex 5120"),'CALCULO PINTURA'!S45," ") | T44: =+IF(OR(O44="Blaze Shield II",O44="Cafco 400",O44="Cafco 300"),'CALCULO MORTERO'!N45," ") | U44: =+IF(OR(O44="Blaze Shield II",O44="Cafco 400",O44="Cafco 300"),'CALCULO MORTERO'!O45," ") | V44: {=_xlfn.IFS(O44="Blaze Shield II",'CALCULO MORTERO'!P45, O44="Cafco 400",'CALCULO MORTERO'!Q45,O44="Cafco 300",'CALCULO MORTERO'!S45, AND(OR(O44="Fire tex 5090", O44="Fire Tex 5062", O44="Fire Tex 5120", O44="Fire Control"),Q44>0), "CERT.",TRUE,"-")} -> -
J45: 4 | N45: 0 | P45: Software Idiem | Q45: =+IF(OR(O45="Fire Control",O45="Fire Tex 5062",O45="Fire Tex 5090",O45="Fire Tex 5120"),'CALCULO PINTURA'!P46," ") | R45: =+IF(OR(O45="Fire Control",O45="Fire Tex 5062",O45="Fire Tex 5090",O45="Fire Tex 5120"),'CALCULO PINTURA'!R46," ") | S45: =+IF(OR(O45="Fire Control",O45="Fire Tex 5062",O45="Fire Tex 5090",O45="Fire Tex 5120"),'CALCULO PINTURA'!S46," ") | T45: =+IF(OR(O45="Blaze Shield II",O45="Cafco 400",O45="Cafco 300"),'CALCULO MORTERO'!N46," ") | U45: =+IF(OR(O45="Blaze Shield II",O45="Cafco 400",O45="Cafco 300"),'CALCULO MORTERO'!O46," ") | V45: {=_xlfn.IFS(O45="Blaze Shield II",'CALCULO MORTERO'!P46, O45="Cafco 400",'CALCULO MORTERO'!Q46,O45="Cafco 300",'CALCULO MORTERO'!S46, AND(OR(O45="Fire tex 5090", O45="Fire Tex 5062", O45="Fire Tex 5120", O45="Fire Control"),Q45>0), "CERT.",TRUE,"-")} -> -
A46: PLANTA TECHUMBRE | B46: 104-B | C46: COSTANERA TIP | D46: COSTANERA | E46: 125X50X15X2 | F46: C | G46: 28 | H46: 1 | I46: 68200 | J46: 3 | K46: 445 | L46: 60 | M46: 1057 | N46: =+IF(F46="","",(K46*I46*H46*G46)/1000000) -> 849.772 | O46: Blaze Shield II | P46: Software Idiem | Q46: =+IF(OR(O46="Fire Control",O46="Fire Tex 5062",O46="Fire Tex 5090",O46="Fire Tex 5120"),'CALCULO PINTURA'!P47," ") | R46: =+IF(OR(O46="Fire Control",O46="Fire Tex 5062",O46="Fire Tex 5090",O46="Fire Tex 5120"),'CALCULO PINTURA'!R47," ") | S46: =+IF(OR(O46="Fire Control",O46="Fire Tex 5062",O46="Fire Tex 5090",O46="Fire Tex 5120"),'CALCULO PINTURA'!S47," ") | T46: =+IF(OR(O46="Blaze Shield II",O46="Cafco 400",O46="Cafco 300"),'CALCULO MORTERO'!N47," ") -> 54 | U46: =+IF(OR(O46="Blaze Shield II",O46="Cafco 400",O46="Cafco 300"),'CALCULO MORTERO'!O47," ") -> 519.25542 | V46: {=_xlfn.IFS(O46="Blaze Shield II",'CALCULO MORTERO'!P47, O46="Cafco 400",'CALCULO MORTERO'!Q47,O46="Cafco 300",'CALCULO MORTERO'!S47, AND(OR(O46="Fire tex 5090", O46="Fire Tex 5062", O46="Fire Tex 5120", O46="Fire Control"),Q46>0), "CERT.",TRUE,"-")} -> NO CERT.
A47: ELEVACION EJE 1 | B47: 211-B | C47: VM3 | D47: VIGA | E47: 100X100X3 | F47: CJ | G47: 1 | H47: 1 | I47: 29210 | J47: 4 | K47: 400 | L47: F-60 | M47: 333 | N47: =+IF(F47="","",(K47*I47*H47*G47)/1000000) -> 11.684 | O47: Fire Tex 5090 | P47: Software Idiem | Q47: =+IF(OR(O47="Fire Control",O47="Fire Tex 5062",O47="Fire Tex 5090",O47="Fire Tex 5120"),'CALCULO PINTURA'!P48," ") -> 2828 | R47: =+IF(OR(O47="Fire Control",O47="Fire Tex 5062",O47="Fire Tex 5090",O47="Fire Tex 5120"),'CALCULO PINTURA'!R48," ") -> 3.1121349 | S47: =+IF(OR(O47="Fire Control",O47="Fire Tex 5062",O47="Fire Tex 5090",O47="Fire Tex 5120"),'CALCULO PINTURA'!S48," ") -> 3.7543359 | T47: =+IF(OR(O47="Blaze Shield II",O47="Cafco 400",O47="Cafco 300"),'CALCULO MORTERO'!N48," ") | U47: =+IF(OR(O47="Blaze Shield II",O47="Cafco 400",O47="Cafco 300"),'CALCULO MORTERO'!O48," ") | V47: {=_xlfn.IFS(O47="Blaze Shield II",'CALCULO MORTERO'!P48, O47="Cafco 400",'CALCULO MORTERO'!Q48,O47="Cafco 300",'CALCULO MORTERO'!S48, AND(OR(O47="Fire tex 5090", O47="Fire Tex 5062", O47="Fire Tex 5120", O47="Fire Control"),Q47>0), "CERT.",TRUE,"-")} -> CERT.
A48: ELEVACION EJE 1 | B48: 211-B | C48: PM1 | D48: PILAR | E48: MM 400X200X4 | F48: CJ | G48: 6 | H48: 1 | I48: 7000 | J48: 4 | K48: 1200 | L48: F-60 | M48: 236 | N48: =+IF(F48="","",(K48*I48*H48*G48)/1000000) -> 50.4 | O48: Fire Tex 5090 | P48: Software Idiem | Q48: =+IF(OR(O48="Fire Control",O48="Fire Tex 5062",O48="Fire Tex 5090",O48="Fire Tex 5120"),'CALCULO PINTURA'!P49," ") -> 2196 | R48: =+IF(OR(O48="Fire Control",O48="Fire Tex 5062",O48="Fire Tex 5090",O48="Fire Tex 5120"),'CALCULO PINTURA'!R49," ") -> 4.0077949 | S48: =+IF(OR(O48="Fire Control",O48="Fire Tex 5062",O48="Fire Tex 5090",O48="Fire Tex 5120"),'CALCULO PINTURA'!S49," ") -> 12.575494 | T48: =+IF(OR(O48="Blaze Shield II",O48="Cafco 400",O48="Cafco 300"),'CALCULO MORTERO'!N49," ") | U48: =+IF(OR(O48="Blaze Shield II",O48="Cafco 400",O48="Cafco 300"),'CALCULO MORTERO'!O49," ") | V48: {=_xlfn.IFS(O48="Blaze Shield II",'CALCULO MORTERO'!P49, O48="Cafco 400",'CALCULO MORTERO'!Q49,O48="Cafco 300",'CALCULO MORTERO'!S49, AND(OR(O48="Fire tex 5090", O48="Fire Tex 5062", O48="Fire Tex 5120", O48="Fire Control"),Q48>0), "CERT.",TRUE,"-")} -> CERT.
A49: ELEVACION EJE 1 | B49: 211-B | C49: PM3 | D49: PILAR | E49: 150X150X5 | F49: CJ | G49: 2 | H49: 1 | I49: 4000 | J49: 4 | K49: 600 | L49: F-60 | M49: 200 | N49: =+IF(F49="","",(K49*I49*H49*G49)/1000000) -> 4.8 | O49: Fire Tex 5090 | P49: Software Idiem | Q49: =+IF(OR(O49="Fire Control",O49="Fire Tex 5062",O49="Fire Tex 5090",O49="Fire Tex 5120"),'CALCULO PINTURA'!P50," ") -> 1930 | R49: =+IF(OR(O49="Fire Control",O49="Fire Tex 5062",O49="Fire Tex 5090",O49="Fire Tex 5120"),'CALCULO PINTURA'!R50," ") -> 4.5601646 | S49: =+IF(OR(O49="Fire Control",O49="Fire Tex 5062",O49="Fire Tex 5090",O49="Fire Tex 5120"),'CALCULO PINTURA'!S50," ") -> 1.0525936 | T49: =+IF(OR(O49="Blaze Shield II",O49="Cafco 400",O49="Cafco 300"),'CALCULO MORTERO'!N50," ") | U49: =+IF(OR(O49="Blaze Shield II",O49="Cafco 400",O49="Cafco 300"),'CALCULO MORTERO'!O50," ") | V49: {=_xlfn.IFS(O49="Blaze Shield II",'CALCULO MORTERO'!P50, O49="Cafco 400",'CALCULO MORTERO'!Q50,O49="Cafco 300",'CALCULO MORTERO'!S50, AND(OR(O49="Fire tex 5090", O49="Fire Tex 5062", O49="Fire Tex 5120", O49="Fire Control"),Q49>0), "CERT.",TRUE,"-")} -> CERT.
A50: ELEVACION EJE 1 | B50: 211-B | C50: VM2 IPE 200 | D50: VIGA BAJO LOSA | E50: 200X100X8,5X5,6 | F50: CJ | G50: 1 | H50: 1 | I50: 29210 | J50: 3 | K50: 723 | L50: 60 | M50: 265 | N50: =+IF(F50="","",(K50*I50*H50*G50)/1000000) -> 21.11883 | O50: Blaze Shield II | P50: Software Idiem | Q50: =+IF(OR(O50="Fire Control",O50="Fire Tex 5062",O50="Fire Tex 5090",O50="Fire Tex 5120"),'CALCULO PINTURA'!P51," ") | R50: =+IF(OR(O50="Fire Control",O50="Fire Tex 5062",O50="Fire Tex 5090",O50="Fire Tex 5120"),'CALCULO PINTURA'!R51," ") | S50: =+IF(OR(O50="Fire Control",O50="Fire Tex 5062",O50="Fire Tex 5090",O50="Fire Tex 5120"),'CALCULO PINTURA'!S51," ") | T50: =+IF(OR(O50="Blaze Shield II",O50="Cafco 400",O50="Cafco 300"),'CALCULO MORTERO'!N51," ") -> 35 | U50: =+IF(OR(O50="Blaze Shield II",O50="Cafco 400",O50="Cafco 300"),'CALCULO MORTERO'!O51," ") -> 8.3641682 | V50: {=_xlfn.IFS(O50="Blaze Shield II",'CALCULO MORTERO'!P51, O50="Cafco 400",'CALCULO MORTERO'!Q51,O50="Cafco 300",'CALCULO MORTERO'!S51, AND(OR(O50="Fire tex 5090", O50="Fire Tex 5062", O50="Fire Tex 5120", O50="Fire Control"),Q50>0), "CERT.",TRUE,"-")} -> CERT.
A51: ELEVACION EJE 1 | B51: 211-B | C51: ARRIOSTRA | D51: ARRIOSTRAMINETO VERTICAL | E51: 100X100X3 | F51: CJ | G51: 4 | H51: 1 | I51: 6700 | J51: 4 | K51: 400 | L51: F-60 | M51: 333 | N51: =+IF(F51="","",(K51*I51*H51*G51)/1000000) -> 10.72 | O51: Fire Tex 5090 | P51: Software Idiem | Q51: =+IF(OR(O51="Fire Control",O51="Fire Tex 5062",O51="Fire Tex 5090",O51="Fire Tex 5120"),'CALCULO PINTURA'!P52," ") -> 2828 | R51: =+IF(OR(O51="Fire Control",O51="Fire Tex 5062",O51="Fire Tex 5090",O51="Fire Tex 5120"),'CALCULO PINTURA'!R52," ") -> 3.1121349 | S51: =+IF(OR(O51="Fire Control",O51="Fire Tex 5062",O51="Fire Tex 5090",O51="Fire Tex 5120"),'CALCULO PINTURA'!S52," ") -> 3.4445807 | T51: =+IF(OR(O51="Blaze Shield II",O51="Cafco 400",O51="Cafco 300"),'CALCULO MORTERO'!N52," ") | U51: =+IF(OR(O51="Blaze Shield II",O51="Cafco 400",O51="Cafco 300"),'CALCULO MORTERO'!O52," ") | V51: {=_xlfn.IFS(O51="Blaze Shield II",'CALCULO MORTERO'!P52, O51="Cafco 400",'CALCULO MORTERO'!Q52,O51="Cafco 300",'CALCULO MORTERO'!S52, AND(OR(O51="Fire tex 5090", O51="Fire Tex 5062", O51="Fire Tex 5120", O51="Fire Control"),Q51>0), "CERT.",TRUE,"-")} -> CERT.
A52: ELEVACION EJE 1 | B52: 211-B | C52: CJ200X100X4 | D52: VIGA | E52: 200X100X4 | F52: CJ | G52: 1 | H52: 1 | I52: 2000 | J52: 4 | K52: 600 | L52: F-60 | M52: 250 | N52: =+IF(F52="","",(K52*I52*H52*G52)/1000000) -> 1.2 | O52: Fire Tex 5090 | P52: Software Idiem | Q52: =+IF(OR(O52="Fire Control",O52="Fire Tex 5062",O52="Fire Tex 5090",O52="Fire Tex 5120"),'CALCULO PINTURA'!P53," ") -> 2262 | R52: =+IF(OR(O52="Fire Control",O52="Fire Tex 5062",O52="Fire Tex 5090",O52="Fire Tex 5120"),'CALCULO PINTURA'!R53," ") -> 3.8908566 | S52: =+IF(OR(O52="Fire Control",O52="Fire Tex 5062",O52="Fire Tex 5090",O52="Fire Tex 5120"),'CALCULO PINTURA'!S53," ") -> 0.30841538 | T52: =+IF(OR(O52="Blaze Shield II",O52="Cafco 400",O52="Cafco 300"),'CALCULO MORTERO'!N53," ") | U52: =+IF(OR(O52="Blaze Shield II",O52="Cafco 400",O52="Cafco 300"),'CALCULO MORTERO'!O53," ") | V52: {=_xlfn.IFS(O52="Blaze Shield II",'CALCULO MORTERO'!P53, O52="Cafco 400",'CALCULO MORTERO'!Q53,O52="Cafco 300",'CALCULO MORTERO'!S53, AND(OR(O52="Fire tex 5090", O52="Fire Tex 5062", O52="Fire Tex 5120", O52="Fire Control"),Q52>0), "CERT.",TRUE,"-")} -> CERT.
A53: ELEVACION EJE 1 | B53: 211-B | C53: CJ100X100X3 | D53: VIGA | E53: 100X100X3 | F53: CJ | G53: 2 | H53: 1 | I53: 3400 | J53: 4 | K53: 400 | L53: F-60 | M53: 333 | N53: =+IF(F53="","",(K53*I53*H53*G53)/1000000) -> 2.72 | O53: Fire Tex 5090 | P53: Software Idiem | Q53: =+IF(OR(O53="Fire Control",O53="Fire Tex 5062",O53="Fire Tex 5090",O53="Fire Tex 5120"),'CALCULO PINTURA'!P54," ") -> 2828 | R53: =+IF(OR(O53="Fire Control",O53="Fire Tex 5062",O53="Fire Tex 5090",O53="Fire Tex 5120"),'CALCULO PINTURA'!R54," ") -> 3.1121349 | S53: =+IF(OR(O53="Fire Control",O53="Fire Tex 5062",O53="Fire Tex 5090",O53="Fire Tex 5120"),'CALCULO PINTURA'!S54," ") -> 0.87399809 | T53: =+IF(OR(O53="Blaze Shield II",O53="Cafco 400",O53="Cafco 300"),'CALCULO MORTERO'!N54," ") | U53: =+IF(OR(O53="Blaze Shield II",O53="Cafco 400",O53="Cafco 300"),'CALCULO MORTERO'!O54," ") | V53: {=_xlfn.IFS(O53="Blaze Shield II",'CALCULO MORTERO'!P54, O53="Cafco 400",'CALCULO MORTERO'!Q54,O53="Cafco 300",'CALCULO MORTERO'!S54, AND(OR(O53="Fire tex 5090", O53="Fire Tex 5062", O53="Fire Tex 5120", O53="Fire Control"),Q53>0), "CERT.",TRUE,"-")} -> CERT.
A54: ELEVACION EJE 1 | B54: 211-B | C54: CJ100X100X3 | D54: PILAR | E54: 100X100X3 | F54: CJ | G54: 1 | H54: 1 | I54: 1500 | J54: 4 | K54: 400 | L54: F-60 | M54: 333 | N54: =+IF(F54="","",(K54*I54*H54*G54)/1000000) -> 0.6 | O54: Fire Tex 5090 | P54: Software Idiem | Q54: =+IF(OR(O54="Fire Control",O54="Fire Tex 5062",O54="Fire Tex 5090",O54="Fire Tex 5120"),'CALCULO PINTURA'!P55," ") -> 2828 | R54: =+IF(OR(O54="Fire Control",O54="Fire Tex 5062",O54="Fire Tex 5090",O54="Fire Tex 5120"),'CALCULO PINTURA'!R55," ") -> 3.1121349 | S54: =+IF(OR(O54="Fire Control",O54="Fire Tex 5062",O54="Fire Tex 5090",O54="Fire Tex 5120"),'CALCULO PINTURA'!S55," ") -> 0.1927937 | T54: =+IF(OR(O54="Blaze Shield II",O54="Cafco 400",O54="Cafco 300"),'CALCULO MORTERO'!N55," ") | U54: =+IF(OR(O54="Blaze Shield II",O54="Cafco 400",O54="Cafco 300"),'CALCULO MORTERO'!O55," ") | V54: {=_xlfn.IFS(O54="Blaze Shield II",'CALCULO MORTERO'!P55, O54="Cafco 400",'CALCULO MORTERO'!Q55,O54="Cafco 300",'CALCULO MORTERO'!S55, AND(OR(O54="Fire tex 5090", O54="Fire Tex 5062", O54="Fire Tex 5120", O54="Fire Control"),Q54>0), "CERT.",TRUE,"-")} -> CERT.
A55: ELEVACION EJE 1 | B55: 211-B | C55: CJ100X100X3 | D55: PILAR | E55: 100X100X3 | F55: CJ | G55: 1 | H55: 1 | I55: 4000 | J55: 4 | K55: 400 | L55: F-60 | M55: 333 | N55: =+IF(F55="","",(K55*I55*H55*G55)/1000000) -> 1.6 | O55: Fire Tex 5090 | P55: Software Idiem | Q55: =+IF(OR(O55="Fire Control",O55="Fire Tex 5062",O55="Fire Tex 5090",O55="Fire Tex 5120"),'CALCULO PINTURA'!P56," ") -> 2828 | R55: =+IF(OR(O55="Fire Control",O55="Fire Tex 5062",O55="Fire Tex 5090",O55="Fire Tex 5120"),'CALCULO PINTURA'!R56," ") -> 3.1121349 | S55: =+IF(OR(O55="Fire Control",O55="Fire Tex 5062",O55="Fire Tex 5090",O55="Fire Tex 5120"),'CALCULO PINTURA'!S56," ") -> 0.51411653 | T55: =+IF(OR(O55="Blaze Shield II",O55="Cafco 400",O55="Cafco 300"),'CALCULO MORTERO'!N56," ") | U55: =+IF(OR(O55="Blaze Shield II",O55="Cafco 400",O55="Cafco 300"),'CALCULO MORTERO'!O56," ") | V55: {=_xlfn.IFS(O55="Blaze Shield II",'CALCULO MORTERO'!P56, O55="Cafco 400",'CALCULO MORTERO'!Q56,O55="Cafco 300",'CALCULO MORTERO'!S56, AND(OR(O55="Fire tex 5090", O55="Fire Tex 5062", O55="Fire Tex 5120", O55="Fire Control"),Q55>0), "CERT.",TRUE,"-")} -> CERT.
A56: ELEVACION EJE 1 | B56: 211-B | C56: ARRIOSTRA | D56: ARRIOSTRAMINETO VERTICAL | E56: 100X100X3 | F56: CJ | G56: 4 | H56: 1 | I56: 7200 | J56: 4 | K56: 400 | L56: F-60 | M56: 333 | N56: =+IF(F56="","",(K56*I56*H56*G56)/1000000) -> 11.52 | O56: Fire Tex 5090 | P56: Software Idiem | Q56: =+IF(OR(O56="Fire Control",O56="Fire Tex 5062",O56="Fire Tex 5090",O56="Fire Tex 5120"),'CALCULO PINTURA'!P57," ") -> 2828 | R56: =+IF(OR(O56="Fire Control",O56="Fire Tex 5062",O56="Fire Tex 5090",O56="Fire Tex 5120"),'CALCULO PINTURA'!R57," ") -> 3.1121349 | S56: =+IF(OR(O56="Fire Control",O56="Fire Tex 5062",O56="Fire Tex 5090",O56="Fire Tex 5120"),'CALCULO PINTURA'!S57," ") -> 3.701639 | T56: =+IF(OR(O56="Blaze Shield II",O56="Cafco 400",O56="Cafco 300"),'CALCULO MORTERO'!N57," ") | U56: =+IF(OR(O56="Blaze Shield II",O56="Cafco 400",O56="Cafco 300"),'CALCULO MORTERO'!O57," ") | V56: {=_xlfn.IFS(O56="Blaze Shield II",'CALCULO MORTERO'!P57, O56="Cafco 400",'CALCULO MORTERO'!Q57,O56="Cafco 300",'CALCULO MORTERO'!S57, AND(OR(O56="Fire tex 5090", O56="Fire Tex 5062", O56="Fire Tex 5120", O56="Fire Control"),Q56>0), "CERT.",TRUE,"-")} -> CERT.
A57: ELEVACION EJE 1 | B57: 211-B | C57: CJ100X100X3 | D57: PILAR | E57: 100X100X3 | F57: CJ | G57: 1 | H57: 1 | I57: 3000 | J57: 4 | K57: 400 | L57: F-60 | M57: 333 | N57: =+IF(F57="","",(K57*I57*H57*G57)/1000000) -> 1.2 | O57: Fire Tex 5090 | P57: Software Idiem | Q57: =+IF(OR(O57="Fire Control",O57="Fire Tex 5062",O57="Fire Tex 5090",O57="Fire Tex 5120"),'CALCULO PINTURA'!P58," ") -> 2828 | R57: =+IF(OR(O57="Fire Control",O57="Fire Tex 5062",O57="Fire Tex 5090",O57="Fire Tex 5120"),'CALCULO PINTURA'!R58," ") -> 3.1121349 | S57: =+IF(OR(O57="Fire Control",O57="Fire Tex 5062",O57="Fire Tex 5090",O57="Fire Tex 5120"),'CALCULO PINTURA'!S58," ") -> 0.38558739 | T57: =+IF(OR(O57="Blaze Shield II",O57="Cafco 400",O57="Cafco 300"),'CALCULO MORTERO'!N58," ") | U57: =+IF(OR(O57="Blaze Shield II",O57="Cafco 400",O57="Cafco 300"),'CALCULO MORTERO'!O58," ") | V57: {=_xlfn.IFS(O57="Blaze Shield II",'CALCULO MORTERO'!P58, O57="Cafco 400",'CALCULO MORTERO'!Q58,O57="Cafco 300",'CALCULO MORTERO'!S58, AND(OR(O57="Fire tex 5090", O57="Fire Tex 5062", O57="Fire Tex 5120", O57="Fire Control"),Q57>0), "CERT.",TRUE,"-")} -> CERT.
A58: ELEVACION EJE 2 | B58: 211-B | C58: PM1 | D58: PILAR | E58: MM 400X200X4 | F58: CJ | G58: 6 | H58: 1 | I58: 8000 | J58: 4 | K58: 1200 | L58: F-60 | M58: 236 | N58: =+IF(F58="","",(K58*I58*H58*G58)/1000000) -> 57.6 | O58: Fire Tex 5090 | P58: Software Idiem | Q58: =+IF(OR(O58="Fire Control",O58="Fire Tex 5062",O58="Fire Tex 5090",O58="Fire Tex 5120"),'CALCULO PINTURA'!P59," ") -> 2196 | R58: =+IF(OR(O58="Fire Control",O58="Fire Tex 5062",O58="Fire Tex 5090",O58="Fire Tex 5120"),'CALCULO PINTURA'!R59," ") -> 4.0077949 | S58: =+IF(OR(O58="Fire Control",O58="Fire Tex 5062",O58="Fire Tex 5090",O58="Fire Tex 5120"),'CALCULO PINTURA'!S59," ") -> 14.371993 | T58: =+IF(OR(O58="Blaze Shield II",O58="Cafco 400",O58="Cafco 300"),'CALCULO MORTERO'!N59," ") | U58: =+IF(OR(O58="Blaze Shield II",O58="Cafco 400",O58="Cafco 300"),'CALCULO MORTERO'!O59," ") | V58: {=_xlfn.IFS(O58="Blaze Shield II",'CALCULO MORTERO'!P59, O58="Cafco 400",'CALCULO MORTERO'!Q59,O58="Cafco 300",'CALCULO MORTERO'!S59, AND(OR(O58="Fire tex 5090", O58="Fire Tex 5062", O58="Fire Tex 5120", O58="Fire Control"),Q58>0), "CERT.",TRUE,"-")} -> CERT.
A59: ELEVACION EJE 2 | B59: 211-B | C59: VM3 | D59: VIGA | E59: 100X100X3 | F59: CJ | G59: 1 | H59: 1 | I59: 29210 | J59: 4 | K59: 400 | L59: F-60 | M59: 333 | N59: =+IF(F59="","",(K59*I59*H59*G59)/1000000) -> 11.684 | O59: Fire Tex 5090 | P59: Software Idiem | Q59: =+IF(OR(O59="Fire Control",O59="Fire Tex 5062",O59="Fire Tex 5090",O59="Fire Tex 5120"),'CALCULO PINTURA'!P60," ") -> 2828 | R59: =+IF(OR(O59="Fire Control",O59="Fire Tex 5062",O59="Fire Tex 5090",O59="Fire Tex 5120"),'CALCULO PINTURA'!R60," ") -> 3.1121349 | S59: =+IF(OR(O59="Fire Control",O59="Fire Tex 5062",O59="Fire Tex 5090",O59="Fire Tex 5120"),'CALCULO PINTURA'!S60," ") -> 3.7543359 | T59: =+IF(OR(O59="Blaze Shield II",O59="Cafco 400",O59="Cafco 300"),'CALCULO MORTERO'!N60," ") | U59: =+IF(OR(O59="Blaze Shield II",O59="Cafco 400",O59="Cafco 300"),'CALCULO MORTERO'!O60," ") | V59: {=_xlfn.IFS(O59="Blaze Shield II",'CALCULO MORTERO'!P60, O59="Cafco 400",'CALCULO MORTERO'!Q60,O59="Cafco 300",'CALCULO MORTERO'!S60, AND(OR(O59="Fire tex 5090", O59="Fire Tex 5062", O59="Fire Tex 5120", O59="Fire Control"),Q59>0), "CERT.",TRUE,"-")} -> CERT.
A60: ELEVACION EJE 2 | B60: 211-B | C60: VM2 IPE 200 | D60: VIGA BAJO LOSA | E60: 200X100X8,5X5,6 | F60: CJ | G60: 1 | H60: 1 | I60: 29210 | J60: 3 | K60: 723 | L60: 60 | M60: 265 | N60: =+IF(F60="","",(K60*I60*H60*G60)/1000000) -> 21.11883 | O60: Blaze Shield II | P60: Software Idiem | Q60: =+IF(OR(O60="Fire Control",O60="Fire Tex 5062",O60="Fire Tex 5090",O60="Fire Tex 5120"),'CALCULO PINTURA'!P61," ") | R60: =+IF(OR(O60="Fire Control",O60="Fire Tex 5062",O60="Fire Tex 5090",O60="Fire Tex 5120"),'CALCULO PINTURA'!R61," ") | S60: =+IF(OR(O60="Fire Control",O60="Fire Tex 5062",O60="Fire Tex 5090",O60="Fire Tex 5120"),'CALCULO PINTURA'!S61," ") | T60: =+IF(OR(O60="Blaze Shield II",O60="Cafco 400",O60="Cafco 300"),'CALCULO MORTERO'!N61," ") -> 35 | U60: =+IF(OR(O60="Blaze Shield II",O60="Cafco 400",O60="Cafco 300"),'CALCULO MORTERO'!O61," ") -> 8.3641682 | V60: {=_xlfn.IFS(O60="Blaze Shield II",'CALCULO MORTERO'!P61, O60="Cafco 400",'CALCULO MORTERO'!Q61,O60="Cafco 300",'CALCULO MORTERO'!S61, AND(OR(O60="Fire tex 5090", O60="Fire Tex 5062", O60="Fire Tex 5120", O60="Fire Control"),Q60>0), "CERT.",TRUE,"-")} -> CERT.
A61: ELEVACION EJE 2 | B61: 211-B | C61: PM3 | D61: PILAR | E61: 150X150X5 | F61: CJ | G61: 2 | H61: 1 | I61: 4000 | J61: 4 | K61: 600 | L61: F-60 | M61: 200 | N61: =+IF(F61="","",(K61*I61*H61*G61)/1000000) -> 4.8 | O61: Fire Tex 5090 | P61: Software Idiem | Q61: =+IF(OR(O61="Fire Control",O61="Fire Tex 5062",O61="Fire Tex 5090",O61="Fire Tex 5120"),'CALCULO PINTURA'!P62," ") -> 1930 | R61: =+IF(OR(O61="Fire Control",O61="Fire Tex 5062",O61="Fire Tex 5090",O61="Fire Tex 5120"),'CALCULO PINTURA'!R62," ") -> 4.5601646 | S61: =+IF(OR(O61="Fire Control",O61="Fire Tex 5062",O61="Fire Tex 5090",O61="Fire Tex 5120"),'CALCULO PINTURA'!S62," ") -> 1.0525936 | T61: =+IF(OR(O61="Blaze Shield II",O61="Cafco 400",O61="Cafco 300"),'CALCULO MORTERO'!N62," ") | U61: =+IF(OR(O61="Blaze Shield II",O61="Cafco 400",O61="Cafco 300"),'CALCULO MORTERO'!O62," ") | V61: {=_xlfn.IFS(O61="Blaze Shield II",'CALCULO MORTERO'!P62, O61="Cafco 400",'CALCULO MORTERO'!Q62,O61="Cafco 300",'CALCULO MORTERO'!S62, AND(OR(O61="Fire tex 5090", O61="Fire Tex 5062", O61="Fire Tex 5120", O61="Fire Control"),Q61>0), "CERT.",TRUE,"-")} -> CERT.
A62: ELEVACION EJE 2 | B62: 211-B | C62: ARRIOSTRA | D62: ARRIOSTRAMINETO VERTICAL | E62: 100X100X3 | F62: CJ | G62: 4 | H62: 1 | I62: 7200 | J62: 4 | K62: 400 | L62: F-60 | M62: 333 | N62: =+IF(F62="","",(K62*I62*H62*G62)/1000000) -> 11.52 | O62: Fire Tex 5090 | P62: Software Idiem | Q62: =+IF(OR(O62="Fire Control",O62="Fire Tex 5062",O62="Fire Tex 5090",O62="Fire Tex 5120"),'CALCULO PINTURA'!P63," ") -> 2828 | R62: =+IF(OR(O62="Fire Control",O62="Fire Tex 5062",O62="Fire Tex 5090",O62="Fire Tex 5120"),'CALCULO PINTURA'!R63," ") -> 3.1121349 | S62: =+IF(OR(O62="Fire Control",O62="Fire Tex 5062",O62="Fire Tex 5090",O62="Fire Tex 5120"),'CALCULO PINTURA'!S63," ") -> 3.701639 | T62: =+IF(OR(O62="Blaze Shield II",O62="Cafco 400",O62="Cafco 300"),'CALCULO MORTERO'!N63," ") | U62: =+IF(OR(O62="Blaze Shield II",O62="Cafco 400",O62="Cafco 300"),'CALCULO MORTERO'!O63," ") | V62: {=_xlfn.IFS(O62="Blaze Shield II",'CALCULO MORTERO'!P63, O62="Cafco 400",'CALCULO MORTERO'!Q63,O62="Cafco 300",'CALCULO MORTERO'!S63, AND(OR(O62="Fire tex 5090", O62="Fire Tex 5062", O62="Fire Tex 5120", O62="Fire Control"),Q62>0), "CERT.",TRUE,"-")} -> CERT.
A63: ELEVACION EJE 2 | B63: 211-B | C63: ARRIOSTRA | D63: ARRIOSTRAMINETO VERTICAL | E63: 100X100X3 | F63: CJ | G63: 4 | H63: 1 | I63: 6700 | J63: 4 | K63: 400 | L63: F-60 | M63: 333 | N63: =+IF(F63="","",(K63*I63*H63*G63)/1000000) -> 10.72 | O63: Fire Tex 5090 | P63: Software Idiem | Q63: =+IF(OR(O63="Fire Control",O63="Fire Tex 5062",O63="Fire Tex 5090",O63="Fire Tex 5120"),'CALCULO PINTURA'!P64," ") -> 2828 | R63: =+IF(OR(O63="Fire Control",O63="Fire Tex 5062",O63="Fire Tex 5090",O63="Fire Tex 5120"),'CALCULO PINTURA'!R64," ") -> 3.1121349 | S63: =+IF(OR(O63="Fire Control",O63="Fire Tex 5062",O63="Fire Tex 5090",O63="Fire Tex 5120"),'CALCULO PINTURA'!S64," ") -> 3.4445807 | T63: =+IF(OR(O63="Blaze Shield II",O63="Cafco 400",O63="Cafco 300"),'CALCULO MORTERO'!N64," ") | U63: =+IF(OR(O63="Blaze Shield II",O63="Cafco 400",O63="Cafco 300"),'CALCULO MORTERO'!O64," ") | V63: {=_xlfn.IFS(O63="Blaze Shield II",'CALCULO MORTERO'!P64, O63="Cafco 400",'CALCULO MORTERO'!Q64,O63="Cafco 300",'CALCULO MORTERO'!S64, AND(OR(O63="Fire tex 5090", O63="Fire Tex 5062", O63="Fire Tex 5120", O63="Fire Control"),Q63>0), "CERT.",TRUE,"-")} -> CERT.
A64: ELEVACION EJE 2 | B64: 211-B | C64: ARRIOSTRA | D64: ARRIOSTRAMINETO VERTICAL | E64: 100X100X3 | F64: CJ | G64: 2 | H64: 1 | I64: 5800 | J64: 4 | K64: 400 | L64: F-60 | M64: 333 | N64: =+IF(F64="","",(K64*I64*H64*G64)/1000000) -> 4.64 | O64: Fire Tex 5090 | P64: Software Idiem | Q64: =+IF(OR(O64="Fire Control",O64="Fire Tex 5062",O64="Fire Tex 5090",O64="Fire Tex 5120"),'CALCULO PINTURA'!P65," ") -> 2828 | R64: =+IF(OR(O64="Fire Control",O64="Fire Tex 5062",O64="Fire Tex 5090",O64="Fire Tex 5120"),'CALCULO PINTURA'!R65," ") -> 3.1121349 | S64: =+IF(OR(O64="Fire Control",O64="Fire Tex 5062",O64="Fire Tex 5090",O64="Fire Tex 5120"),'CALCULO PINTURA'!S65," ") -> 1.4909379 | T64: =+IF(OR(O64="Blaze Shield II",O64="Cafco 400",O64="Cafco 300"),'CALCULO MORTERO'!N65," ") | U64: =+IF(OR(O64="Blaze Shield II",O64="Cafco 400",O64="Cafco 300"),'CALCULO MORTERO'!O65," ") | V64: {=_xlfn.IFS(O64="Blaze Shield II",'CALCULO MORTERO'!P65, O64="Cafco 400",'CALCULO MORTERO'!Q65,O64="Cafco 300",'CALCULO MORTERO'!S65, AND(OR(O64="Fire tex 5090", O64="Fire Tex 5062", O64="Fire Tex 5120", O64="Fire Control"),Q64>0), "CERT.",TRUE,"-")} -> CERT.
A65: ELEVACION EJE 2 | B65: 211-B | C65: ARRIOSTRA | D65: ARRIOSTRAMINETO VERTICAL | E65: 100X100X3 | F65: CJ | G65: 2 | H65: 1 | I65: 5250 | J65: 4 | K65: 400 | L65: F-60 | M65: 333 | N65: =+IF(F65="","",(K65*I65*H65*G65)/1000000) -> 4.2 | O65: Fire Tex 5090 | P65: Software Idiem | Q65: =+IF(OR(O65="Fire Control",O65="Fire Tex 5062",O65="Fire Tex 5090",O65="Fire Tex 5120"),'CALCULO PINTURA'!P66," ") -> 2828 | R65: =+IF(OR(O65="Fire Control",O65="Fire Tex 5062",O65="Fire Tex 5090",O65="Fire Tex 5120"),'CALCULO PINTURA'!R66," ") -> 3.1121349 | S65: =+IF(OR(O65="Fire Control",O65="Fire Tex 5062",O65="Fire Tex 5090",O65="Fire Tex 5120"),'CALCULO PINTURA'!S66," ") -> 1.3495559 | T65: =+IF(OR(O65="Blaze Shield II",O65="Cafco 400",O65="Cafco 300"),'CALCULO MORTERO'!N66," ") | U65: =+IF(OR(O65="Blaze Shield II",O65="Cafco 400",O65="Cafco 300"),'CALCULO MORTERO'!O66," ") | V65: {=_xlfn.IFS(O65="Blaze Shield II",'CALCULO MORTERO'!P66, O65="Cafco 400",'CALCULO MORTERO'!Q66,O65="Cafco 300",'CALCULO MORTERO'!S66, AND(OR(O65="Fire tex 5090", O65="Fire Tex 5062", O65="Fire Tex 5120", O65="Fire Control"),Q65>0), "CERT.",TRUE,"-")} -> CERT.
A66: ELEVACION EJE 3 | B66: 212-B | C66: PM1 | D66: PILAR | E66: MM 400X200X4 | F66: CJ | G66: 6 | H66: 1 | I66: 7000 | J66: 4 | K66: 1200 | L66: F-60 | M66: 236 | N66: =+IF(F66="","",(K66*I66*H66*G66)/1000000) -> 50.4 | O66: Fire Tex 5090 | P66: Software Idiem | Q66: =+IF(OR(O66="Fire Control",O66="Fire Tex 5062",O66="Fire Tex 5090",O66="Fire Tex 5120"),'CALCULO PINTURA'!P67," ") -> 2196 | R66: =+IF(OR(O66="Fire Control",O66="Fire Tex 5062",O66="Fire Tex 5090",O66="Fire Tex 5120"),'CALCULO PINTURA'!R67," ") -> 4.0077949 | S66: =+IF(OR(O66="Fire Control",O66="Fire Tex 5062",O66="Fire Tex 5090",O66="Fire Tex 5120"),'CALCULO PINTURA'!S67," ") -> 12.575494 | T66: =+IF(OR(O66="Blaze Shield II",O66="Cafco 400",O66="Cafco 300"),'CALCULO MORTERO'!N67," ") | U66: =+IF(OR(O66="Blaze Shield II",O66="Cafco 400",O66="Cafco 300"),'CALCULO MORTERO'!O67," ") | V66: {=_xlfn.IFS(O66="Blaze Shield II",'CALCULO MORTERO'!P67, O66="Cafco 400",'CALCULO MORTERO'!Q67,O66="Cafco 300",'CALCULO MORTERO'!S67, AND(OR(O66="Fire tex 5090", O66="Fire Tex 5062", O66="Fire Tex 5120", O66="Fire Control"),Q66>0), "CERT.",TRUE,"-")} -> CERT.
A67: ELEVACION EJE 3 | B67: 212-B | C67: VM3 | D67: VIGA | E67: 100X100X3 | F67: CJ | G67: 2 | H67: 1 | I67: 29210 | J67: 4 | K67: 400 | L67: F-60 | M67: 333 | N67: =+IF(F67="","",(K67*I67*H67*G67)/1000000) -> 23.368 | O67: Fire Tex 5090 | P67: Software Idiem | Q67: =+IF(OR(O67="Fire Control",O67="Fire Tex 5062",O67="Fire Tex 5090",O67="Fire Tex 5120"),'CALCULO PINTURA'!P68," ") -> 2828 | R67: =+IF(OR(O67="Fire Control",O67="Fire Tex 5062",O67="Fire Tex 5090",O67="Fire Tex 5120"),'CALCULO PINTURA'!R68," ") -> 3.1121349 | S67: =+IF(OR(O67="Fire Control",O67="Fire Tex 5062",O67="Fire Tex 5090",O67="Fire Tex 5120"),'CALCULO PINTURA'!S68," ") -> 7.5086719 | T67: =+IF(OR(O67="Blaze Shield II",O67="Cafco 400",O67="Cafco 300"),'CALCULO MORTERO'!N68," ") | U67: =+IF(OR(O67="Blaze Shield II",O67="Cafco 400",O67="Cafco 300"),'CALCULO MORTERO'!O68," ") | V67: {=_xlfn.IFS(O67="Blaze Shield II",'CALCULO MORTERO'!P68, O67="Cafco 400",'CALCULO MORTERO'!Q68,O67="Cafco 300",'CALCULO MORTERO'!S68, AND(OR(O67="Fire tex 5090", O67="Fire Tex 5062", O67="Fire Tex 5120", O67="Fire Control"),Q67>0), "CERT.",TRUE,"-")} -> CERT.
A68: ELEVACION EJE 3 | B68: 212-B | C68: CJ200X100X4 | D68: VIGA | E68: 200X100X4 | F68: CJ | G68: 1 | H68: 1 | I68: 2000 | J68: 4 | K68: 600 | L68: F-60 | M68: 250 | N68: =+IF(F68="","",(K68*I68*H68*G68)/1000000) -> 1.2 | O68: Fire Tex 5090 | P68: Software Idiem | Q68: =+IF(OR(O68="Fire Control",O68="Fire Tex 5062",O68="Fire Tex 5090",O68="Fire Tex 5120"),'CALCULO PINTURA'!P69," ") -> 2262 | R68: =+IF(OR(O68="Fire Control",O68="Fire Tex 5062",O68="Fire Tex 5090",O68="Fire Tex 5120"),'CALCULO PINTURA'!R69," ") -> 3.8908566 | S68: =+IF(OR(O68="Fire Control",O68="Fire Tex 5062",O68="Fire Tex 5090",O68="Fire Tex 5120"),'CALCULO PINTURA'!S69," ") -> 0.30841538 | T68: =+IF(OR(O68="Blaze Shield II",O68="Cafco 400",O68="Cafco 300"),'CALCULO MORTERO'!N69," ") | U68: =+IF(OR(O68="Blaze Shield II",O68="Cafco 400",O68="Cafco 300"),'CALCULO MORTERO'!O69," ") | V68: {=_xlfn.IFS(O68="Blaze Shield II",'CALCULO MORTERO'!P69, O68="Cafco 400",'CALCULO MORTERO'!Q69,O68="Cafco 300",'CALCULO MORTERO'!S69, AND(OR(O68="Fire tex 5090", O68="Fire Tex 5062", O68="Fire Tex 5120", O68="Fire Control"),Q68>0), "CERT.",TRUE,"-")} -> CERT.
A69: ELEVACION EJE 3 | B69: 212-B | C69: ARRIOSTRA | D69: ARRIOSTRAMINETO VERTICAL | E69: 100X100X3 | F69: CJ | G69: 8 | H69: 1 | I69: 6900 | J69: 4 | K69: 400 | L69: F-60 | M69: 333 | N69: =+IF(F69="","",(K69*I69*H69*G69)/1000000) -> 22.08 | O69: Fire Tex 5090 | P69: Software Idiem | Q69: =+IF(OR(O69="Fire Control",O69="Fire Tex 5062",O69="Fire Tex 5090",O69="Fire Tex 5120"),'CALCULO PINTURA'!P70," ") -> 2828 | R69: =+IF(OR(O69="Fire Control",O69="Fire Tex 5062",O69="Fire Tex 5090",O69="Fire Tex 5120"),'CALCULO PINTURA'!R70," ") -> 3.1121349 | S69: =+IF(OR(O69="Fire Control",O69="Fire Tex 5062",O69="Fire Tex 5090",O69="Fire Tex 5120"),'CALCULO PINTURA'!S70," ") -> 7.094808 | T69: =+IF(OR(O69="Blaze Shield II",O69="Cafco 400",O69="Cafco 300"),'CALCULO MORTERO'!N70," ") | U69: =+IF(OR(O69="Blaze Shield II",O69="Cafco 400",O69="Cafco 300"),'CALCULO MORTERO'!O70," ") | V69: {=_xlfn.IFS(O69="Blaze Shield II",'CALCULO MORTERO'!P70, O69="Cafco 400",'CALCULO MORTERO'!Q70,O69="Cafco 300",'CALCULO MORTERO'!S70, AND(OR(O69="Fire tex 5090", O69="Fire Tex 5062", O69="Fire Tex 5120", O69="Fire Control"),Q69>0), "CERT.",TRUE,"-")} -> CERT.
A70: ELEVACION EJE 3 | B70: 212-B | C70: ARRIOSTRA | D70: ARRIOSTRAMINETO VERTICAL | E70: 100X100X3 | F70: CJ | G70: 4 | H70: 1 | I70: 5800 | J70: 4 | K70: 400 | L70: F-60 | M70: 333 | N70: =+IF(F70="","",(K70*I70*H70*G70)/1000000) -> 9.28 | O70: Fire Tex 5090 | P70: Software Idiem | Q70: =+IF(OR(O70="Fire Control",O70="Fire Tex 5062",O70="Fire Tex 5090",O70="Fire Tex 5120"),'CALCULO PINTURA'!P71," ") -> 2828 | R70: =+IF(OR(O70="Fire Control",O70="Fire Tex 5062",O70="Fire Tex 5090",O70="Fire Tex 5120"),'CALCULO PINTURA'!R71," ") -> 3.1121349 | S70: =+IF(OR(O70="Fire Control",O70="Fire Tex 5062",O70="Fire Tex 5090",O70="Fire Tex 5120"),'CALCULO PINTURA'!S71," ") -> 2.9818758 | T70: =+IF(OR(O70="Blaze Shield II",O70="Cafco 400",O70="Cafco 300"),'CALCULO MORTERO'!N71," ") | U70: =+IF(OR(O70="Blaze Shield II",O70="Cafco 400",O70="Cafco 300"),'CALCULO MORTERO'!O71," ") | V70: {=_xlfn.IFS(O70="Blaze Shield II",'CALCULO MORTERO'!P71, O70="Cafco 400",'CALCULO MORTERO'!Q71,O70="Cafco 300",'CALCULO MORTERO'!S71, AND(OR(O70="Fire tex 5090", O70="Fire Tex 5062", O70="Fire Tex 5120", O70="Fire Control"),Q70>0), "CERT.",TRUE,"-")} -> CERT.
A71: ELEVACION EJE A-F | B71: 208-B | C71: M1 MM400X200X4 | D71: VIGA | E71: M1 MM400X200X4 | F71: CJ | G71: 2 | H71: 6 | I71: 11700 | J71: 4 | K71: 1200 | L71: F-60 | M71: 236 | N71: =+IF(F71="","",(K71*I71*H71*G71)/1000000) -> 168.48 | O71: Fire Tex 5090 | P71: Software Idiem | Q71: =+IF(OR(O71="Fire Control",O71="Fire Tex 5062",O71="Fire Tex 5090",O71="Fire Tex 5120"),'CALCULO PINTURA'!P72," ") -> 2196 | R71: =+IF(OR(O71="Fire Control",O71="Fire Tex 5062",O71="Fire Tex 5090",O71="Fire Tex 5120"),'CALCULO PINTURA'!R72," ") -> 4.0077949 | S71: =+IF(OR(O71="Fire Control",O71="Fire Tex 5062",O71="Fire Tex 5090",O71="Fire Tex 5120"),'CALCULO PINTURA'!S72," ") -> 42.038079 | T71: =+IF(OR(O71="Blaze Shield II",O71="Cafco 400",O71="Cafco 300"),'CALCULO MORTERO'!N72," ") | U71: =+IF(OR(O71="Blaze Shield II",O71="Cafco 400",O71="Cafco 300"),'CALCULO MORTERO'!O72," ") | V71: {=_xlfn.IFS(O71="Blaze Shield II",'CALCULO MORTERO'!P72, O71="Cafco 400",'CALCULO MORTERO'!Q72,O71="Cafco 300",'CALCULO MORTERO'!S72, AND(OR(O71="Fire tex 5090", O71="Fire Tex 5062", O71="Fire Tex 5120", O71="Fire Control"),Q71>0), "CERT.",TRUE,"-")} -> CERT.
A72: ELEVACION A | B72: 208-B | C72: PM2 | D72: PILAR | E72: 200X100X4 | F72: CJ | G72: 3 | H72: 1 | I72: 7100 | J72: 4 | K72: 600 | L72: F-60 | M72: 250 | N72: =+IF(F72="","",(K72*I72*H72*G72)/1000000) -> 12.78 | O72: Fire Tex 5090 | P72: Software Idiem | Q72: =+IF(OR(O72="Fire Control",O72="Fire Tex 5062",O72="Fire Tex 5090",O72="Fire Tex 5120"),'CALCULO PINTURA'!P73," ") -> 2262 | R72: =+IF(OR(O72="Fire Control",O72="Fire Tex 5062",O72="Fire Tex 5090",O72="Fire Tex 5120"),'CALCULO PINTURA'!R73," ") -> 3.8908566 | S72: =+IF(OR(O72="Fire Control",O72="Fire Tex 5062",O72="Fire Tex 5090",O72="Fire Tex 5120"),'CALCULO PINTURA'!S73," ") -> 3.2846238 | T72: =+IF(OR(O72="Blaze Shield II",O72="Cafco 400",O72="Cafco 300"),'CALCULO MORTERO'!N73," ") | U72: =+IF(OR(O72="Blaze Shield II",O72="Cafco 400",O72="Cafco 300"),'CALCULO MORTERO'!O73," ") | V72: {=_xlfn.IFS(O72="Blaze Shield II",'CALCULO MORTERO'!P73, O72="Cafco 400",'CALCULO MORTERO'!Q73,O72="Cafco 300",'CALCULO MORTERO'!S73, AND(OR(O72="Fire tex 5090", O72="Fire Tex 5062", O72="Fire Tex 5120", O72="Fire Control"),Q72>0), "CERT.",TRUE,"-")} -> CERT.
... A79: ELEVACION EJE C | B79: 209-B | C79: PM3 | D79: PILAR | E79: 150X150X5 | F79: CJ | G79: 1 | H79: 1 | I79: 4000 | J79: 4 | K79: 600 | L79: F-60 | M79: 200 | N79: =+IF(F79="","",(K79*I79*H79*G79)/1000000) -> 2.4 | O79: Fire Tex 5090 | P79: Software Idiem | Q79: =+IF(OR(O79="Fire Control",O79="Fire Tex 5062",O79="Fire Tex 5090",O79="Fire Tex 5120"),'CALCULO PINTURA'!P80," ") -> 1930 | R79: =+IF(OR(O79="Fire Control",O79="Fire Tex 5062",O79="Fire Tex 5090",O79="Fire Tex 5120"),'CALCULO PINTURA'!R80," ") -> 4.5601646 | S79: =+IF(OR(O79="Fire Control",O79="Fire Tex 5062",O79="Fire Tex 5090",O79="Fire Tex 5120"),'CALCULO PINTURA'!S80," ") -> 0.5262968 | T79: =+IF(OR(O79="Blaze Shield II",O79="Cafco 400",O79="Cafco 300"),'CALCULO MORTERO'!N80," ") | U79: =+IF(OR(O79="Blaze Shield II",O79="Cafco 400",O79="Cafco 300"),'CALCULO MORTERO'!O80," ") | V79: {=_xlfn.IFS(O79="Blaze Shield II",'CALCULO MORTERO'!P80, O79="Cafco 400",'CALCULO MORTERO'!Q80,O79="Cafco 300",'CALCULO MORTERO'!S80, AND(OR(O79="Fire tex 5090", O79="Fire Tex 5062", O79="Fire Tex 5120", O79="Fire Control"),Q79>0), "CERT.",TRUE,"-")} -> CERT.
A80: ELEVACION EJE C | B80: 209-B | C80: VM1 IPE 240 | D80: VIGA BAJO LOSA | E80: 240X120X9,8X6,2 | F80: IN | G80: 1 | H80: 1 | I80: 11650 | J80: 3 | K80: 867 | L80: 60 | M80: 233 | N80: =+IF(F80="","",(K80*I80*H80*G80)/1000000) -> 10.10055 | O80: Blaze Shield II | P80: Software Idiem | Q80: =+IF(OR(O80="Fire Control",O80="Fire Tex 5062",O80="Fire Tex 5090",O80="Fire Tex 5120"),'CALCULO PINTURA'!P81," ") | R80: =+IF(OR(O80="Fire Control",O80="Fire Tex 5062",O80="Fire Tex 5090",O80="Fire Tex 5120"),'CALCULO PINTURA'!R81," ") | S80: =+IF(OR(O80="Fire Control",O80="Fire Tex 5062",O80="Fire Tex 5090",O80="Fire Tex 5120"),'CALCULO PINTURA'!S81," ") | T80: =+IF(OR(O80="Blaze Shield II",O80="Cafco 400",O80="Cafco 300"),'CALCULO MORTERO'!N81," ") -> 21 | U80: =+IF(OR(O80="Blaze Shield II",O80="Cafco 400",O80="Cafco 300"),'CALCULO MORTERO'!O81," ") -> 2.4002096 | V80: {=_xlfn.IFS(O80="Blaze Shield II",'CALCULO MORTERO'!P81, O80="Cafco 400",'CALCULO MORTERO'!Q81,O80="Cafco 300",'CALCULO MORTERO'!S81, AND(OR(O80="Fire tex 5090", O80="Fire Tex 5062", O80="Fire Tex 5120", O80="Fire Control"),Q80>0), "CERT.",TRUE,"-")} -> CERT.
A81: ELEVACION EJE D | B81: 209-B | C81: PM3 | D81: PILAR | E81: 150X150X5 | F81: CJ | G81: 1 | H81: 1 | I81: 4000 | J81: 4 | K81: 600 | L81: F-60 | M81: 200 | N81: =+IF(F81="","",(K81*I81*H81*G81)/1000000) -> 2.4 | O81: Fire Tex 5090 | P81: Software Idiem | Q81: =+IF(OR(O81="Fire Control",O81="Fire Tex 5062",O81="Fire Tex 5090",O81="Fire Tex 5120"),'CALCULO PINTURA'!P82," ") -> 1930 | R81: =+IF(OR(O81="Fire Control",O81="Fire Tex 5062",O81="Fire Tex 5090",O81="Fire Tex 5120"),'CALCULO PINTURA'!R82," ") -> 4.5601646 | S81: =+IF(OR(O81="Fire Control",O81="Fire Tex 5062",O81="Fire Tex 5090",O81="Fire Tex 5120"),'CALCULO PINTURA'!S82," ") -> 0.5262968 | T81: =+IF(OR(O81="Blaze Shield II",O81="Cafco 400",O81="Cafco 300"),'CALCULO MORTERO'!N82," ") | U81: =+IF(OR(O81="Blaze Shield II",O81="Cafco 400",O81="Cafco 300"),'CALCULO MORTERO'!O82," ") | V81: {=_xlfn.IFS(O81="Blaze Shield II",'CALCULO MORTERO'!P82, O81="Cafco 400",'CALCULO MORTERO'!Q82,O81="Cafco 300",'CALCULO MORTERO'!S82, AND(OR(O81="Fire tex 5090", O81="Fire Tex 5062", O81="Fire Tex 5120", O81="Fire Control"),Q81>0), "CERT.",TRUE,"-")} -> CERT.
A82: ELEVACION EJE D | B82: 209-B | C82: VM1 IPE 240 | D82: VIGA BAJO LOSA | E82: 240X120X9,8X6,2 | F82: IN | G82: 1 | H82: 1 | I82: 11650 | J82: 3 | K82: 867 | L82: 60 | M82: 233 | N82: =+IF(F82="","",(K82*I82*H82*G82)/1000000) -> 10.10055 | O82: Blaze Shield II | P82: Software Idiem | Q82: =+IF(OR(O82="Fire Control",O82="Fire Tex 5062",O82="Fire Tex 5090",O82="Fire Tex 5120"),'CALCULO PINTURA'!P83," ") | R82: =+IF(OR(O82="Fire Control",O82="Fire Tex 5062",O82="Fire Tex 5090",O82="Fire Tex 5120"),'CALCULO PINTURA'!R83," ") | S82: =+IF(OR(O82="Fire Control",O82="Fire Tex 5062",O82="Fire Tex 5090",O82="Fire Tex 5120"),'CALCULO PINTURA'!S83," ") | T82: =+IF(OR(O82="Blaze Shield II",O82="Cafco 400",O82="Cafco 300"),'CALCULO MORTERO'!N83," ") -> 21 | U82: =+IF(OR(O82="Blaze Shield II",O82="Cafco 400",O82="Cafco 300"),'CALCULO MORTERO'!O83," ") -> 2.4002096 | V82: {=_xlfn.IFS(O82="Blaze Shield II",'CALCULO MORTERO'!P83, O82="Cafco 400",'CALCULO MORTERO'!Q83,O82="Cafco 300",'CALCULO MORTERO'!S83, AND(OR(O82="Fire tex 5090", O82="Fire Tex 5062", O82="Fire Tex 5120", O82="Fire Control"),Q82>0), "CERT.",TRUE,"-")} -> CERT.
A83: ELEVACION EJE D | B83: 209-B | C83: ARRIOSTRA | D83: ARRIOSTRAMINETO VERTICAL | E83: 100X100X3 | F83: CJ | G83: 2 | H83: 1 | I83: 7900 | J83: 4 | K83: 400 | L83: F-60 | M83: 333 | N83: =+IF(F83="","",(K83*I83*H83*G83)/1000000) -> 6.32 | O83: Fire Tex 5090 | P83: Software Idiem | Q83: =+IF(OR(O83="Fire Control",O83="Fire Tex 5062",O83="Fire Tex 5090",O83="Fire Tex 5120"),'CALCULO PINTURA'!P84," ") -> 2828 | R83: =+IF(OR(O83="Fire Control",O83="Fire Tex 5062",O83="Fire Tex 5090",O83="Fire Tex 5120"),'CALCULO PINTURA'!R84," ") -> 3.1121349 | S83: =+IF(OR(O83="Fire Control",O83="Fire Tex 5062",O83="Fire Tex 5090",O83="Fire Tex 5120"),'CALCULO PINTURA'!S84," ") -> 2.0307603 | T83: =+IF(OR(O83="Blaze Shield II",O83="Cafco 400",O83="Cafco 300"),'CALCULO MORTERO'!N84," ") | U83: =+IF(OR(O83="Blaze Shield II",O83="Cafco 400",O83="Cafco 300"),'CALCULO MORTERO'!O84," ") | V83: {=_xlfn.IFS(O83="Blaze Shield II",'CALCULO MORTERO'!P84, O83="Cafco 400",'CALCULO MORTERO'!Q84,O83="Cafco 300",'CALCULO MORTERO'!S84, AND(OR(O83="Fire tex 5090", O83="Fire Tex 5062", O83="Fire Tex 5120", O83="Fire Control"),Q83>0), "CERT.",TRUE,"-")} -> CERT.
A84: ELEVACION EJE E | B84: 210-B | C84: PM3 | D84: PILAR | E84: 150X150X5 | F84: CJ | G84: 1 | H84: 1 | I84: 4000 | J84: 4 | K84: 600 | L84: F-60 | M84: 200 | N84: =+IF(F84="","",(K84*I84*H84*G84)/1000000) -> 2.4 | O84: Fire Tex 5090 | P84: Software Idiem | Q84: =+IF(OR(O84="Fire Control",O84="Fire Tex 5062",O84="Fire Tex 5090",O84="Fire Tex 5120"),'CALCULO PINTURA'!P85," ") -> 1930 | R84: =+IF(OR(O84="Fire Control",O84="Fire Tex 5062",O84="Fire Tex 5090",O84="Fire Tex 5120"),'CALCULO PINTURA'!R85," ") -> 4.5601646 | S84: =+IF(OR(O84="Fire Control",O84="Fire Tex 5062",O84="Fire Tex 5090",O84="Fire Tex 5120"),'CALCULO PINTURA'!S85," ") -> 0.5262968 | T84: =+IF(OR(O84="Blaze Shield II",O84="Cafco 400",O84="Cafco 300"),'CALCULO MORTERO'!N85," ") | U84: =+IF(OR(O84="Blaze Shield II",O84="Cafco 400",O84="Cafco 300"),'CALCULO MORTERO'!O85," ") | V84: {=_xlfn.IFS(O84="Blaze Shield II",'CALCULO MORTERO'!P85, O84="Cafco 400",'CALCULO MORTERO'!Q85,O84="Cafco 300",'CALCULO MORTERO'!S85, AND(OR(O84="Fire tex 5090", O84="Fire Tex 5062", O84="Fire Tex 5120", O84="Fire Control"),Q84>0), "CERT.",TRUE,"-")} -> CERT.
A85: ELEVACION EJE E | B85: 210-B | C85: VM1 IPE 240 | D85: VIGA BAJO LOSA | E85: 240X120X9,8X6,2 | F85: IN | G85: 1 | H85: 1 | I85: 11650 | J85: 3 | K85: 867 | L85: 60 | M85: 233 | N85: =+IF(F85="","",(K85*I85*H85*G85)/1000000) -> 10.10055 | O85: Blaze Shield II | P85: Software Idiem | Q85: =+IF(OR(O85="Fire Control",O85="Fire Tex 5062",O85="Fire Tex 5090",O85="Fire Tex 5120"),'CALCULO PINTURA'!P86," ") | R85: =+IF(OR(O85="Fire Control",O85="Fire Tex 5062",O85="Fire Tex 5090",O85="Fire Tex 5120"),'CALCULO PINTURA'!R86," ") | S85: =+IF(OR(O85="Fire Control",O85="Fire Tex 5062",O85="Fire Tex 5090",O85="Fire Tex 5120"),'CALCULO PINTURA'!S86," ") | T85: =+IF(OR(O85="Blaze Shield II",O85="Cafco 400",O85="Cafco 300"),'CALCULO MORTERO'!N86," ") -> 21 | U85: =+IF(OR(O85="Blaze Shield II",O85="Cafco 400",O85="Cafco 300"),'CALCULO MORTERO'!O86," ") -> 2.4002096 | V85: {=_xlfn.IFS(O85="Blaze Shield II",'CALCULO MORTERO'!P86, O85="Cafco 400",'CALCULO MORTERO'!Q86,O85="Cafco 300",'CALCULO MORTERO'!S86, AND(OR(O85="Fire tex 5090", O85="Fire Tex 5062", O85="Fire Tex 5120", O85="Fire Control"),Q85>0), "CERT.",TRUE,"-")} -> CERT.
A86: ELEVACION EJE F | B86: 210-B | C86: PM3 | D86: PILAR | E86: 150X150X5 | F86: CJ | G86: 1 | H86: 1 | I86: 4000 | J86: 4 | K86: 600 | L86: F-60 | M86: 200 | N86: =+IF(F86="","",(K86*I86*H86*G86)/1000000) -> 2.4 | O86: Fire Tex 5090 | P86: Software Idiem | Q86: =+IF(OR(O86="Fire Control",O86="Fire Tex 5062",O86="Fire Tex 5090",O86="Fire Tex 5120"),'CALCULO PINTURA'!P87," ") -> 1930 | R86: =+IF(OR(O86="Fire Control",O86="Fire Tex 5062",O86="Fire Tex 5090",O86="Fire Tex 5120"),'CALCULO PINTURA'!R87," ") -> 4.5601646 | S86: =+IF(OR(O86="Fire Control",O86="Fire Tex 5062",O86="Fire Tex 5090",O86="Fire Tex 5120"),'CALCULO PINTURA'!S87," ") -> 0.5262968 | T86: =+IF(OR(O86="Blaze Shield II",O86="Cafco 400",O86="Cafco 300"),'CALCULO MORTERO'!N87," ") | U86: =+IF(OR(O86="Blaze Shield II",O86="Cafco 400",O86="Cafco 300"),'CALCULO MORTERO'!O87," ") | V86: {=_xlfn.IFS(O86="Blaze Shield II",'CALCULO MORTERO'!P87, O86="Cafco 400",'CALCULO MORTERO'!Q87,O86="Cafco 300",'CALCULO MORTERO'!S87, AND(OR(O86="Fire tex 5090", O86="Fire Tex 5062", O86="Fire Tex 5120", O86="Fire Control"),Q86>0), "CERT.",TRUE,"-")} -> CERT.
A87: ELEVACION EJE F | B87: 210-B | C87: VM1 IPE 240 | D87: VIGA BAJO LOSA | E87: 240X120X9,8X6,2 | F87: IN | G87: 1 | H87: 1 | I87: 11650 | J87: 3 | K87: 867 | L87: 60 | M87: 233 | N87: =+IF(F87="","",(K87*I87*H87*G87)/1000000) -> 10.10055 | O87: Blaze Shield II | P87: Software Idiem | Q87: =+IF(OR(O87="Fire Control",O87="Fire Tex 5062",O87="Fire Tex 5090",O87="Fire Tex 5120"),'CALCULO PINTURA'!P88," ") | R87: =+IF(OR(O87="Fire Control",O87="Fire Tex 5062",O87="Fire Tex 5090",O87="Fire Tex 5120"),'CALCULO PINTURA'!R88," ") | S87: =+IF(OR(O87="Fire Control",O87="Fire Tex 5062",O87="Fire Tex 5090",O87="Fire Tex 5120"),'CALCULO PINTURA'!S88," ") | T87: =+IF(OR(O87="Blaze Shield II",O87="Cafco 400",O87="Cafco 300"),'CALCULO MORTERO'!N88," ") -> 21 | U87: =+IF(OR(O87="Blaze Shield II",O87="Cafco 400",O87="Cafco 300"),'CALCULO MORTERO'!O88," ") -> 2.4002096 | V87: {=_xlfn.IFS(O87="Blaze Shield II",'CALCULO MORTERO'!P88, O87="Cafco 400",'CALCULO MORTERO'!Q88,O87="Cafco 300",'CALCULO MORTERO'!S88, AND(OR(O87="Fire tex 5090", O87="Fire Tex 5062", O87="Fire Tex 5120", O87="Fire Control"),Q87>0), "CERT.",TRUE,"-")} -> CERT.
A88: ELEVACION EJE F | B88: 210-B | C88: ARRIOSTRA | D88: ARRIOSTRAMINETO VERTICAL | E88: 100X100X3 | F88: CJ | G88: 2 | H88: 1 | I88: 7900 | J88: 4 | K88: 400 | L88: F-60 | M88: 333 | N88: =+IF(F88="","",(K88*I88*H88*G88)/1000000) -> 6.32 | O88: Fire Tex 5090 | P88: Software Idiem | Q88: =+IF(OR(O88="Fire Control",O88="Fire Tex 5062",O88="Fire Tex 5090",O88="Fire Tex 5120"),'CALCULO PINTURA'!P89," ") -> 2828 | R88: =+IF(OR(O88="Fire Control",O88="Fire Tex 5062",O88="Fire Tex 5090",O88="Fire Tex 5120"),'CALCULO PINTURA'!R89," ") -> 3.1121349 | S88: =+IF(OR(O88="Fire Control",O88="Fire Tex 5062",O88="Fire Tex 5090",O88="Fire Tex 5120"),'CALCULO PINTURA'!S89," ") -> 2.0307603 | T88: =+IF(OR(O88="Blaze Shield II",O88="Cafco 400",O88="Cafco 300"),'CALCULO MORTERO'!N89," ") | U88: =+IF(OR(O88="Blaze Shield II",O88="Cafco 400",O88="Cafco 300"),'CALCULO MORTERO'!O89," ") | V88: {=_xlfn.IFS(O88="Blaze Shield II",'CALCULO MORTERO'!P89, O88="Cafco 400",'CALCULO MORTERO'!Q89,O88="Cafco 300",'CALCULO MORTERO'!S89, AND(OR(O88="Fire tex 5090", O88="Fire Tex 5062", O88="Fire Tex 5120", O88="Fire Control"),Q88>0), "CERT.",TRUE,"-")} -> CERT.
A89: ELEVACION EJE F | B89: 210-B | C89: ARRIOSTRA | D89: ARRIOSTRAMINETO VERTICAL | E89: 100X100X3 | F89: CJ | G89: 2 | H89: 1 | I89: 6250 | J89: 4 | K89: 400 | L89: F-60 | M89: 333 | N89: =+IF(F89="","",(K89*I89*H89*G89)/1000000) -> 5 | O89: Fire Tex 5090 | P89: Software Idiem | Q89: =+IF(OR(O89="Fire Control",O89="Fire Tex 5062",O89="Fire Tex 5090",O89="Fire Tex 5120"),'CALCULO PINTURA'!P90," ") -> 2828 | R89: =+IF(OR(O89="Fire Control",O89="Fire Tex 5062",O89="Fire Tex 5090",O89="Fire Tex 5120"),'CALCULO PINTURA'!R90," ") -> 3.1121349 | S89: =+IF(OR(O89="Fire Control",O89="Fire Tex 5062",O89="Fire Tex 5090",O89="Fire Tex 5120"),'CALCULO PINTURA'!S90," ") -> 1.6066141 | T89: =+IF(OR(O89="Blaze Shield II",O89="Cafco 400",O89="Cafco 300"),'CALCULO MORTERO'!N90," ") | U89: =+IF(OR(O89="Blaze Shield II",O89="Cafco 400",O89="Cafco 300"),'CALCULO MORTERO'!O90," ") | V89: {=_xlfn.IFS(O89="Blaze Shield II",'CALCULO MORTERO'!P90, O89="Cafco 400",'CALCULO MORTERO'!Q90,O89="Cafco 300",'CALCULO MORTERO'!S90, AND(OR(O89="Fire tex 5090", O89="Fire Tex 5062", O89="Fire Tex 5120", O89="Fire Control"),Q89>0), "CERT.",TRUE,"-")} -> CERT.
A90: ELEVACION EJE F | B90: 210-B | C90: CJ100X100X3 | D90: PILAR | E90: 100X100X3 | F90: CJ | G90: 1 | H90: 1 | I90: 3000 | J90: 4 | K90: 400 | L90: F-60 | M90: 333 | N90: =+IF(F90="","",(K90*I90*H90*G90)/1000000) -> 1.2 | O90: Fire Tex 5090 | P90: Software Idiem | Q90: =+IF(OR(O90="Fire Control",O90="Fire Tex 5062",O90="Fire Tex 5090",O90="Fire Tex 5120"),'CALCULO PINTURA'!P91," ") -> 2828 | R90: =+IF(OR(O90="Fire Control",O90="Fire Tex 5062",O90="Fire Tex 5090",O90="Fire Tex 5120"),'CALCULO PINTURA'!R91," ") -> 3.1121349 | S90: =+IF(OR(O90="Fire Control",O90="Fire Tex 5062",O90="Fire Tex 5090",O90="Fire Tex 5120"),'CALCULO PINTURA'!S91," ") -> 0.38558739 | T90: =+IF(OR(O90="Blaze Shield II",O90="Cafco 400",O90="Cafco 300"),'CALCULO MORTERO'!N91," ") | U90: =+IF(OR(O90="Blaze Shield II",O90="Cafco 400",O90="Cafco 300"),'CALCULO MORTERO'!O91," ") | V90: {=_xlfn.IFS(O90="Blaze Shield II",'CALCULO MORTERO'!P91, O90="Cafco 400",'CALCULO MORTERO'!Q91,O90="Cafco 300",'CALCULO MORTERO'!S91, AND(OR(O90="Fire tex 5090", O90="Fire Tex 5062", O90="Fire Tex 5120", O90="Fire Control"),Q90>0), "CERT.",TRUE,"-")} -> CERT.
A91: ELEVACION EJE F | B91: 210-B | C91: PM2 | D91: PILAR | E91: 200X100X4 | F91: CJ | G91: 1 | H91: 1 | I91: 7100 | J91: 4 | K91: 600 | L91: F-60 | M91: 250 | N91: =+IF(F91="","",(K91*I91*H91*G91)/1000000) -> 4.26 | O91: Fire Tex 5090 | P91: Software Idiem | Q91: =+IF(OR(O91="Fire Control",O91="Fire Tex 5062",O91="Fire Tex 5090",O91="Fire Tex 5120"),'CALCULO PINTURA'!P92," ") -> 2262 | R91: =+IF(OR(O91="Fire Control",O91="Fire Tex 5062",O91="Fire Tex 5090",O91="Fire Tex 5120"),'CALCULO PINTURA'!R92," ") -> 3.8908566 | S91: =+IF(OR(O91="Fire Control",O91="Fire Tex 5062",O91="Fire Tex 5090",O91="Fire Tex 5120"),'CALCULO PINTURA'!S92," ") -> 1.0948746 | T91: =+IF(OR(O91="Blaze Shield II",O91="Cafco 400",O91="Cafco 300"),'CALCULO MORTERO'!N92," ") | U91: =+IF(OR(O91="Blaze Shield II",O91="Cafco 400",O91="Cafco 300"),'CALCULO MORTERO'!O92," ") | V91: {=_xlfn.IFS(O91="Blaze Shield II",'CALCULO MORTERO'!P92, O91="Cafco 400",'CALCULO MORTERO'!Q92,O91="Cafco 300",'CALCULO MORTERO'!S92, AND(OR(O91="Fire tex 5090", O91="Fire Tex 5062", O91="Fire Tex 5120", O91="Fire Control"),Q91>0), "CERT.",TRUE,"-")} -> CERT.
A92: PLANTA TECHUMBRE | B92: 207-B | C92: COSTANERA TIP | D92: COSTANERA | E92: 125X50X15X2 | F92: C | G92: 24 | H92: 1 | I92: 29210 | J92: 3 | K92: 445 | L92: 60 | M92: 1057 | N92: =+IF(F92="","",(K92*I92*H92*G92)/1000000) -> 311.9628 | O92: Blaze Shield II | P92: Software Idiem | Q92: =+IF(OR(O92="Fire Control",O92="Fire Tex 5062",O92="Fire Tex 5090",O92="Fire Tex 5120"),'CALCULO PINTURA'!P93," ") | R92: =+IF(OR(O92="Fire Control",O92="Fire Tex 5062",O92="Fire Tex 5090",O92="Fire Tex 5120"),'CALCULO PINTURA'!R93," ") | S92: =+IF(OR(O92="Fire Control",O92="Fire Tex 5062",O92="Fire Tex 5090",O92="Fire Tex 5120"),'CALCULO PINTURA'!S93," ") | T92: =+IF(OR(O92="Blaze Shield II",O92="Cafco 400",O92="Cafco 300"),'CALCULO MORTERO'!N93," ") -> 54 | U92: =+IF(OR(O92="Blaze Shield II",O92="Cafco 400",O92="Cafco 300"),'CALCULO MORTERO'!O93," ") -> 190.62569 | V92: {=_xlfn.IFS(O92="Blaze Shield II",'CALCULO MORTERO'!P93, O92="Cafco 400",'CALCULO MORTERO'!Q93,O92="Cafco 300",'CALCULO MORTERO'!S93, AND(OR(O92="Fire tex 5090", O92="Fire Tex 5062", O92="Fire Tex 5120", O92="Fire Control"),Q92>0), "CERT.",TRUE,"-")} -> NO CERT.
A93: PLANTA TECHUMBRE | B93: 207-B | C93: PUNTAL. TIP | D93: PUNTAL | E93: 100X100X3 | F93: CJ | G93: 2 | H93: 1 | I93: 29210 | J93: 4 | K93: 400 | L93: F-60 | M93: 333 | N93: =+IF(F93="","",(K93*I93*H93*G93)/1000000) -> 23.368 | O93: Fire Tex 5090 | P93: Software Idiem | Q93: =+IF(OR(O93="Fire Control",O93="Fire Tex 5062",O93="Fire Tex 5090",O93="Fire Tex 5120"),'CALCULO PINTURA'!P94," ") -> 2828 | R93: =+IF(OR(O93="Fire Control",O93="Fire Tex 5062",O93="Fire Tex 5090",O93="Fire Tex 5120"),'CALCULO PINTURA'!R94," ") -> 3.1121349 | S93: =+IF(OR(O93="Fire Control",O93="Fire Tex 5062",O93="Fire Tex 5090",O93="Fire Tex 5120"),'CALCULO PINTURA'!S94," ") -> 7.5086719 | T93: =+IF(OR(O93="Blaze Shield II",O93="Cafco 400",O93="Cafco 300"),'CALCULO MORTERO'!N94," ") | U93: =+IF(OR(O93="Blaze Shield II",O93="Cafco 400",O93="Cafco 300"),'CALCULO MORTERO'!O94," ") | V93: {=_xlfn.IFS(O93="Blaze Shield II",'CALCULO MORTERO'!P94, O93="Cafco 400",'CALCULO MORTERO'!Q94,O93="Cafco 300",'CALCULO MORTERO'!S94, AND(OR(O93="Fire tex 5090", O93="Fire Tex 5062", O93="Fire Tex 5120", O93="Fire Control"),Q93>0), "CERT.",TRUE,"-")} -> CERT.
A94: PLANTA CIELO PISO 1 | B94: 205-B | C94: - | D94: LOSA | E94: - | F94: - | G94: 1 | H94: 1 | I94: 27900 | J94: 1 | K94: 11640 | L94: 60 | M94: - | N94: =(K94*I94*H94*G94)/1000000 -> 324.756 | O94: Blaze Shield II | P94: Software Idiem | Q94: =+IF(OR(O94="Fire Control",O94="Fire Tex 5062",O94="Fire Tex 5090",O94="Fire Tex 5120"),'CALCULO PINTURA'!P95," ") | R94: =+IF(OR(O94="Fire Control",O94="Fire Tex 5062",O94="Fire Tex 5090",O94="Fire Tex 5120"),'CALCULO PINTURA'!R95," ") | S94: =+IF(OR(O94="Fire Control",O94="Fire Tex 5062",O94="Fire Tex 5090",O94="Fire Tex 5120"),'CALCULO PINTURA'!S95," ") | T94: =+IF(OR(O94="Blaze Shield II",O94="Cafco 400",O94="Cafco 300"),'CALCULO MORTERO'!N95," ") -> 15 | U94: =+IF(OR(O94="Blaze Shield II",O94="Cafco 400",O94="Cafco 300"),'CALCULO MORTERO'!O95," ") -> 55.123058 | V94: {=_xlfn.IFS(O94="Blaze Shield II",'CALCULO MORTERO'!P95, O94="Cafco 400",'CALCULO MORTERO'!Q95,O94="Cafco 300",'CALCULO MORTERO'!S95, AND(OR(O94="Fire tex 5090", O94="Fire Tex 5062", O94="Fire Tex 5120", O94="Fire Control"),Q94>0), "CERT.",TRUE,"-")} -> NO CERT.
A95: PLANTA CIELO PISO 1 | B95: 205-B | C95: - | D95: LOSA | E95: - | F95: - | G95: 1 | H95: 1 | I95: 2550 | J95: 1 | K95: 1500 | L95: 60 | M95: - | N95: =(K95*I95*H95*G95)/1000000 -> 3.825 | O95: Blaze Shield II | P95: Software Idiem | Q95: =+IF(OR(O95="Fire Control",O95="Fire Tex 5062",O95="Fire Tex 5090",O95="Fire Tex 5120"),'CALCULO PINTURA'!P96," ") | R95: =+IF(OR(O95="Fire Control",O95="Fire Tex 5062",O95="Fire Tex 5090",O95="Fire Tex 5120"),'CALCULO PINTURA'!R96," ") | S95: =+IF(OR(O95="Fire Control",O95="Fire Tex 5062",O95="Fire Tex 5090",O95="Fire Tex 5120"),'CALCULO PINTURA'!S96," ") | T95: =+IF(OR(O95="Blaze Shield II",O95="Cafco 400",O95="Cafco 300"),'CALCULO MORTERO'!N96," ") -> 15 | U95: =+IF(OR(O95="Blaze Shield II",O95="Cafco 400",O95="Cafco 300"),'CALCULO MORTERO'!O96," ") -> 0.64924342 | V95: {=_xlfn.IFS(O95="Blaze Shield II",'CALCULO MORTERO'!P96, O95="Cafco 400",'CALCULO MORTERO'!Q96,O95="Cafco 300",'CALCULO MORTERO'!S96, AND(OR(O95="Fire tex 5090", O95="Fire Tex 5062", O95="Fire Tex 5120", O95="Fire Control"),Q95>0), "CERT.",TRUE,"-")} -> NO CERT.
A96: PLANTA CIELO PISO 1 | B96: 205-B | C96: VM2 IPE 200 | D96: VIGA BAJO LOSA | E96: 200X100X8,5X5,6 | F96: IN | G96: 5 | H96: 1 | I96: 27900 | J96: 3 | K96: 723 | L96: 60 | M96: 265 | N96: =+IF(F96="","",(K96*I96*H96*G96)/1000000) -> 100.8585 | O96: Blaze Shield II | P96: Software Idiem | Q96: =+IF(OR(O96="Fire Control",O96="Fire Tex 5062",O96="Fire Tex 5090",O96="Fire Tex 5120"),'CALCULO PINTURA'!P97," ") | R96: =+IF(OR(O96="Fire Control",O96="Fire Tex 5062",O96="Fire Tex 5090",O96="Fire Tex 5120"),'CALCULO PINTURA'!R97," ") | S96: =+IF(OR(O96="Fire Control",O96="Fire Tex 5062",O96="Fire Tex 5090",O96="Fire Tex 5120"),'CALCULO PINTURA'!S97," ") | T96: =+IF(OR(O96="Blaze Shield II",O96="Cafco 400",O96="Cafco 300"),'CALCULO MORTERO'!N97," ") -> 22 | U96: =+IF(OR(O96="Blaze Shield II",O96="Cafco 400",O96="Cafco 300"),'CALCULO MORTERO'!O97," ") -> 25.108458 | V96: {=_xlfn.IFS(O96="Blaze Shield II",'CALCULO MORTERO'!P97, O96="Cafco 400",'CALCULO MORTERO'!Q97,O96="Cafco 300",'CALCULO MORTERO'!S97, AND(OR(O96="Fire tex 5090", O96="Fire Tex 5062", O96="Fire Tex 5120", O96="Fire Control"),Q96>0), "CERT.",TRUE,"-")} -> CERT.
A97: PLANTA CIELO PISO 1 | B97: 205-B | C97: VM2 IPE 200 | D97: VIGA BAJO LOSA | E97: 200X100X8,5X5,6 | F97: IN | G97: 2 | H97: 1 | I97: 1377 | J97: 3 | K97: 723 | L97: 60 | M97: 265 | N97: =+IF(F97="","",(K97*I97*H97*G97)/1000000) -> 1.991142 | O97: Blaze Shield II | P97: Software Idiem | Q97: =+IF(OR(O97="Fire Control",O97="Fire Tex 5062",O97="Fire Tex 5090",O97="Fire Tex 5120"),'CALCULO PINTURA'!P98," ") | R97: =+IF(OR(O97="Fire Control",O97="Fire Tex 5062",O97="Fire Tex 5090",O97="Fire Tex 5120"),'CALCULO PINTURA'!R98," ") | S97: =+IF(OR(O97="Fire Control",O97="Fire Tex 5062",O97="Fire Tex 5090",O97="Fire Tex 5120"),'CALCULO PINTURA'!S98," ") | T97: =+IF(OR(O97="Blaze Shield II",O97="Cafco 400",O97="Cafco 300"),'CALCULO MORTERO'!N98," ") -> 22 | U97: =+IF(OR(O97="Blaze Shield II",O97="Cafco 400",O97="Cafco 300"),'CALCULO MORTERO'!O98," ") -> 0.49568956 | V97: {=_xlfn.IFS(O97="Blaze Shield II",'CALCULO MORTERO'!P98, O97="Cafco 400",'CALCULO MORTERO'!Q98,O97="Cafco 300",'CALCULO MORTERO'!S98, AND(OR(O97="Fire tex 5090", O97="Fire Tex 5062", O97="Fire Tex 5120", O97="Fire Control"),Q97>0), "CERT.",TRUE,"-")} -> CERT.
A98: PLANTA CIELO PISO 1 | B98: 205-B | C98: VM1 IPE 240 | D98: VIGA BAJO LOSA | E98: 240X120X9,8X6,2 | F98: IN | G98: 2 | H98: 1 | I98: 11650 | J98: 3 | K98: 867 | L98: 60 | M98: 233 | N98: =+IF(F98="","",(K98*I98*H98*G98)/1000000) -> 20.2011 | O98: Blaze Shield II | P98: Software Idiem | Q98: =+IF(OR(O98="Fire Control",O98="Fire Tex 5062",O98="Fire Tex 5090",O98="Fire Tex 5120"),'CALCULO PINTURA'!P99," ") | R98: =+IF(OR(O98="Fire Control",O98="Fire Tex 5062",O98="Fire Tex 5090",O98="Fire Tex 5120"),'CALCULO PINTURA'!R99," ") | S98: =+IF(OR(O98="Fire Control",O98="Fire Tex 5062",O98="Fire Tex 5090",O98="Fire Tex 5120"),'CALCULO PINTURA'!S99," ") | T98: =+IF(OR(O98="Blaze Shield II",O98="Cafco 400",O98="Cafco 300"),'CALCULO MORTERO'!N99," ") -> 21 | U98: =+IF(OR(O98="Blaze Shield II",O98="Cafco 400",O98="Cafco 300"),'CALCULO MORTERO'!O99," ") -> 4.8004193 | V98: {=_xlfn.IFS(O98="Blaze Shield II",'CALCULO MORTERO'!P99, O98="Cafco 400",'CALCULO MORTERO'!Q99,O98="Cafco 300",'CALCULO MORTERO'!S99, AND(OR(O98="Fire tex 5090", O98="Fire Tex 5062", O98="Fire Tex 5120", O98="Fire Control"),Q98>0), "CERT.",TRUE,"-")} -> CERT.
J99: 3 | N99: =+IF(F99="","",(K99*I99*H99*G99)/1000000) | P99: Software Idiem | Q99: =+IF(OR(O99="Fire Control",O99="Fire Tex 5062",O99="Fire Tex 5090",O99="Fire Tex 5120"),'CALCULO PINTURA'!P100," ") | R99: =+IF(OR(O99="Fire Control",O99="Fire Tex 5062",O99="Fire Tex 5090",O99="Fire Tex 5120"),'CALCULO PINTURA'!R100," ") | S99: =+IF(OR(O99="Fire Control",O99="Fire Tex 5062",O99="Fire Tex 5090",O99="Fire Tex 5120"),'CALCULO PINTURA'!S100," ") | T99: =+IF(OR(O99="Blaze Shield II",O99="Cafco 400",O99="Cafco 300"),'CALCULO MORTERO'!N100," ") | U99: =+IF(OR(O99="Blaze Shield II",O99="Cafco 400",O99="Cafco 300"),'CALCULO MORTERO'!O100," ") | V99: {=_xlfn.IFS(O99="Blaze Shield II",'CALCULO MORTERO'!P100, O99="Cafco 400",'CALCULO MORTERO'!Q100,O99="Cafco 300",'CALCULO MORTERO'!S100, AND(OR(O99="Fire tex 5090", O99="Fire Tex 5062", O99="Fire Tex 5120", O99="Fire Control"),Q99>0), "CERT.",TRUE,"-")} -> -
J100: 4 | N100: =+IF(F100="","",(K100*I100*H100*G100)/1000000) | P100: Software Idiem | Q100: =+IF(OR(O100="Fire Control",O100="Fire Tex 5062",O100="Fire Tex 5090",O100="Fire Tex 5120"),'CALCULO PINTURA'!P101," ") | R100: =+IF(OR(O100="Fire Control",O100="Fire Tex 5062",O100="Fire Tex 5090",O100="Fire Tex 5120"),'CALCULO PINTURA'!R101," ") | S100: =+IF(OR(O100="Fire Control",O100="Fire Tex 5062",O100="Fire Tex 5090",O100="Fire Tex 5120"),'CALCULO PINTURA'!S101," ") | T100: =+IF(OR(O100="Blaze Shield II",O100="Cafco 400",O100="Cafco 300"),'CALCULO MORTERO'!N101," ") | U100: =+IF(OR(O100="Blaze Shield II",O100="Cafco 400",O100="Cafco 300"),'CALCULO MORTERO'!O101," ") | V100: {=_xlfn.IFS(O100="Blaze Shield II",'CALCULO MORTERO'!P101, O100="Cafco 400",'CALCULO MORTERO'!Q101,O100="Cafco 300",'CALCULO MORTERO'!S101, AND(OR(O100="Fire tex 5090", O100="Fire Tex 5062", O100="Fire Tex 5120", O100="Fire Control"),Q100>0), "CERT.",TRUE,"-")} -> -
J101: 4 | N101: =+IF(F101="","",(K101*I101*H101*G101)/1000000) | P101: Software Idiem | Q101: =+IF(OR(O101="Fire Control",O101="Fire Tex 5062",O101="Fire Tex 5090",O101="Fire Tex 5120"),'CALCULO PINTURA'!P102," ") | R101: =+IF(OR(O101="Fire Control",O101="Fire Tex 5062",O101="Fire Tex 5090",O101="Fire Tex 5120"),'CALCULO PINTURA'!R102," ") | S101: =+IF(OR(O101="Fire Control",O101="Fire Tex 5062",O101="Fire Tex 5090",O101="Fire Tex 5120"),'CALCULO PINTURA'!S102," ") | T101: =+IF(OR(O101="Blaze Shield II",O101="Cafco 400",O101="Cafco 300"),'CALCULO MORTERO'!N102," ") | U101: =+IF(OR(O101="Blaze Shield II",O101="Cafco 400",O101="Cafco 300"),'CALCULO MORTERO'!O102," ") | V101: {=_xlfn.IFS(O101="Blaze Shield II",'CALCULO MORTERO'!P102, O101="Cafco 400",'CALCULO MORTERO'!Q102,O101="Cafco 300",'CALCULO MORTERO'!S102, AND(OR(O101="Fire tex 5090", O101="Fire Tex 5062", O101="Fire Tex 5120", O101="Fire Control"),Q101>0), "CERT.",TRUE,"-")} -> -
J102: 4 | N102: =+IF(F102="","",(K102*I102*H102*G102)/1000000) | P102: Software Idiem | Q102: =+IF(OR(O102="Fire Control",O102="Fire Tex 5062",O102="Fire Tex 5090",O102="Fire Tex 5120"),'CALCULO PINTURA'!P103," ") | R102: =+IF(OR(O102="Fire Control",O102="Fire Tex 5062",O102="Fire Tex 5090",O102="Fire Tex 5120"),'CALCULO PINTURA'!R103," ") | S102: =+IF(OR(O102="Fire Control",O102="Fire Tex 5062",O102="Fire Tex 5090",O102="Fire Tex 5120"),'CALCULO PINTURA'!S103," ") | T102: =+IF(OR(O102="Blaze Shield II",O102="Cafco 400",O102="Cafco 300"),'CALCULO MORTERO'!N103," ") | U102: =+IF(OR(O102="Blaze Shield II",O102="Cafco 400",O102="Cafco 300"),'CALCULO MORTERO'!O103," ") | V102: {=_xlfn.IFS(O102="Blaze Shield II",'CALCULO MORTERO'!P103, O102="Cafco 400",'CALCULO MORTERO'!Q103,O102="Cafco 300",'CALCULO MORTERO'!S103, AND(OR(O102="Fire tex 5090", O102="Fire Tex 5062", O102="Fire Tex 5120", O102="Fire Control"),Q102>0), "CERT.",TRUE,"-")} -> -
J103: 4 | N103: =+IF(F103="","",(K103*I103*H103*G103)/1000000) | P103: Software Idiem | Q103: =+IF(OR(O103="Fire Control",O103="Fire Tex 5062",O103="Fire Tex 5090",O103="Fire Tex 5120"),'CALCULO PINTURA'!P104," ") | R103: =+IF(OR(O103="Fire Control",O103="Fire Tex 5062",O103="Fire Tex 5090",O103="Fire Tex 5120"),'CALCULO PINTURA'!R104," ") | S103: =+IF(OR(O103="Fire Control",O103="Fire Tex 5062",O103="Fire Tex 5090",O103="Fire Tex 5120"),'CALCULO PINTURA'!S104," ") | T103: =+IF(OR(O103="Blaze Shield II",O103="Cafco 400",O103="Cafco 300"),'CALCULO MORTERO'!N104," ") | U103: =+IF(OR(O103="Blaze Shield II",O103="Cafco 400",O103="Cafco 300"),'CALCULO MORTERO'!O104," ") | V103: {=_xlfn.IFS(O103="Blaze Shield II",'CALCULO MORTERO'!P104, O103="Cafco 400",'CALCULO MORTERO'!Q104,O103="Cafco 300",'CALCULO MORTERO'!S104, AND(OR(O103="Fire tex 5090", O103="Fire Tex 5062", O103="Fire Tex 5120", O103="Fire Control"),Q103>0), "CERT.",TRUE,"-")} -> -
J104: 4 | N104: =+IF(F104="","",(K104*I104*H104*G104)/1000000) | P104: Software Idiem | Q104: =+IF(OR(O104="Fire Control",O104="Fire Tex 5062",O104="Fire Tex 5090",O104="Fire Tex 5120"),'CALCULO PINTURA'!P105," ") | R104: =+IF(OR(O104="Fire Control",O104="Fire Tex 5062",O104="Fire Tex 5090",O104="Fire Tex 5120"),'CALCULO PINTURA'!R105," ") | S104: =+IF(OR(O104="Fire Control",O104="Fire Tex 5062",O104="Fire Tex 5090",O104="Fire Tex 5120"),'CALCULO PINTURA'!S105," ") | T104: =+IF(OR(O104="Blaze Shield II",O104="Cafco 400",O104="Cafco 300"),'CALCULO MORTERO'!N105," ") | U104: =+IF(OR(O104="Blaze Shield II",O104="Cafco 400",O104="Cafco 300"),'CALCULO MORTERO'!O105," ") | V104: {=_xlfn.IFS(O104="Blaze Shield II",'CALCULO MORTERO'!P105, O104="Cafco 400",'CALCULO MORTERO'!Q105,O104="Cafco 300",'CALCULO MORTERO'!S105, AND(OR(O104="Fire tex 5090", O104="Fire Tex 5062", O104="Fire Tex 5120", O104="Fire Control"),Q104>0), "CERT.",TRUE,"-")} -> -
J105: 4 | N105: =+IF(F105="","",(K105*I105*H105*G105)/1000000) | P105: Software Idiem | Q105: =+IF(OR(O105="Fire Control",O105="Fire Tex 5062",O105="Fire Tex 5090",O105="Fire Tex 5120"),'CALCULO PINTURA'!P106," ") | R105: =+IF(OR(O105="Fire Control",O105="Fire Tex 5062",O105="Fire Tex 5090",O105="Fire Tex 5120"),'CALCULO PINTURA'!R106," ") | S105: =+IF(OR(O105="Fire Control",O105="Fire Tex 5062",O105="Fire Tex 5090",O105="Fire Tex 5120"),'CALCULO PINTURA'!S106," ") | T105: =+IF(OR(O105="Blaze Shield II",O105="Cafco 400",O105="Cafco 300"),'CALCULO MORTERO'!N106," ") | U105: =+IF(OR(O105="Blaze Shield II",O105="Cafco 400",O105="Cafco 300"),'CALCULO MORTERO'!O106," ") | V105: {=_xlfn.IFS(O105="Blaze Shield II",'CALCULO MORTERO'!P106, O105="Cafco 400",'CALCULO MORTERO'!Q106,O105="Cafco 300",'CALCULO MORTERO'!S106, AND(OR(O105="Fire tex 5090", O105="Fire Tex 5062", O105="Fire Tex 5120", O105="Fire Control"),Q105>0), "CERT.",TRUE,"-")} -> -
J106: 4 | N106: =+IF(F106="","",(K106*I106*H106*G106)/1000000) | P106: Software Idiem | Q106: =+IF(OR(O106="Fire Control",O106="Fire Tex 5062",O106="Fire Tex 5090",O106="Fire Tex 5120"),'CALCULO PINTURA'!P107," ") | R106: =+IF(OR(O106="Fire Control",O106="Fire Tex 5062",O106="Fire Tex 5090",O106="Fire Tex 5120"),'CALCULO PINTURA'!R107," ") | S106: =+IF(OR(O106="Fire Control",O106="Fire Tex 5062",O106="Fire Tex 5090",O106="Fire Tex 5120"),'CALCULO PINTURA'!S107," ") | T106: =+IF(OR(O106="Blaze Shield II",O106="Cafco 400",O106="Cafco 300"),'CALCULO MORTERO'!N107," ") | U106: =+IF(OR(O106="Blaze Shield II",O106="Cafco 400",O106="Cafco 300"),'CALCULO MORTERO'!O107," ") | V106: {=_xlfn.IFS(O106="Blaze Shield II",'CALCULO MORTERO'!P107, O106="Cafco 400",'CALCULO MORTERO'!Q107,O106="Cafco 300",'CALCULO MORTERO'!S107, AND(OR(O106="Fire tex 5090", O106="Fire Tex 5062", O106="Fire Tex 5120", O106="Fire Control"),Q106>0), "CERT.",TRUE,"-")} -> -
J107: 4 | N107: =+IF(F107="","",(K107*I107*H107*G107)/1000000) | P107: Software Idiem | Q107: =+IF(OR(O107="Fire Control",O107="Fire Tex 5062",O107="Fire Tex 5090",O107="Fire Tex 5120"),'CALCULO PINTURA'!P108," ") | R107: =+IF(OR(O107="Fire Control",O107="Fire Tex 5062",O107="Fire Tex 5090",O107="Fire Tex 5120"),'CALCULO PINTURA'!R108," ") | S107: =+IF(OR(O107="Fire Control",O107="Fire Tex 5062",O107="Fire Tex 5090",O107="Fire Tex 5120"),'CALCULO PINTURA'!S108," ") | T107: =+IF(OR(O107="Blaze Shield II",O107="Cafco 400",O107="Cafco 300"),'CALCULO MORTERO'!N108," ") | U107: =+IF(OR(O107="Blaze Shield II",O107="Cafco 400",O107="Cafco 300"),'CALCULO MORTERO'!O108," ") | V107: {=_xlfn.IFS(O107="Blaze Shield II",'CALCULO MORTERO'!P108, O107="Cafco 400",'CALCULO MORTERO'!Q108,O107="Cafco 300",'CALCULO MORTERO'!S108, AND(OR(O107="Fire tex 5090", O107="Fire Tex 5062", O107="Fire Tex 5120", O107="Fire Control"),Q107>0), "CERT.",TRUE,"-")} -> -
J108: 4 | N108: =+IF(F108="","",(K108*I108*H108*G108)/1000000) | P108: Software Idiem | Q108: =+IF(OR(O108="Fire Control",O108="Fire Tex 5062",O108="Fire Tex 5090",O108="Fire Tex 5120"),'CALCULO PINTURA'!P109," ") | R108: =+IF(OR(O108="Fire Control",O108="Fire Tex 5062",O108="Fire Tex 5090",O108="Fire Tex 5120"),'CALCULO PINTURA'!R109," ") | S108: =+IF(OR(O108="Fire Control",O108="Fire Tex 5062",O108="Fire Tex 5090",O108="Fire Tex 5120"),'CALCULO PINTURA'!S109," ") | T108: =+IF(OR(O108="Blaze Shield II",O108="Cafco 400",O108="Cafco 300"),'CALCULO MORTERO'!N109," ") | U108: =+IF(OR(O108="Blaze Shield II",O108="Cafco 400",O108="Cafco 300"),'CALCULO MORTERO'!O109," ") | V108: {=_xlfn.IFS(O108="Blaze Shield II",'CALCULO MORTERO'!P109, O108="Cafco 400",'CALCULO MORTERO'!Q109,O108="Cafco 300",'CALCULO MORTERO'!S109, AND(OR(O108="Fire tex 5090", O108="Fire Tex 5062", O108="Fire Tex 5120", O108="Fire Control"),Q108>0), "CERT.",TRUE,"-")} -> -
J109: 4 | N109: =+IF(F109="","",(K109*I109*H109*G109)/1000000) | P109: Software Idiem | Q109: =+IF(OR(O109="Fire Control",O109="Fire Tex 5062",O109="Fire Tex 5090",O109="Fire Tex 5120"),'CALCULO PINTURA'!P110," ") | R109: =+IF(OR(O109="Fire Control",O109="Fire Tex 5062",O109="Fire Tex 5090",O109="Fire Tex 5120"),'CALCULO PINTURA'!R110," ") | S109: =+IF(OR(O109="Fire Control",O109="Fire Tex 5062",O109="Fire Tex 5090",O109="Fire Tex 5120"),'CALCULO PINTURA'!S110," ") | T109: =+IF(OR(O109="Blaze Shield II",O109="Cafco 400",O109="Cafco 300"),'CALCULO MORTERO'!N110," ") | U109: =+IF(OR(O109="Blaze Shield II",O109="Cafco 400",O109="Cafco 300"),'CALCULO MORTERO'!O110," ") | V109: {=_xlfn.IFS(O109="Blaze Shield II",'CALCULO MORTERO'!P110, O109="Cafco 400",'CALCULO MORTERO'!Q110,O109="Cafco 300",'CALCULO MORTERO'!S110, AND(OR(O109="Fire tex 5090", O109="Fire Tex 5062", O109="Fire Tex 5120", O109="Fire Control"),Q109>0), "CERT.",TRUE,"-")} -> -
J110: 4 | N110: =+IF(F110="","",(K110*I110*H110*G110)/1000000) | P110: Software Idiem | Q110: =+IF(OR(O110="Fire Control",O110="Fire Tex 5062",O110="Fire Tex 5090",O110="Fire Tex 5120"),'CALCULO PINTURA'!P111," ") | R110: =+IF(OR(O110="Fire Control",O110="Fire Tex 5062",O110="Fire Tex 5090",O110="Fire Tex 5120"),'CALCULO PINTURA'!R111," ") | S110: =+IF(OR(O110="Fire Control",O110="Fire Tex 5062",O110="Fire Tex 5090",O110="Fire Tex 5120"),'CALCULO PINTURA'!S111," ") | T110: =+IF(OR(O110="Blaze Shield II",O110="Cafco 400",O110="Cafco 300"),'CALCULO MORTERO'!N111," ") | U110: =+IF(OR(O110="Blaze Shield II",O110="Cafco 400",O110="Cafco 300"),'CALCULO MORTERO'!O111," ") | V110: {=_xlfn.IFS(O110="Blaze Shield II",'CALCULO MORTERO'!P111, O110="Cafco 400",'CALCULO MORTERO'!Q111,O110="Cafco 300",'CALCULO MORTERO'!S111, AND(OR(O110="Fire tex 5090", O110="Fire Tex 5062", O110="Fire Tex 5120", O110="Fire Control"),Q110>0), "CERT.",TRUE,"-")} -> -
... J117: 4 | N117: =+IF(F117="","",(K117*I117*H117*G117)/1000000) | P117: Software Idiem | Q117: =+IF(OR(O117="Fire Control",O117="Fire Tex 5062",O117="Fire Tex 5090",O117="Fire Tex 5120"),'CALCULO PINTURA'!P118," ") | R117: =+IF(OR(O117="Fire Control",O117="Fire Tex 5062",O117="Fire Tex 5090",O117="Fire Tex 5120"),'CALCULO PINTURA'!R118," ") | S117: =+IF(OR(O117="Fire Control",O117="Fire Tex 5062",O117="Fire Tex 5090",O117="Fire Tex 5120"),'CALCULO PINTURA'!S118," ") | T117: =+IF(OR(O117="Blaze Shield II",O117="Cafco 400",O117="Cafco 300"),'CALCULO MORTERO'!N118," ") | U117: =+IF(OR(O117="Blaze Shield II",O117="Cafco 400",O117="Cafco 300"),'CALCULO MORTERO'!O118," ") | V117: {=_xlfn.IFS(O117="Blaze Shield II",'CALCULO MORTERO'!P118, O117="Cafco 400",'CALCULO MORTERO'!Q118,O117="Cafco 300",'CALCULO MORTERO'!S118, AND(OR(O117="Fire tex 5090", O117="Fire Tex 5062", O117="Fire Tex 5120", O117="Fire Control"),Q117>0), "CERT.",TRUE,"-")} -> -
...

Sheet FIRE CONTROL
C2: MASIVIDAD m-1 | D2: RESISTENCIA AL FUEGO
D3: F15 | E3: F30 | F3: F60 | G3: F90
C4: 60 | D4: 400 | E4: 400 | F4: 700 | G4: 1300
C5: 70 | D5: 400 | E5: 400 | F5: 750 | G5: 1400
C6: 80 | D6: 400 | E6: 400 | F6: 800 | G6: 1450
C7: 90 | D7: 400 | E7: 400 | F7: 850 | G7: 1550
C8: 100 | D8: 400 | E8: 400 | F8: 850 | G8: 1650
C9: 110 | D9: 400 | E9: 400 | F9: 900 | G9: 1700
C10: 120 | D10: 400 | E10: 400 | F10: 950 | G10: 1800
C11: 130 | D11: 400 | E11: 400 | F11: 1000
C12: 140 | D12: 400 | E12: 400 | F12: 1050
C13: 150 | D13: 400 | E13: 450 | F13: 1100
C14: 160 | D14: 400 | E14: 450 | F14: 1100
C15: 170 | D15: 400 | E15: 500 | F15: 1150
C16: 180 | D16: 400 | E16: 500 | F16: 1200
C17: 190 | D17: 400 | E17: 500 | F17: 1250
C18: 200 | D18: 400 | E18: 550 | F18: 1300
C19: 210 | D19: 400 | E19: 550 | F19: 1300
C20: 220 | D20: 400 | E20: 550 | F20: 1350
C21: 230 | D21: 400 | E21: 600 | F21: 1400
C22: 240 | D22: 400 | E22: 600 | F22: 1450
... C32: 340 | D32: 400 | E32: 750 | F32: 1800
C33: 350 | D33: 400 | E33: 750
C34: 360 | D34: 400 | E34: 800
C35: 370 | D35: 450 | E35: 800
C36: 380 | D36: 450 | E36: 800
C37: 390 | D37: 450 | E37: 800

Sheet FIRE TEX 5062
B2: IN BAJO LOSA | G2: IN 4 CARAS | L2: CJ BAJO LOSA | Q2: CJ 4 CARAS
B3: [m-1] | C3: F-15 | D3: F-30 | E3: F-60 | F3: F-90 | G3: [m-1] | H3: F-15 | I3: F-30 | J3: F-60 | K3: F-90 | L3: [m-1] | M3: F-15 | N3: F-30 | O3: F-60 | P3: F-90 | Q3: [m-1] | R3: F-15 | S3: F-30 | T3: F-60 | U3: F-90
B4: 60 | C4: 181 | D4: 181 | E4: 197 | F4: 650 | G4: 60 | H4: 174 | I4: 174 | J4: 193 | K4: 567 | L4: 60 | M4: 192 | N4: 192 | O4: 209 | P4: 689 | Q4: 60 | R4: 185 | S4: 185 | T4: 205 | U4: 602
B5: 70 | C5: 181 | D5: 181 | E5: 219 | F5: 730 | G5: 70 | H5: 174 | I5: 174 | J5: 216 | K5: 592 | L5: 70 | M5: 194 | N5: 194 | O5: 235 | P5: 782 | Q5: 70 | R5: 187 | S5: 187 | T5: 232 | U5: 634
B6: 80 | C6: 181 | D6: 181 | E6: 241 | F6: 809 | G6: 80 | H6: 174 | I6: 174 | J6: 238 | K6: 617 | L6: 80 | M6: 196 | N6: 196 | O6: 261 | P6: 874 | Q6: 80 | R6: 188 | S6: 188 | T6: 258 | U6: 667
B7: 90 | C7: 181 | D7: 181 | E7: 263 | F7: 889 | G7: 90 | H7: 174 | I7: 174 | J7: 261 | K7: 643 | L7: 90 | M7: 198 | N7: 198 | O7: 287 | Q7: 90 | R7: 190 | S7: 190 | T7: 285 | U7: 701
B8: 100 | C8: 181 | D8: 181 | E8: 285 | G8: 100 | H8: 174 | I8: 174 | J8: 283 | K8: 668 | L8: 100 | M8: 200 | N8: 200 | O8: 314 | Q8: 100 | R8: 192 | S8: 192 | T8: 312 | U8: 735
B9: 110 | C9: 181 | D9: 181 | E9: 306 | G9: 110 | H9: 174 | I9: 174 | J9: 306 | K9: 693 | L9: 110 | M9: 201 | N9: 201 | O9: 340 | Q9: 110 | R9: 194 | S9: 194 | T9: 340 | U9: 770
B10: 120 | C10: 181 | D10: 181 | E10: 328 | G10: 120 | H10: 174 | I10: 174 | J10: 328 | K10: 718 | L10: 120 | M10: 203 | N10: 203 | O10: 368 | Q10: 120 | R10: 195 | S10: 195 | T10: 368 | U10: 805
B11: 130 | C11: 181 | D11: 181 | E11: 350 | G11: 130 | H11: 174 | I11: 174 | J11: 351 | K11: 743 | L11: 130 | M11: 205 | N11: 205 | O11: 396 | Q11: 130 | R11: 197 | S11: 197 | T11: 397 | U11: 840
B12: 140 | C12: 181 | D12: 181 | E12: 372 | G12: 140 | H12: 174 | I12: 174 | J12: 373 | K12: 768 | L12: 140 | M12: 207 | N12: 207 | O12: 425 | Q12: 140 | R12: 199 | S12: 199 | T12: 426 | U12: 876
B13: 150 | C13: 181 | D13: 181 | E13: 394 | G13: 150 | H13: 174 | I13: 174 | J13: 396 | K13: 793 | L13: 150 | M13: 209 | N13: 209 | O13: 454 | Q13: 150 | R13: 201 | S13: 201 | T13: 456
B14: 160 | C14: 181 | D14: 181 | E14: 420 | G14: 160 | H14: 174 | I14: 174 | J14: 418 | K14: 818 | L14: 160 | M14: 210 | N14: 210 | O14: 488 | Q14: 160 | R14: 202 | S14: 202 | T14: 485
B15: 170 | C15: 181 | D15: 181 | E15: 449 | G15: 170 | H15: 174 | I15: 174 | J15: 441 | K15: 843 | L15: 170 | M15: 212 | N15: 212 | O15: 526 | Q15: 170 | R15: 204 | S15: 204 | T15: 516
B16: 180 | C16: 181 | D16: 181 | E16: 478 | G16: 180 | H16: 174 | I16: 174 | J16: 463 | K16: 868 | L16: 180 | M16: 214 | N16: 214 | O16: 565 | Q16: 180 | R16: 206 | S16: 206 | T16: 547
B17: 185 | C17: =+ROUNDUP(AVERAGE(C16,C18),0) -> 181 | D17: =+ROUNDUP(AVERAGE(D16,D18),0) -> 181 | E17: =+ROUNDUP(AVERAGE(E16,E18),0) -> 493 | G17: 185 | H17: 174 | I17: 174 | J17: 474 | K17: 881 | L17: 185 | M17: =+ROUNDUP(AVERAGE(M16,M18),0) -> 215 | N17: =+ROUNDUP(AVERAGE(N16,N18),0) -> 215 | O17: =+ROUNDUP(AVERAGE(O16,O18),0) -> 585 | Q17: 185 | R17: 207 | S17: 207 | T17: 562
B18: 190 | C18: 181 | D18: 181 | E18: 507 | G18: 190 | H18: 174 | I18: 174 | J18: 486 | L18: 190 | M18: 216 | N18: 216 | O18: 604 | Q18: 190 | R18: 208 | S18: 208 | T18: 579
B19: 200 | C19: 181 | D19: 181 | E19: 536 | G19: 200 | H19: 174 | I19: 174 | J19: 508 | L19: 200 | M19: 218 | N19: 218 | O19: 644 | Q19: 200 | R19: 209 | S19: 209 | T19: 610
B20: 210 | C20: 181 | D20: 181 | E20: 565 | G20: 210 | H20: 174 | I20: 174 | J20: 541 | L20: 210 | M20: 220 | N20: 220 | O20: 684 | Q20: 210 | R20: 211 | S20: 211 | T20: 655
B21: 220 | C21: 181 | D21: 181 | E21: 594 | G21: 220 | H21: 174 | I21: 174 | J21: 573 | L21: 220 | M21: 221 | N21: 221 | O21: 725 | Q21: 220 | R21: 213 | S21: 213 | T21: 700
B22: 230 | C22: 181 | D22: 181 | E22: 623 | G22: 230 | H22: 174 | I22: 174 | J22: 606 | L22: 230 | M22: 223 | N22: 223 | O22: 767 | Q22: 230 | R22: 215 | S22: 215 | T22: 746
B23: 240 | C23: 181 | D23: 181 | E23: 652 | G23: 240 | H23: 174 | I23: 174 | J23: 638 | L23: 240 | M23: 225 | N23: 225 | O23: 809 | Q23: 240 | R23: 216 | S23: 216 | T23: 792
B24: 245 | C24: 181 | D24: 181 | E24: 666 | G24: 245 | H24: =+ROUNDUP(AVERAGE(H23,H25),0) -> 174 | I24: =+ROUNDUP(AVERAGE(I23,I25),0) -> 174 | J24: =+ROUNDUP(AVERAGE(J23,J25),0) -> 655 | L24: 245 | M24: 226 | N24: 226 | O24: 830 | Q24: 245 | R24: =+ROUNDUP(AVERAGE(R23,R25),0) -> 217 | S24: =+ROUNDUP(AVERAGE(S23,S25),0) -> 217 | T24: =+ROUNDUP(AVERAGE(T23,T25),0) -> 816
B25: 250 | C25: 181 | D25: 181 | G25: 250 | H25: 174 | I25: 174 | J25: 671 | L25: 250 | M25: 227 | N25: 227 | Q25: 250 | R25: 218 | S25: 218 | T25: 839
B26: 260 | C26: 181 | D26: 181 | G26: 260 | H26: 174 | I26: 174 | J26: 704 | L26: 260 | M26: 229 | N26: 229 | Q26: 260 | R26: 220 | S26: 220
B27: 270 | C27: 181 | D27: 181 | G27: 270 | H27: 174 | I27: 174 | J27: 736 | L27: 270 | M27: 230 | N27: 230 | Q27: 270 | R27: 221 | S27: 221
B28: 280 | C28: 181 | D28: 181 | G28: 280 | H28: 174 | I28: 174 | J28: 769 | L28: 280 | M28: 232 | N28: 232 | Q28: 280 | R28: 223 | S28: 223
B29: 290 | C29: 181 | D29: 181 | G29: 290 | H29: 174 | I29: 174 | J29: 802 | L29: 290 | M29: 234 | N29: 234 | Q29: 290 | R29: 225 | S29: 225
B30: 300 | C30: 181 | D30: 181 | G30: 300 | H30: 174 | I30: 174 | J30: 834 | L30: 300 | M30: 236 | N30: 236 | Q30: 300 | R30: 227 | S30: 227
B31: 310 | C31: 181 | D31: 181 | G31: 310 | H31: 174 | I31: 174 | J31: 867 | L31: 310 | M31: 238 | N31: 238 | Q31: 310 | R31: 228 | S31: 228
B32: 320 | C32: 181 | D32: 181 | G32: 320 | H32: 174 | I32: 174 | L32: 320 | M32: 239 | N32: 239 | Q32: 320 | R32: 230 | S32: 230
B33: 330 | C33: 181 | D33: 181 | G33: 330 | H33: 174 | I33: 174 | L33: 330 | M33: 241 | N33: 241 | Q33: 330 | R33: 232 | S33: 232
B34: 340 | C34: 181 | D34: 191 | G34: 340 | L34: 340 | M34: 243 | N34: 256 | Q34: 340 | R34: 234 | S34: 234

Sheet FIRE TEX 5090
B2: PINTURA INTUMESCENTE FIRE TEX 5090 | J2: PINTURA INTUMESCENTE FIRE TEX 5090 | R2: PINTURA INTUMESCENTE FIRE TEX 5090 | Y2: PINTURA INTUMESCENTE FIRE TEX 5090
B3: IN BAJO LOSA | J3: IN 4 CARAS | R3: CJ BAJO LOSA | Y3: CJ 4 CARAS
B4: Masividad [m-1] | C4: F-15 | D4: F-30 | E4: F-60 | F4: F-90 | G4: F-120 | H4: F-150 | J4: Masividad [m-1] | K4: F-15 | L4: F-30 | M4: F-60 | N4: F-90 | O4: F-120 | P4: F-150 | R4: Masividad [m-1] | S4: F-15 | T4: F-30 | U4: F-60 | V4: F-90 | W4: F-120 | Y4: Masividad [m-1] | Z4: F-15 | AA4: F-30 | AB4: F-60 | AC4: F-90 | AD4: F-120
B5: 30 | C5: 196 | D5: 196 | E5: 196 | F5: 595 | G5: 875 | H5: 1658 | J5: 30 | K5: 177 | L5: 177 | M5: 177 | N5: 652 | O5: 1009 | P5: 1564 | R5: 30 | S5: 182 | T5: 182 | U5: 605 | V5: 1243 | W5: 1811 | Y5: 30 | Z5: 359 | AA5: 359 | AB5: 574 | AC5: 1365 | AD5: 2835
B6: 40 | C6: 196 | D6: 196 | E6: 263 | F6: 706 | G6: 1137 | H6: 1968 | J6: 40 | K6: 177 | L6: 177 | M6: 272 | N6: 781 | O6: 1334 | P6: 2180 | R6: 40 | S6: 182 | T6: 182 | U6: 605 | V6: 1243 | W6: 1811 | Y6: 40 | Z6: 359 | AA6: 359 | AB6: 574 | AC6: 1365 | AD6: 2835
B7: 45 | C7: =+ROUNDUP(AVERAGE(C6,C8),0) -> 196 | D7: =+ROUNDUP(AVERAGE(D6,D8),0) -> 196 | E7: =+ROUNDUP(AVERAGE(E6,E8),0) -> 329 | F7: =+ROUNDUP(AVERAGE(F6,F8),0) -> 761 | G7: =+ROUNDUP(AVERAGE(G6,G8),0) -> 1268 | H7: =+ROUNDUP(AVERAGE(H6,H8),0) -> 2103 | J7: 45 | K7: =+ROUNDUP(AVERAGE(K6,K8),0) -> 177 | L7: =+ROUNDUP(AVERAGE(L6,L8),0) -> 177 | M7: =+ROUNDUP(AVERAGE(M6,M8),0) -> 334 | N7: =+ROUNDUP(AVERAGE(N6,N8),0) -> 860 | O7: =+ROUNDUP(AVERAGE(O6,O8),0) -> 1514 | P7: =+ROUNDUP(AVERAGE(P6,P8),0) -> 2463 | R7: 45 | S7: 182 | T7: 182 | U7: 605 | V7: 1243 | W7: 1811 | Y7: 45 | Z7: 359 | AA7: 359 | AB7: 574 | AC7: 1365 | AD7: 2835
B8: 50 | C8: 196 | D8: 196 | E8: 395 | F8: 815 | G8: 1399 | H8: 2237 | J8: 50 | K8: 177 | L8: 177 | M8: 395 | N8: 939 | O8: 1693 | P8: 2745 | R8: 50 | S8: 182 | T8: 182 | U8: 650 | V8: 1287 | W8: 1915 | Y8: 50 | Z8: 359 | AA8: 359 | AB8: 574 | AC8: 1365 | AD8: 2835
B9: 60 | C9: 196 | D9: 196 | E9: 522 | F9: 924 | G9: 1661 | H9: 2507 | J9: 60 | K9: 177 | L9: 177 | M9: 517 | N9: 1096 | O9: 2053 | P9: 3256 | R9: 60 | S9: 182 | T9: 182 | U9: 739 | V9: 1374 | W9: 2386 | Y9: 60 | Z9: 359 | AA9: 359 | AB9: 671 | AC9: 1611 | AD9: 3241
B10: 70 | C10: 196 | D10: 196 | E10: 548 | F10: 1023 | G10: 1814 | H10: 2776 | J10: 70 | K10: 177 | L10: 177 | M10: 547 | N10: 1254 | O10: 2413 | P10: 3635 | R10: 70 | S10: 182 | T10: 182 | U10: 828 | V10: 1461 | W10: 3035 | Y10: 70 | Z10: 359 | AA10: 359 | AB10: 768 | AC10: 1809 | AD10: 3646
B11: 80 | C11: 196 | D11: 196 | E11: 574 | F11: 1122 | G11: 1930 | H11: 3045 | J11: 80 | K11: 177 | L11: 177 | M11: 576 | N11: 1380 | O11: 2657 | P11: 3901 | R11: 80 | S11: 182 | T11: 182 | U11: 917 | V11: 1548 | W11: 3574 | Y11: 80 | Z11: 359 | AA11: 359 | AB11: 865 | AC11: 1970 | AD11: 4051
B12: 90 | C12: 196 | D12: 196 | E12: 600 | F12: 1222 | G12: 2047 | H12: 3315 | J12: 90 | K12: 177 | L12: 177 | M12: 605 | N12: 1490 | O12: 2865 | P12: 4166 | R12: 90 | S12: 182 | T12: 182 | U12: 1006 | V12: 1634 | W12: 3893 | Y12: 90 | Z12: 359 | AA12: 359 | AB12: 913 | AC12: 2051 | AD12: 4254
B13: 100 | C13: 196 | D13: 196 | E13: 627 | F13: 1321 | G13: 2164 | H13: 3583 | J13: 100 | K13: 177 | L13: 177 | M13: 634 | N13: 1599 | O13: 3073 | P13: 4432 | R13: 100 | S13: 182 | T13: 182 | U13: 1096 | V13: 1722 | W13: 4212 | Y13: 100 | Z13: 359 | AA13: 359 | AB13: 962 | AC13: 2131
B14: 110 | C14: 196 | D14: 196 | E14: 653 | F14: 1420 | G14: 2281 | H14: 3714 | J14: 110 | K14: 177 | L14: 177 | M14: 663 | N14: 1709 | O14: 3281 | P14: 4697 | R14: 110 | S14: 182 | T14: 182 | U14: 1185 | V14: 1808 | W14: 4530 | Y14: 110 | Z14: 359 | AA14: 359 | AB14: 1058 | AC14: 2293
B15: 120 | C15: 196 | D15: 196 | E15: 679 | F15: 1519 | G15: 2397 | H15: 3845 | J15: 120 | K15: 177 | L15: 177 | M15: 693 | N15: 1819 | O15: 3489 | P15: 4963 | R15: 120 | S15: 182 | T15: 182 | U15: 1274 | V15: 1895 | W15: 4849 | Y15: 120 | Z15: 359 | AA15: 359 | AB15: 1155 | AC15: 2454
B16: 130 | C16: 196 | D16: 196 | E16: 705 | F16: 1618 | G16: 2514 | H16: 3977 | J16: 130 | K16: 177 | L16: 177 | M16: 722 | N16: 1928 | O16: 3631 | P16: 5228 | R16: 130 | S16: 182 | T16: 220 | U16: 1363 | V16: 1982 | W16: 5168 | Y16: 130 | Z16: 359 | AA16: 359 | AB16: 1252 | AC16: 2615
B17: 135 | C17: =+ROUNDUP(AVERAGE(C16,C18),0) -> 196 | D17: =+ROUNDUP(AVERAGE(D16,D18),0) -> 196 | E17: =+ROUNDUP(AVERAGE(E16,E18),0) -> 718 | F17: =+ROUNDUP(AVERAGE(F16,F18),0) -> 1668 | G17: =+ROUNDUP(AVERAGE(G16,G18),0) -> 5073 | H17: =+ROUNDUP(AVERAGE(H16,H18),0) -> 4043 | J17: 135 | K17: 177 | L17: 177 | M17: 736 | N17: 1983 | O17: 3702 | P17: 5361 | R17: 135 | S17: 182 | T17: 250 | U17: 1408 | V17: 2331 | W17: 5327 | Y17: 135 | Z17: 359 | AA17: 359 | AB17: 1349 | AC17: 2776
B18: 140 | C18: 196 | D18: 196 | E18: 731 | F18: 1717 | G18: 7631 | H18: 4108 | J18: 140 | K18: 177 | L18: 177 | M18: 751 | N18: 2038 | O18: 3772 | R18: 140 | S18: 182 | T18: 280 | U18: 1452 | V18: 2890 | Y18: 140 | Z18: 359 | AA18: 359 | AB18: 1449 | AC18: 3057
B19: 150 | C19: 196 | D19: 196 | E19: 758 | F19: 1804 | G19: 3747 | H19: 4239 | J19: 150 | K19: 177 | L19: 177 | M19: 780 | N19: 2148 | O19: 3913 | R19: 150 | S19: 182 | T19: 341 | U19: 1542 | V19: 3535 | Y19: 150 | Z19: 359 | AA19: 359 | AB19: 1543 | AC19: 3378
B20: 160 | C20: 196 | D20: 196 | E20: 784 | F20: 1891 | G20: 2864 | H20: 4370 | J20: 160 | K20: 177 | L20: 177 | M20: 809 | N20: 2257 | O20: 4054 | R20: 160 | S20: 182 | T20: 401 | U20: 1631 | V20: 3673 | Y20: 160 | Z20: 359 | AA20: 359 | AB20: 1639 | AC20: 3699
B21: 170 | C21: 196 | D21: 196 | E21: 810 | F21: 1977 | G21: 2981 | H21: 4501 | J21: 170 | K21: 177 | L21: 177 | M21: 838 | N21: 2367 | O21: 4194 | R21: 170 | S21: 182 | T21: 461 | U21: 1720 | V21: 3812 | Y21: 170 | Z21: 359 | AA21: 359 | AB21: 1730 | AC21: 4019
B22: 180 | C22: 196 | D22: 196 | E22: 836 | F22: 2063 | G22: 3097 | H22: 4632 | J22: 180 | K22: 177 | L22: 177 | M22: 868 | N22: 2477 | O22: 4335 | R22: 180 | S22: 182 | T22: 522 | U22: 1809 | V22: 3950 | Y22: 180 | Z22: 359 | AA22: 359 | AB22: 1797 | AC22: 4340
B23: 190 | C23: 196 | D23: 218 | E23: 863 | F23: 2149 | G23: 3214 | H23: 4763 | J23: 190 | K23: 177 | L23: 177 | M23: 897 | N23: 2548 | O23: 4476 | R23: 190 | S23: 182 | T23: 582 | U23: 1898 | V23: 4088 | Y23: 190 | Z23: 359 | AA23: 359 | AB23: 1863
B24: 200 | C24: 196 | D24: 241 | E24: 889 | F24: 2236 | G24: 3331 | H24: 4895 | J24: 200 | K24: 177 | L24: 177 | M24: 926 | N24: 2611 | O24: 4617 | R24: 200 | S24: 182 | T24: 643 | U24: 1987 | V24: 4227 | Y24: 200 | Z24: 359 | AA24: 359 | AB24: 1930
B25: 210 | C25: 196 | D25: 264 | E25: 916 | F25: 2322 | G25: 3447 | H25: 5026 | J25: 210 | K25: 177 | L25: 178 | M25: 955 | N25: 2673 | O25: 4758 | R25: 210 | S25: 182 | T25: 703 | U25: 2200 | V25: 4365 | Y25: 210 | Z25: 359 | AA25: 359 | AB25: 1996
B26: 220 | C26: 196 | D26: 286 | E26: 982 | F26: 2408 | G26: 3564 | H26: 5157 | J26: 220 | K26: 177 | L26: 213 | M26: 984 | N26: 2735 | O26: 4899 | R26: 220 | S26: 182 | T26: 764 | U26: 2433 | V26: 4503 | Y26: 220 | Z26: 359 | AA26: 359 | AB26: 2063
B27: 230 | C27: 196 | D27: 309 | E27: 1048 | F27: 2494 | G27: 3831 | H27: 5288 | J27: 230 | K27: 177 | L27: 248 | M27: 1014 | N27: 2797 | O27: 5039 | R27: 230 | S27: 182 | T27: 824 | U27: 2666 | V27: 4642 | Y27: 230 | Z27: 359 | AA27: 359 | AB27: 2129
B28: 240 | C28: 196 | D28: 332 | E28: 1114 | F28: 2580 | G28: 4125 | J28: 240 | K28: 177 | L28: 284 | M28: 1043 | N28: 2860 | O28: 5180 | R28: 240 | S28: 182 | T28: 885 | U28: 2899 | V28: 4780 | Y28: 240 | Z28: 359 | AA28: 359 | AB28: 2196
B29: 250 | C29: 196 | D29: 354 | E29: 1180 | F29: 2667 | G29: 4418 | J29: 250 | K29: 177 | L29: 319 | M29: 1072 | N29: 2922 | O29: 5321 | R29: 250 | S29: 182 | T29: 945 | U29: 3132 | V29: 4918 | Y29: 250 | Z29: 359 | AA29: 406 | AB29: 2262
B30: 260 | C30: 196 | D30: 377 | E30: 1246 | F30: 2753 | G30: 4713 | J30: 260 | K30: 177 | L30: 354 | M30: 1101 | N30: 2984 | R30: 260 | S30: 182 | T30: 976 | U30: 3249 | V30: 4987 | Y30: 260 | Z30: 359 | AA30: 466 | AB30: 2329
B31: 270 | C31: 196 | D31: 400 | E31: 1312 | F31: 2839 | G31: 5006 | J31: 270 | K31: 177 | L31: 389 | M31: 1150 | N31: 3047 | R31: 270 | Y31: 270 | Z31: 359 | AA31: 527 | AB31: 2395
B32: 280 | C32: 196 | D32: 423 | E32: 1378 | F32: 2925 | G32: 5300 | J32: 280 | K32: 177 | L32: 424 | M32: 1159 | N32: 3109 | R32: 280 | Y32: 280 | Z32: 359 | AA32: 588 | AB32: 2462
B33: 290 | C33: 196 | D33: 445 | E33: 1444 | F33: 3013 | G33: 5564 | J33: 290 | K33: 177 | L33: 442 | M33: 1189 | N33: 3171 | R33: 290 | Y33: 290 | Z33: 359 | AA33: 648 | AB33: 2529
B34: 300 | C34: 196 | D34: 468 | E34: 1511 | F34: 3098 | J34: 300 | K34: 177 | L34: 477 | M34: 1218 | N34: 3233 | R34: 300 | Y34: 300 | Z34: 359 | AA34: 709 | AB34: 2595
B35: 310 | C35: 196 | D35: 491 | E35: 1577 | F35: 3184 | J35: 310 | K35: 177 | L35: 512 | M35: 1247 | N35: 3296 | R35: 310 | Y35: 310 | Z35: 359 | AA35: 770 | AB35: 2662
B36: 320 | C36: 196 | D36: 513 | E36: 1643 | F36: 3270 | J36: 320 | K36: 177 | L36: 532 | M36: 1276 | N36: 3358 | R36: 320 | Y36: 320 | Z36: 359 | AA36: 830 | AB36: 2728
B37: 330 | C37: 196 | D37: 534 | E37: 1709 | F37: 3356 | J37: 330 | K37: =+ROUNDUP(AVERAGE(K36,K39),0) -> 177 | L37: =+ROUNDUP(AVERAGE(L36,L39),0) -> 404 | M37: =+ROUNDUP(AVERAGE(M36,M39),0) -> 1348 | N37: =+ROUNDUP(AVERAGE(N36,N39),0) -> 3421 | R37: 330 | Y37: 330 | Z37: 359 | AA37: 891 | AB37: 2795
B38: 335 | C38: 196 | D38: 543 | E38: 1747 | F38: 3400 | J38: 335 | K38: =+ROUNDUP(AVERAGE(K37,K39),0) -> 177 | L38: =+ROUNDUP(AVERAGE(L37,L39),0) -> 340 | M38: =+ROUNDUP(AVERAGE(M37,M39),0) -> 1384 | N38: =+ROUNDUP(AVERAGE(N37,N39),0) -> 3452 | R38: 335 | Y38: 335 | Z38: =+ROUNDUP(AVERAGE(Z37,Z39),0) -> 359 | AA38: =+ROUNDUP(AVERAGE(AA37,AA39),0) -> 921 | AB38: =+ROUNDUP(AVERAGE(AB37,AB39),0) -> 2828
B39: 340 | J39: 340 | K39: 177 | L39: 276 | M39: 1419 | N39: 3483 | R39: 340 | Y39: 340 | Z39: 359 | AA39: 951 | AB39: 2861
B40: 350 | J40: 350 | K40: 177 | L40: 596 | M40: 1540 | N40: 3825 | R40: 350 | Y40: 350
B41: 360 | J41: 360 | K41: 177 | L41: 617 | M41: 1660 | N41: 4224 | R41: 360 | Y41: 360
B42: 370 | J42: 370 | K42: 177 | L42: 637 | M42: 1780 | N42: 4623 | R42: 370 | Y42: 370
B43: 380 | J43: 380 | K43: 177 | L43: 658 | M43: 1900 | N43: 5022 | R43: 380 | Y43: 380

Sheet FIRE TEX 5120
O2: PINTURA INTUMESCENTE FIRE TEX 5120
B3: IN BAJO LOSA | H3: IN 4 CARAS | O3: CJ 4 CARAS
B4: Masividad [m-1] | C4: F-15 | D4: F-30 | E4: F-60 | F4: F-90 | G4: F-120 | H4: Masividad [m-1] | I4: F-15 | J4: F-30 | K4: F-60 | L4: F-90 | M4: F-120 | O4: Masividad [m-1] | P4: F-15 | Q4: F-30 | R4: F-60 | S4: F-90 | T4: F-120
B5: 47 | C5: 477 | D5: 477 | E5: 713 | F5: 1657 | G5: 2809 | H5: 47 | I5: 489 | J5: 489 | K5: 725 | L5: 1648 | M5: 2709 | O5: 47 | P5: 944 | Q5: 944 | R5: 944 | S5: 1463 | T5: 2855
B6: 48 | C6: 477 | D6: 477 | E6: 713 | F6: 1657 | G6: 2809 | H6: 48 | I6: 489 | J6: 489 | K6: 725 | L6: 1648 | M6: 2709 | O6: 48 | P6: 944 | Q6: 944 | R6: 944 | S6: 1463 | T6: 2861
B7: 49 | C7: 477 | D7: 477 | E7: 713 | F7: 1657 | G7: 2809 | H7: 49 | I7: =+ROUNDUP(AVERAGE(I6,I8),0) -> 489 | J7: =+ROUNDUP(AVERAGE(J6,J8),0) -> 489 | K7: =+ROUNDUP(AVERAGE(K6,K8),0) -> 725 | L7: =+ROUNDUP(AVERAGE(L6,L8),0) -> 1648 | M7: =+ROUNDUP(AVERAGE(M6,M8),0) -> 2709 | O7: 49 | P7: 944 | Q7: 944 | R7: 944 | S7: 1463 | T7: 2861
B8: 50 | C8: 477 | D8: 477 | E8: 713 | F8: 1657 | G8: 2815 | H8: 50 | I8: 489 | J8: 489 | K8: 725 | L8: 1648 | M8: 2709 | O8: 50 | P8: 944 | Q8: 944 | R8: 944 | S8: 1463 | T8: 2861
B9: 60 | C9: 477 | D9: 477 | E9: 804 | F9: 1877 | G9: 3085 | H9: 60 | I9: 489 | J9: 489 | K9: 841 | L9: 1902 | M9: 3131 | O9: 60 | P9: 944 | Q9: 944 | R9: 944 | S9: 1755 | T9: 3360
B10: 70 | C10: 477 | D10: 477 | E10: 905 | F10: 2147 | G10: 3354 | H10: 70 | I10: 489 | J10: 489 | K10: 987 | L10: 2243 | M10: 3596 | O10: 70 | P10: 944 | Q10: 944 | R10: 1144 | S10: 2600 | T10: 3898
B11: 80 | C11: 477 | D11: 477 | E11: 993 | F11: 2418 | G11: 3624 | H11: 80 | I11: 489 | J11: 489 | K11: 1101 | L11: 2546 | M11: 4000 | O11: 80 | P11: 944 | Q11: 944 | R11: 1356 | S11: 3150 | T11: 4533
B12: 90 | C12: 477 | D12: 477 | E12: 1063 | F12: 2536 | G12: 3894 | H12: 90 | I12: 489 | J12: 489 | K12: 1211 | L12: 2782 | M12: 4404 | O12: 90 | P12: 944 | Q12: 944 | R12: 1568 | S12: 3514 | T12: 5168
B13: 100 | C13: 477 | D13: 477 | E13: 1134 | F13: 2637 | G13: 4164 | H13: 100 | I13: 489 | J13: 489 | K13: 1322 | L13: 3019 | M13: 4737 | O13: 100 | P13: 944 | Q13: 944 | R13: 1780 | S13: 3862 | T13: 5803
B14: 110 | C14: 477 | D14: 477 | E14: 1204 | F14: 2739 | G14: 4434 | H14: 110 | I14: 489 | J14: 489 | K14: 1432 | L14: 3255 | M14: 4850 | O14: 110 | P14: 944 | Q14: 944 | R14: 2049 | S14: 4189 | T14: 6438
B15: 120 | C15: 477 | D15: 477 | E15: 1274 | F15: 2841 | G15: 4704 | H15: 120 | I15: 489 | J15: 489 | K15: 1542 | L15: 3487 | M15: 4963 | O15: 120 | P15: 944 | Q15: 944 | R15: 2457 | S15: 4516 | T15: 7073
B16: 130 | C16: 477 | D16: 477 | E16: 1344 | F16: 2943 | G16: 4974 | H16: 130 | I16: 489 | J16: 489 | K16: 1653 | L16: 3569 | M16: 5077 | O16: 130 | P16: 944 | Q16: 944 | R16: 2862 | S16: 4843 | T16: 7708
B17: 140 | C17: 477 | D17: 477 | E17: 1415 | F17: 3044 | G17: 5244 | H17: 140 | I17: 489 | J17: 489 | K17: 1763 | L17: 3651 | M17: 5190 | O17: 140 | P17: 944 | Q17: 944 | R17: 3100 | S17: 5170 | T17: 8343
B18: 150 | C18: 477 | D18: 477 | E18: 1485 | F18: 3146 | G18: 5513 | H18: 150 | I18: 489 | J18: 489 | K18: 1873 | L18: 3733 | M18: 5303 | O18: 150 | P18: 944 | Q18: 1005 | R18: 3338 | S18: 5497
B19: 155 | C19: 477 | D19: 477 | E19: 1520 | F19: 3197 | G19: 5635 | H19: 155 | I19: =+ROUNDUP(AVERAGE(I18,I20),0) -> 489 | J19: =+ROUNDUP(AVERAGE(J18,J20),0) -> 489 | K19: =+ROUNDUP(AVERAGE(K18,K20),0) -> 1929 | L19: =+ROUNDUP(AVERAGE(L18,L20),0) -> 3774 | M19: =+ROUNDUP(AVERAGE(M18,M20),0) -> 5360 | O19: 155 | P19: =+ROUNDUP(AVERAGE(P18,P20),0) -> 944 | Q19: =+ROUNDUP(AVERAGE(Q18,Q20),0) -> 1036 | R19: =+ROUNDUP(AVERAGE(R18,R20),0) -> 3457 | S19: =+ROUNDUP(AVERAGE(S18,S20),0) -> 5661
B20: 160 | C20: 477 | D20: 477 | E20: 1555 | F20: 3248 | H20: 160 | I20: 489 | J20: 489 | K20: 1984 | L20: 3815 | M20: 5416 | O20: 160 | P20: 944 | Q20: 1066 | R20: 3576 | S20: 5824
B21: 170 | C21: 477 | D21: 477 | E21: 1626 | F21: 3349 | H21: 170 | I21: 489 | J21: 496 | K21: 2094 | L21: 3896 | M21: 5529 | O21: 170 | P21: 944 | Q21: 1126 | R21: 3793 | S21: 6218
B22: 180 | C22: 477 | D22: 477 | E22: 1696 | F22: 3451 | H22: 180 | I22: 489 | J22: 532 | K22: 2204 | L22: 3978 | M22: 5642 | O22: 180 | P22: 944 | Q22: 1187 | R22: 3979 | S22: 6618
B23: 190 | C23: 477 | D23: 477 | E23: 1766 | F23: 3551 | H23: 190 | I23: 489 | J23: 568 | K23: 2314 | L23: 4060 | M23: 5755 | O23: 190 | P23: 944 | Q23: 1247 | R23: 4165 | S23: 7018
B24: 200 | C24: 477 | D24: 477 | E24: 1836 | F24: 3649 | H24: 200 | I24: 489 | J24: 604 | K24: 2425 | L24: 4142 | M24: 5868 | O24: 200 | P24: 944 | Q24: 1307 | R24: 4352 | S24: 7418
B25: 210 | C25: 477 | D25: 509 | E25: 1907 | F25: 3748 | H25: 210 | I25: 489 | J25: 640 | K25: 2510 | L25: 4223 | M25: 5981 | O25: 210 | P25: 944 | Q25: 1368 | R25: 4538 | S25: 7818
B26: 220 | C26: 477 | D26: 546 | E26: 1977 | F26: 3846 | H26: 220 | I26: 489 | J26: 676 | K26: 2583 | L26: 4305 | M26: 6094 | O26: 220 | P26: 944 | Q26: 1428 | R26: 4724 | S26: 8218
B27: 230 | C27: 477 | D27: 583 | E27: 2047 | F27: 3945 | H27: 230 | I27: 489 | J27: 713 | K27: 2657 | L27: 4387 | M27: 6207 | O27: 230 | P27: 944 | Q27: 1489 | R27: 4910
B28: 240 | C28: 477 | D28: 620 | E28: 2118 | F28: 4043 | H28: 240 | I28: 489 | J28: 749 | K28: 2730 | L28: 4469 | M28: 6320 | O28: 240 | P28: 944 | Q28: 1549 | R28: 5096
B29: 250 | C29: 477 | D29: 657 | E29: 2188 | F29: 4142 | H29: 250 | I29: 489 | J29: 785 | K29: 2804 | L29: 4551 | M29: 6433 | O29: 250 | P29: 944 | Q29: 1610 | R29: 5283
B30: 260 | C30: 477 | D30: 694 | E30: 2258 | F30: 4240 | H30: 260 | I30: 489 | J30: 821 | K30: 2877 | L30: 4632 | M30: 6547 | O30: 260 | P30: 944 | Q30: 1670 | R30: 5469
B31: 270 | C31: 477 | D31: 732 | E31: 2328 | F31: 4339 | H31: 270 | I31: 489 | J31: 857 | K31: 2951 | L31: 4719 | M31: 6660 | O31: 270 | P31: 944 | Q31: 1731 | R31: 5655
B32: 280 | C32: 477 | D32: 769 | E32: 2399 | F32: 4437 | H32: 280 | I32: 489 | J32: 894 | K32: 3024 | L32: 4892 | M32: 6773 | O32: 280 | P32: 944 | Q32: 1791 | R32: 5841
B33: 290 | C33: 477 | D33: 806 | E33: 2493 | F33: 4535 | H33: 290 | I33: 489 | J33: 930 | K33: 3098 | L33: 5066 | M33: 6886 | O33: 290 | P33: 944 | Q33: 1852 | R33: 6054
B34: 300 | C34: 477 | D34: 843 | E34: 2629 | F34: 4634 | H34: 300 | I34: 489 | J34: 966 | K34: 3171 | L34: 5239 | M34: 6999 | O34: 300 | P34: 944 | Q34: 1912 | R34: 6268
B35: 310 | C35: 477 | D35: 880 | E35: 2765 | F35: 4732 | H35: 310 | I35: 489 | J35: 1002 | K35: 3244 | L35: 5413 | M35: 7112 | O35: 310 | P35: 944 | Q35: 2000 | R35: 6482
B36: 320 | C36: 477 | D36: 917 | E36: 2902 | F36: 4831 | H36: 320 | I36: 489 | J36: 1056 | K36: 3318 | L36: 5586 | M36: 7225 | O36: 320 | P36: 944 | Q36: 2098 | R36: 6696
B37: =+ROUNDUP(AVERAGE(B36,B38),0) -> 325 | C37: =+ROUNDUP(AVERAGE(C36,C38),0) -> 477 | D37: =+ROUNDUP(AVERAGE(D36,D38),0) -> 936 | E37: =+ROUNDUP(AVERAGE(E36,E38),0) -> 2970 | F37: =+ROUNDUP(AVERAGE(F36,F38),0) -> 4880 | H37: =+ROUNDUP(AVERAGE(H36,H38),0) -> 325 | I37: 489 | J37: 1083 | K37: 3355 | L37: 5673 | M37: 7282 | O37: =+ROUNDUP(AVERAGE(O36,O38),0) -> 325 | P37: 944 | Q37: 2147 | R37: 6803
B38: 330 | C38: 477 | D38: 954 | E38: 3038 | F38: 4929 | H38: 330 | I38: 489 | J38: 1110 | K38: 3391 | L38: 5760 | O38: 330
B39: 335 | C39: =+ROUNDUP(AVERAGE(C38,C40),0) -> 477 | D39: =+ROUNDUP(AVERAGE(D38,D40),0) -> 979 | E39: =+ROUNDUP(AVERAGE(E38,E40),0) -> 3107 | F39: =+ROUNDUP(AVERAGE(F38,F40),0) -> 4979 | H39: 335 | I39: 489 | J39: 1137 | K39: 3428 | L39: 5847 | O39: 335
B40: 340 | C40: 477 | D40: 1004 | E40: 3175 | F40: 5028 | H40: 340 | O40: 340

Sheet AUTO CALCULO
D5: D | E5: E
D6: H | E6: A | F6: T
D7: H | E7: A Y B | F7: E | G7: T
A8: PERFIL | B8: DIMENSIONES | C8: CARAS | D8: H | E8: A | F8: E1 | G8: B | H8: E2 | I8: T | J8: AREA
A9: =CUBICACION!F9 -> CJ | B9: =CUBICACION!E9 -> MM 400X200X4 | C9: =CUBICACION!J9 -> 4 | D9: {=_xlfn.TEXTSPLIT(B9,{"X";"x"})} -> MM 400 | E9: 200 | F9: 4 | J9: {=_xlfn.IFS(AND(A9="IN",I9<>""), (E9*F9+G9*H9)+I9*(D9-F9-H9),AND(A9="IN",I9=""), (2*E9*F9)+G9*(D9-2*F9),AND(A9="CJ",F9<>""),(D9*E9)-((D9-2*F9)*(E9-2*F9)),AND(A9="CJ",F9=""),ROUND((PI()*(D9/2)^2)-(PI()*(D9/2-E9)^2),0),AND(A9="C",G9=""),(2*E9*F9)+((D9-2*F9)*F9),TRUE,"")} -> #VALUE!
A10: =CUBICACION!F10 -> CJ | B10: =CUBICACION!E10 -> MM 400X200X4 | C10: =CUBICACION!J10 -> 4 | D10: {=_xlfn.TEXTSPLIT(B10,{"X";"x"})} -> MM 400 | E10: 200 | F10: 4 | J10: {=_xlfn.IFS(AND(A10="IN",I10<>""), (E10*F10+G10*H10)+I10*(D10-F10-H10),AND(A10="IN",I10=""), (2*E10*F10)+G10*(D10-2*F10),AND(A10="CJ",F10<>""),(D10*E10)-((D10-2*F10)*(E10-2*F10)),AND(A10="CJ",F10=""),ROUND((PI()*(D10/2)^2)-(PI()*(D10/2-E10)^2),0),TRUE,"")} -> #VALUE!
A11: =CUBICACION!F11 -> CJ | B11: =CUBICACION!E11 -> 150X150X5 | C11: =CUBICACION!J11 -> 4 | D11: {=_xlfn.TEXTSPLIT(B11,{"X";"x"})} -> 150 | E11: 150 | F11: 5 | J11: {=_xlfn.IFS(AND(A11="IN",I11<>""), (E11*F11+G11*H11)+I11*(D11-F11-H11),AND(A11="IN",I11=""), (2*E11*F11)+G11*(D11-2*F11),AND(A11="CJ",F11<>""),(D11*E11)-((D11-2*F11)*(E11-2*F11)),AND(A11="CJ",F11=""),ROUND((PI()*(D11/2)^2)-(PI()*(D11/2-E11)^2),0),TRUE,"")} -> 2900
A12: =CUBICACION!F12 -> CJ | B12: =CUBICACION!E12 -> 200X100X3 | C12: =CUBICACION!J12 -> 4 | D12: {=_xlfn.TEXTSPLIT(B12,{"X";"x"})} -> 200 | E12: 100 | F12: 3 | J12: {=_xlfn.IFS(AND(A12="IN",I12<>""), (E12*F12+G12*H12)+I12*(D12-F12-H12),AND(A12="IN",I12=""), (2*E12*F12)+G12*(D12-2*F12),AND(A12="CJ",F12<>""),(D12*E12)-((D12-2*F12)*(E12-2*F12)),AND(A12="CJ",F12=""),ROUND((PI()*(D12/2)^2)-(PI()*(D12/2-E12)^2),0),TRUE,"")} -> 1764
A13: =CUBICACION!F13 -> CJ | B13: =CUBICACION!E13 -> 100X100X3 | C13: =CUBICACION!J13 -> 4 | D13: {=_xlfn.TEXTSPLIT(B13,{"X";"x"})} -> 100 | E13: 100 | F13: 3 | J13: {=_xlfn.IFS(AND(A13="IN",I13<>""), (E13*F13+G13*H13)+I13*(D13-F13-H13),AND(A13="IN",I13=""), (2*E13*F13)+G13*(D13-2*F13),AND(A13="CJ",F13<>""),(D13*E13)-((D13-2*F13)*(E13-2*F13)),AND(A13="CJ",F13=""),ROUND((PI()*(D13/2)^2)-(PI()*(D13/2-E13)^2),0),TRUE,"")} -> 1164
A14: =CUBICACION!F14 -> CJ | B14: =CUBICACION!E14 -> 100X100X3 | C14: =CUBICACION!J14 -> 4 | D14: {=_xlfn.TEXTSPLIT(B14,{"X";"x"})} -> 100 | E14: 100 | F14: 3 | J14: {=_xlfn.IFS(AND(A14="IN",I14<>""), (E14*F14+G14*H14)+I14*(D14-F14-H14),AND(A14="IN",I14=""), (2*E14*F14)+G14*(D14-2*F14),AND(A14="CJ",F14<>""),(D14*E14)-((D14-2*F14)*(E14-2*F14)),AND(A14="CJ",F14=""),ROUND((PI()*(D14/2)^2)-(PI()*(D14/2-E14)^2),0),TRUE,"")} -> 1164
A15: =CUBICACION!F15 -> CJ | B15: =CUBICACION!E15 -> MM 400X200X4 | C15: =CUBICACION!J15 -> 4 | D15: {=_xlfn.TEXTSPLIT(B15,{"X";"x"})} -> MM 400 | E15: 200 | F15: 4 | J15: {=_xlfn.IFS(AND(A15="IN",I15<>""), (E15*F15+G15*H15)+I15*(D15-F15-H15),AND(A15="IN",I15=""), (2*E15*F15)+G15*(D15-2*F15),AND(A15="CJ",F15<>""),(D15*E15)-((D15-2*F15)*(E15-2*F15)),AND(A15="CJ",F15=""),ROUND((PI()*(D15/2)^2)-(PI()*(D15/2-E15)^2),0),TRUE,"")} -> #VALUE!
A16: =CUBICACION!F16 -> CJ | B16: =CUBICACION!E16 -> MM 400X200X4 | C16: =CUBICACION!J16 -> 4 | D16: {=_xlfn.TEXTSPLIT(B16,{"X";"x"})} -> MM 400 | E16: 200 | F16: 4 | J16: {=_xlfn.IFS(AND(A16="IN",I16<>""), (E16*F16+G16*H16)+I16*(D16-F16-H16),AND(A16="IN",I16=""), (2*E16*F16)+G16*(D16-2*F16),AND(A16="CJ",F16<>""),(D16*E16)-((D16-2*F16)*(E16-2*F16)),AND(A16="CJ",F16=""),ROUND((PI()*(D16/2)^2)-(PI()*(D16/2-E16)^2),0),TRUE,"")} -> #VALUE!
A17: =CUBICACION!F17 -> CJ | B17: =CUBICACION!E17 -> 150X150X5 | C17: =CUBICACION!J17 -> 4 | D17: {=_xlfn.TEXTSPLIT(B17,{"X";"x"})} -> 150 | E17: 150 | F17: 5 | J17: {=_xlfn.IFS(AND(A17="IN",I17<>""), (E17*F17+G17*H17)+I17*(D17-F17-H17),AND(A17="IN",I17=""), (2*E17*F17)+G17*(D17-2*F17),AND(A17="CJ",F17<>""),(D17*E17)-((D17-2*F17)*(E17-2*F17)),AND(A17="CJ",F17=""),ROUND((PI()*(D17/2)^2)-(PI()*(D17/2-E17)^2),0),TRUE,"")} -> 2900
A18: =CUBICACION!F18 -> CJ | B18: =CUBICACION!E18 -> 200X100X3 | C18: =CUBICACION!J18 -> 4 | D18: {=_xlfn.TEXTSPLIT(B18,{"X";"x"})} -> 200 | E18: 100 | F18: 3 | J18: {=_xlfn.IFS(AND(A18="IN",I18<>""), (E18*F18+G18*H18)+I18*(D18-F18-H18),AND(A18="IN",I18=""), (2*E18*F18)+G18*(D18-2*F18),AND(A18="CJ",F18<>""),(D18*E18)-((D18-2*F18)*(E18-2*F18)),AND(A18="CJ",F18=""),ROUND((PI()*(D18/2)^2)-(PI()*(D18/2-E18)^2),0),TRUE,"")} -> 1764
A19: =CUBICACION!F19 -> CJ | B19: =CUBICACION!E19 -> 100X100X3 | C19: =CUBICACION!J19 -> 4 | D19: {=_xlfn.TEXTSPLIT(B19,{"X";"x"})} -> 100 | E19: 100 | F19: 3 | J19: {=_xlfn.IFS(AND(A19="IN",I19<>""), (E19*F19+G19*H19)+I19*(D19-F19-H19),AND(A19="IN",I19=""), (2*E19*F19)+G19*(D19-2*F19),AND(A19="CJ",F19<>""),(D19*E19)-((D19-2*F19)*(E19-2*F19)),AND(A19="CJ",F19=""),ROUND((PI()*(D19/2)^2)-(PI()*(D19/2-E19)^2),0),TRUE,"")} -> 1164
A20: =CUBICACION!F20 -> CJ | B20: =CUBICACION!E20 -> 100X100X3 | C20: =CUBICACION!J20 -> 4 | D20: {=_xlfn.TEXTSPLIT(B20,{"X";"x"})} -> 100 | E20: 100 | F20: 3 | J20: {=_xlfn.IFS(AND(A20="IN",I20<>""), (E20*F20+G20*H20)+I20*(D20-F20-H20),AND(A20="IN",I20=""), (2*E20*F20)+G20*(D20-2*F20),AND(A20="CJ",F20<>""),(D20*E20)-((D20-2*F20)*(E20-2*F20)),AND(A20="CJ",F20=""),ROUND((PI()*(D20/2)^2)-(PI()*(D20/2-E20)^2),0),TRUE,"")} -> 1164
A21: =CUBICACION!F21 -> CJ | B21: =CUBICACION!E21 -> 200X100X4 | C21: =CUBICACION!J21 -> 4 | D21: {=_xlfn.TEXTSPLIT(B21,{"X";"x"})} -> 200 | E21: 100 | F21: 4 | J21: {=_xlfn.IFS(AND(A21="IN",I21<>""), (E21*F21+G21*H21)+I21*(D21-F21-H21),AND(A21="IN",I21=""), (2*E21*F21)+G21*(D21-2*F21),AND(A21="CJ",F21<>""),(D21*E21)-((D21-2*F21)*(E21-2*F21)),AND(A21="CJ",F21=""),ROUND((PI()*(D21/2)^2)-(PI()*(D21/2-E21)^2),0),TRUE,"")} -> 2336
... A23: =CUBICACION!F23 -> CJ | B23: =CUBICACION!E23 -> 150X150X5 | C23: =CUBICACION!J23 -> 4 | D23: {=_xlfn.TEXTSPLIT(B23,{"X";"x"})} -> 150 | E23: 150 | F23: 5 | J23: {=_xlfn.IFS(AND(A23="IN",I23<>""), (E23*F23+G23*H23)+I23*(D23-F23-H23),AND(A23="IN",I23=""), (2*E23*F23)+G23*(D23-2*F23),AND(A23="CJ",F23<>""),(D23*E23)-((D23-2*F23)*(E23-2*F23)),AND(A23="CJ",F23=""),ROUND((PI()*(D23/2)^2)-(PI()*(D23/2-E23)^2),0),TRUE,"")} -> 2900
A24: =CUBICACION!F24 -> 0 | B24: =CUBICACION!E24 -> 0 | C24: =CUBICACION!J24 -> 4 | D24: {=_xlfn.TEXTSPLIT(B24,{"X";"x"})} -> 0 | J24: {=_xlfn.IFS(AND(A24="IN",I24<>""), (E24*F24+G24*H24)+I24*(D24-F24-H24),AND(A24="IN",I24=""), (2*E24*F24)+G24*(D24-2*F24),AND(A24="CJ",F24<>""),(D24*E24)-((D24-2*F24)*(E24-2*F24)),AND(A24="CJ",F24=""),ROUND((PI()*(D24/2)^2)-(PI()*(D24/2-E24)^2),0),TRUE,"")}
A25: =CUBICACION!F25 -> 0 | B25: =CUBICACION!E25 -> 0 | C25: =CUBICACION!J25 -> 4 | D25: {=_xlfn.TEXTSPLIT(B25,{"X";"x"})} -> 0 | J25: {=_xlfn.IFS(AND(A25="IN",I25<>""), (E25*F25+G25*H25)+I25*(D25-F25-H25),AND(A25="IN",I25=""), (2*E25*F25)+G25*(D25-2*F25),AND(A25="CJ",F25<>""),(D25*E25)-((D25-2*F25)*(E25-2*F25)),AND(A25="CJ",F25=""),ROUND((PI()*(D25/2)^2)-(PI()*(D25/2-E25)^2),0),TRUE,"")}
A26: =CUBICACION!F26 -> CJ | B26: =CUBICACION!E26 -> M1 MM600X225X4 | C26: =CUBICACION!J26 -> 4 | D26: {=_xlfn.TEXTSPLIT(B26,{"X";"x"})} -> M1 MM600 | E26: 225 | F26: 4 | J26: {=_xlfn.IFS(AND(A26="IN",I26<>""), (E26*F26+G26*H26)+I26*(D26-F26-H26),AND(A26="IN",I26=""), (2*E26*F26)+G26*(D26-2*F26),AND(A26="CJ",F26<>""),(D26*E26)-((D26-2*F26)*(E26-2*F26)),AND(A26="CJ",F26=""),ROUND((PI()*(D26/2)^2)-(PI()*(D26/2-E26)^2),0),TRUE,"")} -> #VALUE!
A27: =CUBICACION!F27 -> CJ | B27: =CUBICACION!E27 -> M1 MM600X225X4 | C27: =CUBICACION!J27 -> 4 | D27: {=_xlfn.TEXTSPLIT(B27,{"X";"x"})} -> M1 MM600 | E27: 225 | F27: 4 | J27: {=_xlfn.IFS(AND(A27="IN",I27<>""), (E27*F27+G27*H27)+I27*(D27-F27-H27),AND(A27="IN",I27=""), (2*E27*F27)+G27*(D27-2*F27),AND(A27="CJ",F27<>""),(D27*E27)-((D27-2*F27)*(E27-2*F27)),AND(A27="CJ",F27=""),ROUND((PI()*(D27/2)^2)-(PI()*(D27/2-E27)^2),0),TRUE,"")} -> #VALUE!
A28: =CUBICACION!F28 -> CJ | B28: =CUBICACION!E28 -> M1 MM600X225X4 | C28: =CUBICACION!J28 -> 4 | D28: {=_xlfn.TEXTSPLIT(B28,{"X";"x"})} -> M1 MM600 | E28: 225 | F28: 4 | J28: {=_xlfn.IFS(AND(A28="IN",I28<>""), (E28*F28+G28*H28)+I28*(D28-F28-H28),AND(A28="IN",I28=""), (2*E28*F28)+G28*(D28-2*F28),AND(A28="CJ",F28<>""),(D28*E28)-((D28-2*F28)*(E28-2*F28)),AND(A28="CJ",F28=""),ROUND((PI()*(D28/2)^2)-(PI()*(D28/2-E28)^2),0),TRUE,"")} -> #VALUE!
A29: =CUBICACION!F29 -> CJ | B29: =CUBICACION!E29 -> M1 MM600X225X4 | C29: =CUBICACION!J29 -> 4 | D29: {=_xlfn.TEXTSPLIT(B29,{"X";"x"})} -> M1 MM600 | E29: 225 | F29: 4 | J29: {=_xlfn.IFS(AND(A29="IN",I29<>""), (E29*F29+G29*H29)+I29*(D29-F29-H29),AND(A29="IN",I29=""), (2*E29*F29)+G29*(D29-2*F29),AND(A29="CJ",F29<>""),(D29*E29)-((D29-2*F29)*(E29-2*F29)),AND(A29="CJ",F29=""),ROUND((PI()*(D29/2)^2)-(PI()*(D29/2-E29)^2),0),TRUE,"")} -> #VALUE!
A30: =CUBICACION!F30 -> CJ | B30: =CUBICACION!E30 -> M1 MM600X225X4 | C30: =CUBICACION!J30 -> 4 | D30: {=_xlfn.TEXTSPLIT(B30,{"X";"x"})} -> M1 MM600 | E30: 225 | F30: 4 | J30: {=_xlfn.IFS(AND(A30="IN",I30<>""), (E30*F30+G30*H30)+I30*(D30-F30-H30),AND(A30="IN",I30=""), (2*E30*F30)+G30*(D30-2*F30),AND(A30="CJ",F30<>""),(D30*E30)-((D30-2*F30)*(E30-2*F30)),AND(A30="CJ",F30=""),ROUND((PI()*(D30/2)^2)-(PI()*(D30/2-E30)^2),0),TRUE,"")} -> #VALUE!
A31: =CUBICACION!F31 -> CJ | B31: =CUBICACION!E31 -> 200X100X4 | C31: =CUBICACION!J31 -> 4 | D31: {=_xlfn.TEXTSPLIT(B31,{"X";"x"})} -> 200 | E31: 100 | F31: 4 | J31: {=_xlfn.IFS(AND(A31="IN",I31<>""), (E31*F31+G31*H31)+I31*(D31-F31-H31),AND(A31="IN",I31=""), (2*E31*F31)+G31*(D31-2*F31),AND(A31="CJ",F31<>""),(D31*E31)-((D31-2*F31)*(E31-2*F31)),AND(A31="CJ",F31=""),ROUND((PI()*(D31/2)^2)-(PI()*(D31/2-E31)^2),0),TRUE,"")} -> 2336
A32: =CUBICACION!F32 -> CJ | B32: =CUBICACION!E32 -> 200X100X4 | C32: =CUBICACION!J32 -> 4 | D32: {=_xlfn.TEXTSPLIT(B32,{"X";"x"})} -> 200 | E32: 100 | F32: 4 | J32: {=_xlfn.IFS(AND(A32="IN",I32<>""), (E32*F32+G32*H32)+I32*(D32-F32-H32),AND(A32="IN",I32=""), (2*E32*F32)+G32*(D32-2*F32),AND(A32="CJ",F32<>""),(D32*E32)-((D32-2*F32)*(E32-2*F32)),AND(A32="CJ",F32=""),ROUND((PI()*(D32/2)^2)-(PI()*(D32/2-E32)^2),0),TRUE,"")} -> 2336
A33: =CUBICACION!F33 -> CJ | B33: =CUBICACION!E33 -> 200X100X3 | C33: =CUBICACION!J33 -> 4 | D33: {=_xlfn.TEXTSPLIT(B33,{"X";"x"})} -> 200 | E33: 100 | F33: 3 | J33: {=_xlfn.IFS(AND(A33="IN",I33<>""), (E33*F33+G33*H33)+I33*(D33-F33-H33),AND(A33="IN",I33=""), (2*E33*F33)+G33*(D33-2*F33),AND(A33="CJ",F33<>""),(D33*E33)-((D33-2*F33)*(E33-2*F33)),AND(A33="CJ",F33=""),ROUND((PI()*(D33/2)^2)-(PI()*(D33/2-E33)^2),0),TRUE,"")} -> 1764
A34: =CUBICACION!F34 -> CJ | B34: =CUBICACION!E34 -> 150X150X5 | C34: =CUBICACION!J34 -> 4 | D34: {=_xlfn.TEXTSPLIT(B34,{"X";"x"})} -> 150 | E34: 150 | F34: 5 | J34: {=_xlfn.IFS(AND(A34="IN",I34<>""), (E34*F34+G34*H34)+I34*(D34-F34-H34),AND(A34="IN",I34=""), (2*E34*F34)+G34*(D34-2*F34),AND(A34="CJ",F34<>""),(D34*E34)-((D34-2*F34)*(E34-2*F34)),AND(A34="CJ",F34=""),ROUND((PI()*(D34/2)^2)-(PI()*(D34/2-E34)^2),0),TRUE,"")} -> 2900
A35: =CUBICACION!F35 -> CJ | B35: =CUBICACION!E35 -> 200X100X4 | C35: =CUBICACION!J35 -> 4 | D35: {=_xlfn.TEXTSPLIT(B35,{"X";"x"})} -> 200 | E35: 100 | F35: 4 | J35: {=_xlfn.IFS(AND(A35="IN",I35<>""), (E35*F35+G35*H35)+I35*(D35-F35-H35),AND(A35="IN",I35=""), (2*E35*F35)+G35*(D35-2*F35),AND(A35="CJ",F35<>""),(D35*E35)-((D35-2*F35)*(E35-2*F35)),AND(A35="CJ",F35=""),ROUND((PI()*(D35/2)^2)-(PI()*(D35/2-E35)^2),0),TRUE,"")} -> 2336
A36: =CUBICACION!F36 -> CJ | B36: =CUBICACION!E36 -> 200X100X4 | C36: =CUBICACION!J36 -> 4 | D36: {=_xlfn.TEXTSPLIT(B36,{"X";"x"})} -> 200 | E36: 100 | F36: 4 | J36: {=_xlfn.IFS(AND(A36="IN",I36<>""), (E36*F36+G36*H36)+I36*(D36-F36-H36),AND(A36="IN",I36=""), (2*E36*F36)+G36*(D36-2*F36),AND(A36="CJ",F36<>""),(D36*E36)-((D36-2*F36)*(E36-2*F36)),AND(A36="CJ",F36=""),ROUND((PI()*(D36/2)^2)-(PI()*(D36/2-E36)^2),0),TRUE,"")} -> 2336
A37: =CUBICACION!F37 -> CJ | B37: =CUBICACION!E37 -> 200X100X4 | C37: =CUBICACION!J37 -> 4 | D37: {=_xlfn.TEXTSPLIT(B37,{"X";"x"})} -> 200 | E37: 100 | F37: 4 | J37: {=_xlfn.IFS(AND(A37="IN",I37<>""), (E37*F37+G37*H37)+I37*(D37-F37-H37),AND(A37="IN",I37=""), (2*E37*F37)+G37*(D37-2*F37),AND(A37="CJ",F37<>""),(D37*E37)-((D37-2*F37)*(E37-2*F37)),AND(A37="CJ",F37=""),ROUND((PI()*(D37/2)^2)-(PI()*(D37/2-E37)^2),0),TRUE,"")} -> 2336
... A43: =CUBICACION!F43 -> CJ | B43: =CUBICACION!E43 -> 150X150X5 | C43: =CUBICACION!J43 -> 4 | D43: {=_xlfn.TEXTSPLIT(B43,{"X";"x"})} -> 150 | E43: 150 | F43: 5 | J43: {=_xlfn.IFS(AND(A43="IN",I43<>""), (E43*F43+G43*H43)+I43*(D43-F43-H43),AND(A43="IN",I43=""), (2*E43*F43)+G43*(D43-2*F43),AND(A43="CJ",F43<>""),(D43*E43)-((D43-2*F43)*(E43-2*F43)),AND(A43="CJ",F43=""),ROUND((PI()*(D43/2)^2)-(PI()*(D43/2-E43)^2),0),TRUE,"")} -> 2900
A44: =CUBICACION!F44 -> 0 | B44: =CUBICACION!E44 -> 0 | C44: =CUBICACION!J44 -> 4 | D44: {=_xlfn.TEXTSPLIT(B44,{"X";"x"})} -> 0 | J44: {=_xlfn.IFS(AND(A44="IN",I44<>""), (E44*F44+G44*H44)+I44*(D44-F44-H44),AND(A44="IN",I44=""), (2*E44*F44)+G44*(D44-2*F44),AND(A44="CJ",F44<>""),(D44*E44)-((D44-2*F44)*(E44-2*F44)),AND(A44="CJ",F44=""),ROUND((PI()*(D44/2)^2)-(PI()*(D44/2-E44)^2),0),TRUE,"")}
A45: =CUBICACION!F45 -> 0 | B45: =CUBICACION!E45 -> 0 | C45: =CUBICACION!J45 -> 4 | D45: {=_xlfn.TEXTSPLIT(B45,{"X";"x"})} -> 0 | J45: {=_xlfn.IFS(AND(A45="IN",I45<>""), (E45*F45+G45*H45)+I45*(D45-F45-H45),AND(A45="IN",I45=""), (2*E45*F45)+G45*(D45-2*F45),AND(A45="CJ",F45<>""),(D45*E45)-((D45-2*F45)*(E45-2*F45)),AND(A45="CJ",F45=""),ROUND((PI()*(D45/2)^2)-(PI()*(D45/2-E45)^2),0),TRUE,"")}
A46: =CUBICACION!F46 -> C | B46: =CUBICACION!E46 -> 125X50X15X2 | C46: =CUBICACION!J46 -> 3 | D46: {=_xlfn.TEXTSPLIT(B46,{"X";"x"})} -> 125 | E46: 50 | F46: 15 | G46: 2 | J46: {=_xlfn.IFS(AND(A46="IN",I46<>""), (E46*F46+G46*H46)+I46*(D46-F46-H46),AND(A46="IN",I46=""), (2*E46*F46)+G46*(D46-2*F46),AND(A46="CJ",F46<>""),(D46*E46)-((D46-2*F46)*(E46-2*F46)),AND(A46="CJ",F46=""),ROUND((PI()*(D46/2)^2)-(PI()*(D46/2-E46)^2),0),TRUE,"")}
A47: =CUBICACION!F47 -> CJ | B47: =CUBICACION!E47 -> 100X100X3 | C47: =CUBICACION!J47 -> 4 | D47: {=_xlfn.TEXTSPLIT(B47,{"X";"x"})} -> 100 | E47: 100 | F47: 3 | J47: {=_xlfn.IFS(AND(A47="IN",I47<>""), (E47*F47+G47*H47)+I47*(D47-F47-H47),AND(A47="IN",I47=""), (2*E47*F47)+G47*(D47-2*F47),AND(A47="CJ",F47<>""),(D47*E47)-((D47-2*F47)*(E47-2*F47)),AND(A47="CJ",F47=""),ROUND((PI()*(D47/2)^2)-(PI()*(D47/2-E47)^2),0),TRUE,"")} -> 1164
A48: =CUBICACION!F48 -> CJ | B48: =CUBICACION!E48 -> MM 400X200X4 | C48: =CUBICACION!J48 -> 4 | D48: {=_xlfn.TEXTSPLIT(B48,{"X";"x"})} -> MM 400 | E48: 200 | F48: 4 | J48: {=_xlfn.IFS(AND(A48="IN",I48<>""), (E48*F48+G48*H48)+I48*(D48-F48-H48),AND(A48="IN",I48=""), (2*E48*F48)+G48*(D48-2*F48),AND(A48="CJ",F48<>""),(D48*E48)-((D48-2*F48)*(E48-2*F48)),AND(A48="CJ",F48=""),ROUND((PI()*(D48/2)^2)-(PI()*(D48/2-E48)^2),0),TRUE,"")} -> #VALUE!
A49: =CUBICACION!F49 -> CJ | B49: =CUBICACION!E49 -> 150X150X5 | C49: =CUBICACION!J49 -> 4 | D49: {=_xlfn.TEXTSPLIT(B49,{"X";"x"})} -> 150 | E49: 150 | F49: 5 | J49: {=_xlfn.IFS(AND(A49="IN",I49<>""), (E49*F49+G49*H49)+I49*(D49-F49-H49),AND(A49="IN",I49=""), (2*E49*F49)+G49*(D49-2*F49),AND(A49="CJ",F49<>""),(D49*E49)-((D49-2*F49)*(E49-2*F49)),AND(A49="CJ",F49=""),ROUND((PI()*(D49/2)^2)-(PI()*(D49/2-E49)^2),0),TRUE,"")} -> 2900
A50: =CUBICACION!F50 -> CJ | B50: =CUBICACION!E50 -> 200X100X8,5X5,6 | C50: =CUBICACION!J50 -> 3 | D50: {=_xlfn.TEXTSPLIT(B50,{"X";"x"})} -> 200 | E50: 100 | F50: 8,5 | G50: 5,6 | J50: {=_xlfn.IFS(AND(A50="IN",I50<>""), (E50*F50+G50*H50)+I50*(D50-F50-H50),AND(A50="IN",I50=""), (2*E50*F50)+G50*(D50-2*F50),AND(A50="CJ",F50<>""),(D50*E50)-((D50-2*F50)*(E50-2*F50)),AND(A50="CJ",F50=""),ROUND((PI()*(D50/2)^2)-(PI()*(D50/2-E50)^2),0),TRUE,"")} -> 4811
A51: =CUBICACION!F51 -> CJ | B51: =CUBICACION!E51 -> 100X100X3 | C51: =CUBICACION!J51 -> 4 | D51: {=_xlfn.TEXTSPLIT(B51,{"X";"x"})} -> 100 | E51: 100 | F51: 3 | J51: {=_xlfn.IFS(AND(A51="IN",I51<>""), (E51*F51+G51*H51)+I51*(D51-F51-H51),AND(A51="IN",I51=""), (2*E51*F51)+G51*(D51-2*F51),AND(A51="CJ",F51<>""),(D51*E51)-((D51-2*F51)*(E51-2*F51)),AND(A51="CJ",F51=""),ROUND((PI()*(D51/2)^2)-(PI()*(D51/2-E51)^2),0),TRUE,"")} -> 1164
A52: =CUBICACION!F52 -> CJ | B52: =CUBICACION!E52 -> 200X100X4 | C52: =CUBICACION!J52 -> 4 | D52: {=_xlfn.TEXTSPLIT(B52,{"X";"x"})} -> 200 | E52: 100 | F52: 4 | J52: {=_xlfn.IFS(AND(A52="IN",I52<>""), (E52*F52+G52*H52)+I52*(D52-F52-H52),AND(A52="IN",I52=""), (2*E52*F52)+G52*(D52-2*F52),AND(A52="CJ",F52<>""),(D52*E52)-((D52-2*F52)*(E52-2*F52)),AND(A52="CJ",F52=""),ROUND((PI()*(D52/2)^2)-(PI()*(D52/2-E52)^2),0),TRUE,"")} -> 2336
A53: =CUBICACION!F53 -> CJ | B53: =CUBICACION!I53 -> 3400 | C53: =CUBICACION!J53 -> 4 | D53: {=_xlfn.TEXTSPLIT(B53,{"X";"x"})} -> 3400 | J53: {=_xlfn.IFS(AND(A53="IN",I53<>""), (E53*F53+G53*H53)+I53*(D53-F53-H53),AND(A53="IN",I53=""), (2*E53*F53)+G53*(D53-2*F53),AND(A53="CJ",F53<>""),(D53*E53)-((D53-2*F53)*(E53-2*F53)),AND(A53="CJ",F53=""),ROUND((PI()*(D53/2)^2)-(PI()*(D53/2-E53)^2),0),TRUE,"")} -> 0
A54: =CUBICACION!F54 -> CJ | B54: =CUBICACION!E54 -> 100X100X3 | C54: =CUBICACION!J54 -> 4 | D54: {=_xlfn.TEXTSPLIT(B54,{"X";"x"})} -> 100 | E54: 100 | F54: 3 | J54: {=_xlfn.IFS(AND(A54="IN",I54<>""), (E54*F54+G54*H54)+I54*(D54-F54-H54),AND(A54="IN",I54=""), (2*E54*F54)+G54*(D54-2*F54),AND(A54="CJ",F54<>""),(D54*E54)-((D54-2*F54)*(E54-2*F54)),AND(A54="CJ",F54=""),ROUND((PI()*(D54/2)^2)-(PI()*(D54/2-E54)^2),0),TRUE,"")} -> 1164
A55: =CUBICACION!F55 -> CJ | B55: =CUBICACION!E55 -> 100X100X3 | C55: =CUBICACION!J55 -> 4 | D55: {=_xlfn.TEXTSPLIT(B55,{"X";"x"})} -> 100 | E55: 100 | F55: 3 | J55: {=_xlfn.IFS(AND(A55="IN",I55<>""), (E55*F55+G55*H55)+I55*(D55-F55-H55),AND(A55="IN",I55=""), (2*E55*F55)+G55*(D55-2*F55),AND(A55="CJ",F55<>""),(D55*E55)-((D55-2*F55)*(E55-2*F55)),AND(A55="CJ",F55=""),ROUND((PI()*(D55/2)^2)-(PI()*(D55/2-E55)^2),0),TRUE,"")} -> 1164
A56: =CUBICACION!F56 -> CJ | B56: =CUBICACION!E56 -> 100X100X3 | C56: =CUBICACION!J56 -> 4 | D56: {=_xlfn.TEXTSPLIT(B56,{"X";"x"})} -> 100 | E56: 100 | F56: 3 | J56: {=_xlfn.IFS(AND(A56="IN",I56<>""), (E56*F56+G56*H56)+I56*(D56-F56-H56),AND(A56="IN",I56=""), (2*E56*F56)+G56*(D56-2*F56),AND(A56="CJ",F56<>""),(D56*E56)-((D56-2*F56)*(E56-2*F56)),AND(A56="CJ",F56=""),ROUND((PI()*(D56/2)^2)-(PI()*(D56/2-E56)^2),0),TRUE,"")} -> 1164
A57: =CUBICACION!F57 -> CJ | B57: =CUBICACION!E57 -> 100X100X3 | C57: =CUBICACION!J57 -> 4 | D57: {=_xlfn.TEXTSPLIT(B57,{"X";"x"})} -> 100 | E57: 100 | F57: 3 | J57: {=_xlfn.IFS(AND(A57="IN",I57<>""), (E57*F57+G57*H57)+I57*(D57-F57-H57),AND(A57="IN",I57=""), (2*E57*F57)+G57*(D57-2*F57),AND(A57="CJ",F57<>""),(D57*E57)-((D57-2*F57)*(E57-2*F57)),AND(A57="CJ",F57=""),ROUND((PI()*(D57/2)^2)-(PI()*(D57/2-E57)^2),0),TRUE,"")} -> 1164
A58: =CUBICACION!F58 -> CJ | B58: =CUBICACION!E58 -> MM 400X200X4 | C58: =CUBICACION!J58 -> 4 | D58: {=_xlfn.TEXTSPLIT(B58,{"X";"x"})} -> MM 400 | E58: 200 | F58: 4 | J58: {=_xlfn.IFS(AND(A58="IN",I58<>""), (E58*F58+G58*H58)+I58*(D58-F58-H58),AND(A58="IN",I58=""), (2*E58*F58)+G58*(D58-2*F58),AND(A58="CJ",F58<>""),(D58*E58)-((D58-2*F58)*(E58-2*F58)),AND(A58="CJ",F58=""),ROUND((PI()*(D58/2)^2)-(PI()*(D58/2-E58)^2),0),TRUE,"")} -> #VALUE!
A59: =CUBICACION!F59 -> CJ | B59: =CUBICACION!E59 -> 100X100X3 | C59: =CUBICACION!J59 -> 4 | D59: {=_xlfn.TEXTSPLIT(B59,{"X";"x"})} -> 100 | E59: 100 | F59: 3 | J59: {=_xlfn.IFS(AND(A59="IN",I59<>""), (E59*F59+G59*H59)+I59*(D59-F59-H59),AND(A59="IN",I59=""), (2*E59*F59)+G59*(D59-2*F59),AND(A59="CJ",F59<>""),(D59*E59)-((D59-2*F59)*(E59-2*F59)),AND(A59="CJ",F59=""),ROUND((PI()*(D59/2)^2)-(PI()*(D59/2-E59)^2),0),TRUE,"")} -> 1164
A60: =CUBICACION!F60 -> CJ | B60: =CUBICACION!E60 -> 200X100X8,5X5,6 | C60: =CUBICACION!J60 -> 3 | D60: {=_xlfn.TEXTSPLIT(B60,{"X";"x"})} -> 200 | E60: 100 | F60: 8,5 | G60: 5,6 | J60: {=_xlfn.IFS(AND(A60="IN",I60<>""), (E60*F60+G60*H60)+I60*(D60-F60-H60),AND(A60="IN",I60=""), (2*E60*F60)+G60*(D60-2*F60),AND(A60="CJ",F60<>""),(D60*E60)-((D60-2*F60)*(E60-2*F60)),AND(A60="CJ",F60=""),ROUND((PI()*(D60/2)^2)-(PI()*(D60/2-E60)^2),0),TRUE,"")} -> 4811
A61: =CUBICACION!F61 -> CJ | B61: =CUBICACION!E61 -> 150X150X5 | C61: =CUBICACION!J61 -> 4 | D61: {=_xlfn.TEXTSPLIT(B61,{"X";"x"})} -> 150 | E61: 150 | F61: 5 | J61: {=_xlfn.IFS(AND(A61="IN",I61<>""), (E61*F61+G61*H61)+I61*(D61-F61-H61),AND(A61="IN",I61=""), (2*E61*F61)+G61*(D61-2*F61),AND(A61="CJ",F61<>""),(D61*E61)-((D61-2*F61)*(E61-2*F61)),AND(A61="CJ",F61=""),ROUND((PI()*(D61/2)^2)-(PI()*(D61/2-E61)^2),0),TRUE,"")} -> 2900
A62: =CUBICACION!F62 -> CJ | B62: =CUBICACION!E62 -> 100X100X3 | C62: =CUBICACION!J62 -> 4 | D62: {=_xlfn.TEXTSPLIT(B62,{"X";"x"})} -> 100 | E62: 100 | F62: 3 | J62: {=_xlfn.IFS(AND(A62="IN",I62<>""), (E62*F62+G62*H62)+I62*(D62-F62-H62),AND(A62="IN",I62=""), (2*E62*F62)+G62*(D62-2*F62),AND(A62="CJ",F62<>""),(D62*E62)-((D62-2*F62)*(E62-2*F62)),AND(A62="CJ",F62=""),ROUND((PI()*(D62/2)^2)-(PI()*(D62/2-E62)^2),0),TRUE,"")} -> 1164
A63: =CUBICACION!F63 -> CJ | B63: =CUBICACION!E63 -> 100X100X3 | C63: =CUBICACION!J63 -> 4 | D63: {=_xlfn.TEXTSPLIT(B63,{"X";"x"})} -> 100 | E63: 100 | F63: 3 | J63: {=_xlfn.IFS(AND(A63="IN",I63<>""), (E63*F63+G63*H63)+I63*(D63-F63-H63),AND(A63="IN",I63=""), (2*E63*F63)+G63*(D63-2*F63),AND(A63="CJ",F63<>""),(D63*E63)-((D63-2*F63)*(E63-2*F63)),AND(A63="CJ",F63=""),ROUND((PI()*(D63/2)^2)-(PI()*(D63/2-E63)^2),0),TRUE,"")} -> 1164
A64: =CUBICACION!F64 -> CJ | B64: =CUBICACION!E64 -> 100X100X3 | C64: =CUBICACION!J64 -> 4 | D64: {=_xlfn.TEXTSPLIT(B64,{"X";"x"})} -> 100 | E64: 100 | F64: 3 | J64: {=_xlfn.IFS(AND(A64="IN",I64<>""), (E64*F64+G64*H64)+I64*(D64-F64-H64),AND(A64="IN",I64=""), (2*E64*F64)+G64*(D64-2*F64),AND(A64="CJ",F64<>""),(D64*E64)-((D64-2*F64)*(E64-2*F64)),AND(A64="CJ",F64=""),ROUND((PI()*(D64/2)^2)-(PI()*(D64/2-E64)^2),0),TRUE,"")} -> 1164
A65: =CUBICACION!F65 -> CJ | B65: =CUBICACION!E65 -> 100X100X3 | C65: =CUBICACION!J65 -> 4 | D65: {=_xlfn.TEXTSPLIT(B65,{"X";"x"})} -> 100 | E65: 100 | F65: 3 | J65: {=_xlfn.IFS(AND(A65="IN",I65<>""), (E65*F65+G65*H65)+I65*(D65-F65-H65),AND(A65="IN",I65=""), (2*E65*F65)+G65*(D65-2*F65),AND(A65="CJ",F65<>""),(D65*E65)-((D65-2*F65)*(E65-2*F65)),AND(A65="CJ",F65=""),ROUND((PI()*(D65/2)^2)-(PI()*(D65/2-E65)^2),0),TRUE,"")} -> 1164
A66: =CUBICACION!F66 -> CJ | B66: =CUBICACION!E66 -> MM 400X200X4 | C66: =CUBICACION!J66 -> 4 | D66: {=_xlfn.TEXTSPLIT(B66,{"X";"x"})} -> MM 400 | E66: 200 | F66: 4 | J66: {=_xlfn.IFS(AND(A66="IN",I66<>""), (E66*F66+G66*H66)+I66*(D66-F66-H66),AND(A66="IN",I66=""), (2*E66*F66)+G66*(D66-2*F66),AND(A66="CJ",F66<>""),(D66*E66)-((D66-2*F66)*(E66-2*F66)),AND(A66="CJ",F66=""),ROUND((PI()*(D66/2)^2)-(PI()*(D66/2-E66)^2),0),TRUE,"")} -> #VALUE!
A67: =CUBICACION!F67 -> CJ | B67: =CUBICACION!E67 -> 100X100X3 | C67: =CUBICACION!J67 -> 4 | D67: {=_xlfn.TEXTSPLIT(B67,{"X";"x"})} -> 100 | E67: 100 | F67: 3 | J67: {=_xlfn.IFS(AND(A67="IN",I67<>""), (E67*F67+G67*H67)+I67*(D67-F67-H67),AND(A67="IN",I67=""), (2*E67*F67)+G67*(D67-2*F67),AND(A67="CJ",F67<>""),(D67*E67)-((D67-2*F67)*(E67-2*F67)),AND(A67="CJ",F67=""),ROUND((PI()*(D67/2)^2)-(PI()*(D67/2-E67)^2),0),TRUE,"")} -> 1164
A68: =CUBICACION!F68 -> CJ | B68: =CUBICACION!E68 -> 200X100X4 | C68: =CUBICACION!J68 -> 4 | D68: {=_xlfn.TEXTSPLIT(B68,{"X";"x"})} -> 200 | E68: 100 | F68: 4 | J68: {=_xlfn.IFS(AND(A68="IN",I68<>""), (E68*F68+G68*H68)+I68*(D68-F68-H68),AND(A68="IN",I68=""), (2*E68*F68)+G68*(D68-2*F68),AND(A68="CJ",F68<>""),(D68*E68)-((D68-2*F68)*(E68-2*F68)),AND(A68="CJ",F68=""),ROUND((PI()*(D68/2)^2)-(PI()*(D68/2-E68)^2),0),TRUE,"")} -> 2336
A69: =CUBICACION!F69 -> CJ | B69: =CUBICACION!E69 -> 100X100X3 | C69: =CUBICACION!J69 -> 4 | D69: {=_xlfn.TEXTSPLIT(B69,{"X";"x"})} -> 100 | E69: 100 | F69: 3 | J69: {=_xlfn.IFS(AND(A69="IN",I69<>""), (E69*F69+G69*H69)+I69*(D69-F69-H69),AND(A69="IN",I69=""), (2*E69*F69)+G69*(D69-2*F69),AND(A69="CJ",F69<>""),(D69*E69)-((D69-2*F69)*(E69-2*F69)),AND(A69="CJ",F69=""),ROUND((PI()*(D69/2)^2)-(PI()*(D69/2-E69)^2),0),TRUE,"")} -> 1164
A70: =CUBICACION!F70 -> CJ | B70: =CUBICACION!E70 -> 100X100X3 | C70: =CUBICACION!J70 -> 4 | D70: {=_xlfn.TEXTSPLIT(B70,{"X";"x"})} -> 100 | E70: 100 | F70: 3 | J70: {=_xlfn.IFS(AND(A70="IN",I70<>""), (E70*F70+G70*H70)+I70*(D70-F70-H70),AND(A70="IN",I70=""), (2*E70*F70)+G70*(D70-2*F70),AND(A70="CJ",F70<>""),(D70*E70)-((D70-2*F70)*(E70-2*F70)),AND(A70="CJ",F70=""),ROUND((PI()*(D70/2)^2)-(PI()*(D70/2-E70)^2),0),TRUE,"")} -> 1164
A71: =CUBICACION!F71 -> CJ | B71: =CUBICACION!E71 -> M1 MM400X200X4 | C71: =CUBICACION!J71 -> 4 | D71: {=_xlfn.TEXTSPLIT(B71,{"X";"x"})} -> M1 MM400 | E71: 200 | F71: 4 | J71: {=_xlfn.IFS(AND(A71="IN",I71<>""), (E71*F71+G71*H71)+I71*(D71-F71-H71),AND(A71="IN",I71=""), (2*E71*F71)+G71*(D71-2*F71),AND(A71="CJ",F71<>""),(D71*E71)-((D71-2*F71)*(E71-2*F71)),AND(A71="CJ",F71=""),ROUND((PI()*(D71/2)^2)-(PI()*(D71/2-E71)^2),0),TRUE,"")} -> #VALUE!
A72: =CUBICACION!F72 -> CJ | B72: =CUBICACION!E72 -> 200X100X4 | C72: =CUBICACION!J72 -> 4 | D72: {=_xlfn.TEXTSPLIT(B72,{"X";"x"})} -> 200 | E72: 100 | F72: 4 | J72: {=_xlfn.IFS(AND(A72="IN",I72<>""), (E72*F72+G72*H72)+I72*(D72-F72-H72),AND(A72="IN",I72=""), (2*E72*F72)+G72*(D72-2*F72),AND(A72="CJ",F72<>""),(D72*E72)-((D72-2*F72)*(E72-2*F72)),AND(A72="CJ",F72=""),ROUND((PI()*(D72/2)^2)-(PI()*(D72/2-E72)^2),0),TRUE,"")} -> 2336
... A79: =CUBICACION!F79 -> CJ | B79: =CUBICACION!E79 -> 150X150X5 | C79: =CUBICACION!J79 -> 4 | D79: {=_xlfn.TEXTSPLIT(B79,{"X";"x"})} -> 150 | E79: 150 | F79: 5 | J79: {=_xlfn.IFS(AND(A79="IN",I79<>""), (E79*F79+G79*H79)+I79*(D79-F79-H79),AND(A79="IN",I79=""), (2*E79*F79)+G79*(D79-2*F79),AND(A79="CJ",F79<>""),(D79*E79)-((D79-2*F79)*(E79-2*F79)),AND(A79="CJ",F79=""),ROUND((PI()*(D79/2)^2)-(PI()*(D79/2-E79)^2),0),TRUE,"")} -> 2900
A80: =CUBICACION!F80 -> IN | B80: =CUBICACION!E80 -> 240X120X9,8X6,2 | C80: =CUBICACION!J80 -> 3 | D80: {=_xlfn.TEXTSPLIT(B80,{"X";"x"})} -> 240 | E80: 120 | F80: 9,8 | G80: 6,2 | J80: {=_xlfn.IFS(AND(A80="IN",I80<>""), (E80*F80+G80*H80)+I80*(D80-F80-H80),AND(A80="IN",I80=""), (2*E80*F80)+G80*(D80-2*F80),AND(A80="CJ",F80<>""),(D80*E80)-((D80-2*F80)*(E80-2*F80)),AND(A80="CJ",F80=""),ROUND((PI()*(D80/2)^2)-(PI()*(D80/2-E80)^2),0),TRUE,"")} -> 3718.48
A81: =CUBICACION!F81 -> CJ | B81: =CUBICACION!E81 -> 150X150X5 | C81: =CUBICACION!J81 -> 4 | D81: {=_xlfn.TEXTSPLIT(B81,{"X";"x"})} -> 150 | E81: 150 | F81: 5 | J81: {=_xlfn.IFS(AND(A81="IN",I81<>""), (E81*F81+G81*H81)+I81*(D81-F81-H81),AND(A81="IN",I81=""), (2*E81*F81)+G81*(D81-2*F81),AND(A81="CJ",F81<>""),(D81*E81)-((D81-2*F81)*(E81-2*F81)),AND(A81="CJ",F81=""),ROUND((PI()*(D81/2)^2)-(PI()*(D81/2-E81)^2),0),TRUE,"")} -> 2900
A82: =CUBICACION!F82 -> IN | B82: =CUBICACION!E82 -> 240X120X9,8X6,2 | C82: =CUBICACION!J82 -> 3 | D82: {=_xlfn.TEXTSPLIT(B82,{"X";"x"})} -> 240 | E82: 120 | F82: 9,8 | G82: 6,2 | J82: {=_xlfn.IFS(AND(A82="IN",I82<>""), (E82*F82+G82*H82)+I82*(D82-F82-H82),AND(A82="IN",I82=""), (2*E82*F82)+G82*(D82-2*F82),AND(A82="CJ",F82<>""),(D82*E82)-((D82-2*F82)*(E82-2*F82)),AND(A82="CJ",F82=""),ROUND((PI()*(D82/2)^2)-(PI()*(D82/2-E82)^2),0),TRUE,"")} -> 3718.48
A83: =CUBICACION!F83 -> CJ | B83: =CUBICACION!E83 -> 100X100X3 | C83: =CUBICACION!J83 -> 4 | D83: {=_xlfn.TEXTSPLIT(B83,{"X";"x"})} -> 100 | E83: 100 | F83: 3 | J83: {=_xlfn.IFS(AND(A83="IN",I83<>""), (E83*F83+G83*H83)+I83*(D83-F83-H83),AND(A83="IN",I83=""), (2*E83*F83)+G83*(D83-2*F83),AND(A83="CJ",F83<>""),(D83*E83)-((D83-2*F83)*(E83-2*F83)),AND(A83="CJ",F83=""),ROUND((PI()*(D83/2)^2)-(PI()*(D83/2-E83)^2),0),TRUE,"")} -> 1164
A84: =CUBICACION!F84 -> CJ | B84: =CUBICACION!E84 -> 150X150X5 | C84: =CUBICACION!J84 -> 4 | D84: {=_xlfn.TEXTSPLIT(B84,{"X";"x"})} -> 150 | E84: 150 | F84: 5 | J84: {=_xlfn.IFS(AND(A84="IN",I84<>""), (E84*F84+G84*H84)+I84*(D84-F84-H84),AND(A84="IN",I84=""), (2*E84*F84)+G84*(D84-2*F84),AND(A84="CJ",F84<>""),(D84*E84)-((D84-2*F84)*(E84-2*F84)),AND(A84="CJ",F84=""),ROUND((PI()*(D84/2)^2)-(PI()*(D84/2-E84)^2),0),TRUE,"")} -> 2900
A85: =CUBICACION!F85 -> IN | B85: =CUBICACION!E85 -> 240X120X9,8X6,2 | C85: =CUBICACION!J85 -> 3 | D85: {=_xlfn.TEXTSPLIT(B85,{"X";"x"})} -> 240 | E85: 120 | F85: 9,8 | G85: 6,2 | J85: {=_xlfn.IFS(AND(A85="IN",I85<>""), (E85*F85+G85*H85)+I85*(D85-F85-H85),AND(A85="IN",I85=""), (2*E85*F85)+G85*(D85-2*F85),AND(A85="CJ",F85<>""),(D85*E85)-((D85-2*F85)*(E85-2*F85)),AND(A85="CJ",F85=""),ROUND((PI()*(D85/2)^2)-(PI()*(D85/2-E85)^2),0),TRUE,"")} -> 3718.48
A86: =CUBICACION!F86 -> CJ | B86: =CUBICACION!E86 -> 150X150X5 | C86: =CUBICACION!J86 -> 4 | D86: {=_xlfn.TEXTSPLIT(B86,{"X";"x"})} -> 150 | E86: 150 | F86: 5 | J86: {=_xlfn.IFS(AND(A86="IN",I86<>""), (E86*F86+G86*H86)+I86*(D86-F86-H86),AND(A86="IN",I86=""), (2*E86*F86)+G86*(D86-2*F86),AND(A86="CJ",F86<>""),(D86*E86)-((D86-2*F86)*(E86-2*F86)),AND(A86="CJ",F86=""),ROUND((PI()*(D86/2)^2)-(PI()*(D86/2-E86)^2),0),TRUE,"")} -> 2900
A87: =CUBICACION!F87 -> IN | B87: =CUBICACION!E87 -> 240X120X9,8X6,2 | C87: =CUBICACION!J87 -> 3 | D87: {=_xlfn.TEXTSPLIT(B87,{"X";"x"})} -> 240 | E87: 120 | F87: 9,8 | G87: 6,2 | J87: {=_xlfn.IFS(AND(A87="IN",I87<>""), (E87*F87+G87*H87)+I87*(D87-F87-H87),AND(A87="IN",I87=""), (2*E87*F87)+G87*(D87-2*F87),AND(A87="CJ",F87<>""),(D87*E87)-((D87-2*F87)*(E87-2*F87)),AND(A87="CJ",F87=""),ROUND((PI()*(D87/2)^2)-(PI()*(D87/2-E87)^2),0),TRUE,"")} -> 3718.48
A88: =CUBICACION!F88 -> CJ | B88: =CUBICACION!E88 -> 100X100X3 | C88: =CUBICACION!J88 -> 4 | D88: {=_xlfn.TEXTSPLIT(B88,{"X";"x"})} -> 100 | E88: 100 | F88: 3 | J88: {=_xlfn.IFS(AND(A88="IN",I88<>""), (E88*F88+G88*H88)+I88*(D88-F88-H88),AND(A88="IN",I88=""), (2*E88*F88)+G88*(D88-2*F88),AND(A88="CJ",F88<>""),(D88*E88)-((D88-2*F88)*(E88-2*F88)),AND(A88="CJ",F88=""),ROUND((PI()*(D88/2)^2)-(PI()*(D88/2-E88)^2),0),TRUE,"")} -> 1164
A89: =CUBICACION!F89 -> CJ | B89: =CUBICACION!E89 -> 100X100X3 | C89: =CUBICACION!J89 -> 4 | D89: {=_xlfn.TEXTSPLIT(B89,{"X";"x"})} -> 100 | E89: 100 | F89: 3 | J89: {=_xlfn.IFS(AND(A89="IN",I89<>""), (E89*F89+G89*H89)+I89*(D89-F89-H89),AND(A89="IN",I89=""), (2*E89*F89)+G89*(D89-2*F89),AND(A89="CJ",F89<>""),(D89*E89)-((D89-2*F89)*(E89-2*F89)),AND(A89="CJ",F89=""),ROUND((PI()*(D89/2)^2)-(PI()*(D89/2-E89)^2),0),TRUE,"")} -> 1164
A90: =CUBICACION!F90 -> CJ | B90: =CUBICACION!E90 -> 100X100X3 | C90: =CUBICACION!J90 -> 4 | D90: {=_xlfn.TEXTSPLIT(B90,{"X";"x"})} -> 100 | E90: 100 | F90: 3 | J90: {=_xlfn.IFS(AND(A90="IN",I90<>""), (E90*F90+G90*H90)+I90*(D90-F90-H90),AND(A90="IN",I90=""), (2*E90*F90)+G90*(D90-2*F90),AND(A90="CJ",F90<>""),(D90*E90)-((D90-2*F90)*(E90-2*F90)),AND(A90="CJ",F90=""),ROUND((PI()*(D90/2)^2)-(PI()*(D90/2-E90)^2),0),TRUE,"")} -> 1164
